Workbook
Name ASD: #REF!
Name ASD: #REF!
Name ASD: #REF!
Name ASD: #REF!
Name asdfsdf: #REF!
Name asdfsdf: #REF!
Name asdfsdf: #REF!
Name asdfsdf: #REF!
Name asdfsdf: #REF!
Name asdfsdf: #REF!
Name asdfsdf: #REF!
Name sdfsdf: #REF!
Name sdfsdf: #REF!
Name sdfsdf: #REF!
Name sdfsdf: #REF!
Name sdfsdf: #REF!
Name sdfsdf: #REF!
Name sdfsdf: #REF!

Sheet Annexure-I
A1: SL NO | B1: INDENT PART NO | C1: DESCRIPTION | D1: INDENT QTY | E1: Revised INDENT QTY | F1: Ref Unit Basic Price (USD) | G1: REF SA | H1: Ref. SA DATE | I1: Price Level | J1: EST Unit Price (USD) @ 2024 level | K1: Levelled EST Unit Price (Rs) @ 2024 level | L1: LLP REF SA Price | M1: LLP REF SA | N1: LLP REF SA Date | O1: Price Level | P1: LLP EST Unit Price (USD) @ 2024 level | Q1: Levelled LPP Unit Price (Rs) @ 2024 level | R1: Currency
A2: 1 | B2: X1 | C2: OPERATIONAL AMPLIFIER | D2: 7 | E2: 7 | F2: 11 | G2: CONTRACT-A1 | H2: 43298 | I2: 2018 | J2: 14.83 | K2: 1623.4145 | R2: USD
A3: 2 | B3: X2 | C3: MICROCIRCUIT OF KOPYO RADAR | D3: 38 | E3: 38 | F3: 16.16 | G3: CONTRACT-A2 | H3: 40967 | I3: 2012 | J3: 29.61 | K3: 3241.3555 | R3: USD
A4: 3 | B4: X3 | C4: IC (Integrated Circuit ) | D4: 12 | E4: 12 | F4: 22 | G4: CONTRACT-A3 | H4: 43298 | I4: 2018 | J4: 29.65 | K4: 3245.7343 | R4: USD
A5: 4 | B5: X4 | C5: MICROCIRCUIT | D5: 10 | E5: 10 | F5: 7.93 | G5: CONTRACT-A4 | H5: 40967 | I5: 2012 | J5: 14.53 | K5: 1590.574 | R5: USD
A6: 5 | B6: X5 | C6: IC (Integrated Circuit ) | D6: 9 | E6: 9 | F6: 14 | G6: CONTRACT-A5 | H6: 43298 | I6: 2018 | J6: 18.87 | K6: 2065.6663 | R6: USD
A7: 6 | B7: X6 | C7: DIODE | D7: 11 | E7: 11 | F7: 12.02 | G7: CONTRACT-A6 | H7: 41789 | I7: 2014 | J7: 19.79 | K7: 2166.3771 | R7: USD
A8: 7 | B8: X7 | C8: TRANSISTOR | D8: 6 | E8: 6 | F8: 280 | G8: CONTRACT-A7 | H8: 44760 | I8: 2022 | J8: 309.29 | K8: 364.9622 | R8: INR
A9: 8 | B9: X8 | C9: TRANSISTOR | D9: 16 | E9: 16 | F9: 57.75 | G9: CONTRACT-A8 | H9: 40724 | I9: 2011 | J9: 111.94 | K9: 12253.878 | R9: USD
A10: 9 | B10: X9 | C10: TRANSISTOR | D10: 17 | E10: 17 | F10: 6 | G10: CONTRACT-A9 | H10: 43298 | I10: 2018 | J10: 8.09 | K10: 885.59832 | R10: USD
A11: 10 | B11: X10 | C11: IC (Integrated Circuit ) | D11: 30 | E11: 30 | F11: 18.81 | G11: CONTRACT-A10 | H11: 41891 | I11: 2014 | J11: 30.96 | K11: 3389.1377 | R11: USD
A12: 11 | B12: X11 | C12: MOSFET | D12: 4 | E12: 4 | F12: 46 | G12: CONTRACT-A11 | H12: 43298 | I12: 2018 | J12: 62 | K12: 6787.0329 | R12: USD
A13: 12 | B13: X12 | C13: IC (Integrated Circuit ) | D13: 12 | E13: 12 | F13: 12 | G13: CONTRACT-A12 | H13: 43298 | I13: 2018 | J13: 16.17 | K13: 1770.102 | R13: USD
... A28: 27 | B28: X27 | C28: FUSE HOLDER | D28: 121 | E28: 121 | F28: 7.03 | G28: CONTRACT-A27 | H28: 41789 | I28: 2014 | J28: 11.57 | K28: 1266.5479 | R28: USD
A29: 28 | B29: X28 | C29: HIGH VOLTAGE SEALENT | D29: 15 | E29: 15 | F29: 29.97 | G29: CONTRACT-A28 | H29: 29-12-2015 | I29: 2015 | J29: 46.89 | K29: 5132.9673 | R29: USD
A30: 29 | B30: X29 | C30: ELECTRIC TIMER | D30: 3 | E30: 3 | F30: 822.53 | G30: CONTRACT-A29 | H30: 40967 | I30: 2012 | J30: 1506.94 | K30: 164962.12 | R30: USD
A31: 30 | B31: X30 | C31: UNIT 08-11 UFTI / FORMER | D31: 4 | E31: 4 | F31: 35494.03 | G31: CONTRACT-A30 | H31: 40967 | I31: 2012 | J31: 65027.94 | K31: 7118496.2 | R31: USD
A32: 31 | B32: X31 | C32: CAPACITOR | D32: 10 | E32: 10 | F32: 7.34 | G32: CONTRACT-A31 | H32: 40967 | I32: 2012 | J32: 13.45 | K32: 1472.3483 | R32: USD
A33: 32 | B33: X32 | C33: CAPACITOR | D33: 20 | E33: 20 | F33: 4.26 | G33: CONTRACT-A32 | H33: 40966 | I33: 2012 | J33: 7.8 | K33: 853.85252 | R33: USD
A34: 33 | B34: X33 | C34: CAPACITOR | D34: 110 | E34: 110 | F34: 6.65 | G34: CONTRACT-A33 | H34: 30-06-2017 | I34: 2017 | J34: 9.42 | K34: 1031.1911 | R34: USD
A35: 34 | B35: X34 | C35: CAPACITOR | D35: 131 | E35: 131 | F35: 12.63 | G35: CONTRACT-A34 | H35: 24-12-2018 | I35: 2018 | J35: 17.02 | K35: 1863.15 | R35: USD
A36: 35 | B36: X35 | C36: CAPACITOR | D36: 10 | E36: 10 | F36: 92.28 | G36: CONTRACT-A35 | H36: 29-12-2015 | I36: 2015 | J36: 144.39 | K36: 15806.124 | R36: USD
A37: 36 | B37: X36 | C37: CAPACITOR | D37: 28 | E37: 28 | F37: 74.91 | G37: CONTRACT-A36 | H37: 40967 | I37: 2012 | J37: 137.24 | K37: 15023.426 | R37: USD
A38: 37 | B38: X37 | C38: FRAME | D38: 5 | E38: 5 | F38: 9217.05 | G38: CONTRACT-A37 | H38: 40967 | I38: 2012 | J38: 16886.38 | K38: 1848522.8 | R38: USD
A39: 38 | B39: X38 | C39: CONTACTOR | D39: 12 | E39: 12 | F39: 1891.45 | G39: CONTRACT-A38 | H39: 40967 | I39: 2012 | J39: 3465.29 | K39: 379339.31 | R39: USD
A40: 39 | B40: X39 | C40: ARTICLE CONDOR-1 | D40: 4 | E40: 4 | F40: 96734.05 | G40: CONTRACT-A39 | H40: 41789 | I40: 2014 | J40: 159228.04 | K40: 17430418 | R40: USD
A41: 40 | B41: X40 | C41: TRUBKA PICTURE TUBE OF MFD | D41: 5 | E41: 5 | F41: 16818.44 | G41: CONTRACT-A40 | H41: 41789 | I41: 2014 | J41: 27683.81 | K41: 3030498.8 | R41: USD
A42: 41 | B42: X41 | C42: MICROSWITCH | D42: 20 | E42: 20 | F42: 80.29 | G42: CONTRACT-A41 | H42: 40967 | I42: 2012 | J42: 147.1 | K42: 16102.783 | R42: USD
A43: 42 | B43: X42 | C43: SWITCH | D43: 8 | E43: 8 | F43: 147.61 | G43: CONTRACT-A42 | H43: 40967 | I43: 2012 | J43: 270.43 | K43: 29603.505 | R43: USD
A44: 43 | B44: X43 | C44: SWITCH | D44: 8 | E44: 8 | F44: 240.88 | G44: CONTRACT-A43 | H44: 40967 | I44: 2012 | J44: 441.31 | K44: 48309.443 | R44: USD
A45: 44 | B45: X44 | C45: RELAY RS4.569.435-04.01 RS0.459.006 TU | D45: 5 | E45: 5 | F45: 217.1 | G45: CONTRACT-A44 | H45: 41789 | I45: 2014 | J45: 357.36 | K45: 39119.582 | R45: USD
A46: 45 | B46: X45 | C46: BACKELITE CONNECTOR | D46: 10 | E46: 10 | F46: 13.93 | G46: CONTRACT-A45 | H46: 29-12-2015 | I46: 2015 | J46: 21.8 | K46: 2386.4083 | R46: USD
A47: 46 | B47: X46 | C47: CABLE | D47: 10 | E47: 10 | F47: 179.59 | G47: CONTRACT-A46 | H47: 40967 | I47: 2012 | J47: 329.02 | K47: 36017.251 | R47: USD
A48: 47 | B48: X47 | C48: CABLE | D48: 9 | E48: 9 | F48: 179.59 | G48: CONTRACT-A47 | H48: 40967 | I48: 2012 | J48: 329.02 | K48: 36017.251 | R48: USD
A49: 48 | B49: X48 | C49: RESISTOR | D49: 14 | E49: 14 | F49: 3.91 | G49: CONTRACT-A48 | H49: 39386 | I49: 2007 | J49: 8.95 | K49: 979.74103 | R49: USD
A50: 49 | B50: X49 | C50: RESISTOR | D50: 22 | E50: 22 | F50: 0.41 | G50: CONTRACT-A49 | H50: 39386 | I50: 2007 | J50: 0.94 | K50: 102.90018 | R50: USD
A51: 50 | B51: X50 | C51: RESISTOR | D51: 31 | E51: 31 | F51: 1.75 | G51: CONTRACT-A50 | H51: 29-12-2015 | I51: 2015 | J51: 2.74 | K51: 299.94307 | R51: USD
A52: 51 | B52: X51 | C52: RESISTOR | D52: 5 | E52: 5 | F52: 20.26 | G52: CONTRACT-A51 | H52: 29-12-2015 | I52: 2015 | J52: 31.7 | K52: 3470.1442 | R52: USD
A53: 52 | B53: X52 | C53: UNIT PICTURE TUBE | D53: 3 | E53: 3 | F53: 19948 | G53: CONTRACT-A52 | H53: 41789 | I53: 2014 | J53: 32835.19 | K53: 3594411.5 | R53: USD
A54: 53 | B54: X53 | C54: PIN | D54: 5 | E54: 5 | F54: 414.87 | G54: CONTRACT-A53 | H54: 29-12-2015 | I54: 2015 | J54: 649.14 | K54: 71060.234 | R54: USD
A55: 54 | B55: X54 | C55: RUBBER PART | D55: 16 | E55: 16 | F55: 819.87 | G55: CONTRACT-A54 | H55: 29-12-2015 | I55: 2015 | J55: 1282.83 | K55: 140429.18 | R55: USD
A56: 55 | B56: X55 | C56: P1 CIRCUIT | D56: 7 | E56: 7 | F56: 473.38 | G56: CONTRACT-A55 | H56: 42944 | I56: 2017 | J56: 670.55 | K56: 73403.95 | R56: USD
A57: 56 | B57: X56 | C57: PLATE P-1 | D57: 5 | E57: 5 | F57: 1468.85 | G57: CONTRACT-A56 | H57: 41789 | I57: 2014 | J57: 2417.78 | K57: 264670.2 | R57: USD
A58: 57 | B58: X57 | C58: PLATE P-2 | D58: 5 | E58: 5 | F58: 1468.85 | G58: CONTRACT-A57 | H58: 41789 | I58: 2014 | J58: 2417.78 | K58: 264670.2 | R58: USD
A59: 58 | B59: X58 | C59: Wave Guide Addaptor | D59: 5 | E59: 5 | F59: 148.77 | G59: CONTRACT-A58 | H59: 42944 | I59: 2017 | J59: 210.73 | K59: 23068.249 | R59: USD
A60: 59 | B60: X59 | C60: BACKELITE COVER | D60: 10 | E60: 10 | F60: 1061.47 | G60: CONTRACT-A59 | H60: 40967 | I60: 2012 | J60: 1944.7 | K60: 212882.95 | R60: USD
A61: 60 | B61: X60 | C61: PIPE | D61: 7 | E61: 7 | F61: 174.15 | G61: CONTRACT-A60 | H61: 40967 | I61: 2012 | J61: 319.06 | K61: 34926.947 | R61: USD
A62: 61 | B62: X61 | C62: TRAVELING WAVETUBE | D62: 11 | E62: 11 | F62: 47224.06 | G62: CONTRACT-A61 | H62: 41789 | I62: 2014 | J62: 77732.66 | K62: 8509260 | R62: USD
A63: 62 | B63: X62 | C63: HIGH VOLTAGE RECTIFIER | D63: 5 | E63: 5 | F63: 8835.44 | G63: CONTRACT-A62 | H63: 40967 | I63: 2012 | J63: 16187.24 | K63: 1771989.2 | R63: USD
A64: 63 | B64: X63 | C64: UNIT 08-01 TSG | D64: 4 | E64: 4 | F64: 16917.42 | G64: CONTRACT-A63 | H64: 41789 | I64: 2014 | J64: 27846.74 | K64: 3048334.5 | R64: USD
A65: 64 | B65: X64 | C65: UNIT 08-07 US / UNIT | D65: 4 | E65: 4 | F65: 16957.4 | G65: CONTRACT-A64 | H65: 41789 | I65: 2014 | J65: 27912.55 | K65: 3055538.6 | R65: USD
A66: 65 | B66: X65 | C66: UNIT 08-03 UF / UNIT | D66: 4 | E66: 4 | F66: 16858.41 | G66: CONTRACT-A65 | H66: 41789 | I66: 2014 | J66: 27749.6 | K66: 3037700.8 | R66: USD
A67: 66 | B67: X66 | C67: UNIT 08-04 MOD NKN / MODULATOR | D67: 5 | E67: 5 | F67: 16782.25 | G67: CONTRACT-A66 | H67: 41789 | I67: 2014 | J67: 27624.24 | K67: 3023977.8 | R67: USD
... A77: 76 | B77: X76 | C77: PRESSURE ADAPTER | D77: 3 | E77: 3 | F77: 6293.93 | G77: CONTRACT-A76 | H77: 40967 | I77: 2012 | J77: 11530.99 | K77: 1262277.5 | R77: USD
A78: 77 | B78: X77 | C78: CUP WASHER | D78: 11 | E78: 11 | F78: 14.89 | G78: CONTRACT-A77 | H78: 28-07-2017 | I78: 2017 | J78: 21.09 | K78: 2308.6859 | R78: USD
A79: 78 | B79: X78 | C79: CONTACT PACKING | D79: 20 | E79: 20 | F79: 46.18 | G79: CONTRACT-A78 | H79: 40967 | I79: 2012 | J79: 84.61 | K79: 9262.1105 | R79: USD
A80: 79 | B80: X79 | C80: GASKET | D80: 16 | E80: 16 | F80: 19.09 | G80: CONTRACT-A79 | H80: 40967 | I80: 2012 | J80: 34.97 | K80: 3828.1055 | R80: USD
A81: 80 | B81: X80 | C81: ARTICLE DOCTOR | D81: 4 | E81: 4 | F81: 23941.76 | G81: CONTRACT-A80 | H81: 41789 | I81: 2014 | J81: 39409.08 | K81: 4314043.9 | R81: USD
A82: 81 | B82: X81 | C82: MAGNET AMPLIFIER | D82: 5 | E82: 5 | F82: 12393.83 | G82: CONTRACT-A81 | H82: 39196 | I82: 2014 | J82: 20400.73 | K82: 2233232.7 | R82: USD
A83: 82 | B83: X82 | C83: Bushing | D83: 6 | E83: 6 | F83: 56.66 | G83: CONTRACT-A82 | H83: 40967 | I83: 2012 | J83: 103.81 | K83: 11363.901 | R83: USD
A84: 83 | B84: X83 | C84: Collet | D84: 9 | E84: 0 | F84: 311.05 | G84: CONTRACT-A83 | H84: 40967 | I84: 2012 | J84: 569.87 | K84: 62382.684 | R84: USD
A85: 84 | B85: X84 | C85: Handle | D85: 9 | E85: 0 | F85: 233.29 | G85: CONTRACT-A84 | H85: 40967 | I85: 2012 | J85: 427.41 | K85: 46787.834 | R85: USD
A86: 85 | B86: X85 | C86: SCREW | D86: 10 | E86: 10 | F86: 1.1 | G86: CONTRACT-A85 | H86: 39386 | I86: 2007 | J86: 2.52 | K86: 275.86005 | R86: USD

Sheet Form
A1: Stage | B1: E No | C1: HEADING
A2: RFQ | C2: Indent NO | D2: abcd001 | E2: Price Recoverability | F2: Expenditure is fully recoverable in accordance with GOI, MOD letter No. Air HQ/95357/71/09-10/NSK/Fin P/AF/US(S)/D(Air-IV(I)/14 dated 12.09.2014, as applicable for BOI supplies against RMSO..
A3: RFQ | C3: Indent Date | D3: 45073
A4: RFQ | C4: File number | D4: 628
A5: RFQ | C5: Project | D5: MiG/SUROH | E5: Programme details (MFG/ROH/RMSO/ DRE/Others ): | H5: ROH
C6: Fleet | D6: MiG/SUROH | E6: Year provisioned
A7: RFQ | B7: E1 | C7: Type of File | D7: Procurement of BoI Spares & Repair of KOPYO Cards | E7: HAL/NK/MPU-AOD/xyz(208)/23/ dated 01.06.2023
A8: RFQ | C8: Tender Floated on Vendors | D8: 14
A9: RFQ | C9: Tender Opening date | D9: 19.07.2023 | E9: 11.08.2023
A10: TEC | C10: Conversion 1USD = INR | D10: 82.78 | E10: Price Level | F10: 2024
A11: TEC | C11: TEC Letter No
A12: TEC | C12: Reason for deletion of LInes | D12: TEC
C13: Note Sheet | D13: Date
C14: =CONCATENATE("HAL/NK/MPU-AOD/2237(",Form!D4,")/23/107/") -> HAL/NK/MPU-AOD/2237(628)/23/107/ | E14: Vendor | F14: Due Date Ext Letter | G14: Upto | H14: Approved upto
C15: N1 | D15: 44411
A16: DP1 | C16: N2 | D16: 44473
A17: DP2 | C17: N3
C18: N4
C19: N5
C20: N6
C21: N7
C22: N8
C23: N9
C24: N10
D25: ='CST-Calculation'!H3 -> Avi. Equip. | E25: ='CST-Calculation'!P3 -> GIS | F25: ='CST-Calculation'!T3 -> IASL | G25: ='CST-Calculation'!L3 -> Avitronic | H25: ='CST-Calculation'!X3 -> AEC | I25: ='CST-Calculation'!AB3 -> ADRYS | J25: ='CST-Calculation'!AF3 -> AZP | K25: ='CST-Calculation'!AJ3 -> EST | L25: ='CST-Calculation'!AN3 -> NASC | M25: ='CST-Calculation'!AR3 -> ROE | N25: ='CST-Calculation'!AV3 -> VEKS-M | O25: ='CST-Calculation'!AZ3 -> VSMPO | P25: ='CST-Calculation'!BD3 -> TDK
C26: =SUM(IF(D26<>"",1,0),IF(E26<>"",1,0),IF(F26<>"",1,0),IF(G26<>"",1,0),IF(H26<>"",1,0),IF(I26<>"",1,0),IF(J26<>"",1,0),IF(K26<>"",1,0),IF(L26<>"",1,0),IF(M26<>"",1,0),IF(N26<>"",1,0)) -> 4 | D26: =IF(SUM('CST-Calculation'!H5:H2129)>0,'CST-Calculation'!G2,"") | E26: =IF(SUM('CST-Calculation'!P5:P2129)>0,'CST-Calculation'!O2,"") -> GIS | F26: =IF(SUM('CST-Calculation'!T5:T2129)>0,'CST-Calculation'!S2,"") -> INDO AVIA SERVICES LTD | G26: =IF(SUM('CST-Calculation'!L5:L2129)>0,'CST-Calculation'!K2,"") | H26: =IF(SUM('CST-Calculation'!X5:X2129)>0,'CST-Calculation'!W2,"") | I26: =IF(SUM('CST-Calculation'!AB5:AB2129)>0,'CST-Calculation'!AA2,"") -> ADRYS Technologies (ADRYS) | J26: =IF(SUM('CST-Calculation'!AF5:AF2129)>0,'CST-Calculation'!AE2,"") | K26: =IF(SUM('CST-Calculation'!AJ5:AJ2129)>0,'CST-Calculation'!AI2,"") -> Eurasia Special Technologies (EST) | L26: =IF(SUM('CST-Calculation'!AN5:AN2129)>0,'CST-Calculation'!AM2,"") | M26: =IF(SUM('CST-Calculation'!AR5:AR2129)>0,'CST-Calculation'!AQ2,"") | N26: =IF(SUM('CST-Calculation'!AV5:AV2129)>0,'CST-Calculation'!AU2,"") | O26: =IF(SUM('CST-Calculation'!AW5:AW2129)>0,'CST-Calculation'!AV2,"") | P26: =IF(SUM('CST-Calculation'!AX5:AX2129)>0,'CST-Calculation'!AW2,"")
A27: CST | C27: Comm Offer Letter No. | D27: ASC/HAL/092/23 | E27: 94/08-356 In | F27: IASL/205(NK)/2023-24/0723001/095 | I27: ADTS/QUOTE/0720/HAL/IN-123001/23 | J27: 825/RM-27286 | K27: Email
A28: CST | C28: Comm Offer Date | D28: 45146 | E28: 45146 | F28: 45147 | I28: 45127 | J28: 45145 | K28: 10.08.2023
A29: CST | C29: Comm Offer Validity | D29: 90 days | E29: 45291 | F29: 60 days | I29: Offer is valid for 120 days from the closing date of enquiry. | J29: 45231 | K29: 180 days from Tender opening Date
A30: CST | C30: Delivery Schedule | D30: 12 months from the date of signing of contract. | E30: 12 months from the date of signing of contract. | F30: Within 16 months from the date of placement of order & EUC. | I30: 52-60 weeks from the date of receipt of PO. | J30: Within 09 months from the date of signing the contract. | K30: Within 365 days from the date of Purchase order
A31: CST | C31: Payment term | D31: 100% DBT in equivalent RUB. | E31: - | F31: 80% within 30 days of receipt. Remaining 20% after acceptance but within 45 days of receipt | I31: 100% payment within 30 days from the date of supply & acceptance. | J31: 100% DBT in equivalent RUB. | K31: 100% payment within 30 days of date of delivery
A32: TO | C32: Tender Due Extension request letter
A33: TO | C33: Tender Extension request letter upto
A34: PNC | C34: Non Deputation letter with date
A35: PNC | C35: Negotiation Date
A36: PP | C36: Purchase proposal No. (PP No)
A37: PP | C37: Draft Contract No
A38: PP | C38: Draft Contract Date
A39: PP | C39: Draft Contract Forwarding Letter No
A40: PP | C40: DC Forwarding Letter Date
A41: PP | C41: Bottom line Discount % (if Any)
C42: Negotiation approval notesheet
C43: Country | D43: Russia | E43: Bulgaria | F43: INDIA | G43: Russia | H43: Russia | I43: INDIA | J43: Russia | K43: India | L43: Russia | M43: Russia | N43: Russia | O43: Russia | P43: Russia

Sheet CST-Calculation
A1: =CONCATENATE("Price Comparision Statement Against Indent ",Form!D2) -> Price Comparision Statement Against Indent abcd001
A2: RFQ DETAILS | G2: Aviation Equipment | K2: Avitronic Ltd, Russia | O2: GIS | S2: INDO AVIA SERVICES LTD | W2: AEC (AEC) | AA2: ADRYS Technologies (ADRYS) | AE2: AVIAZAPCHAST (AZP) | AI2: Eurasia Special Technologies (EST) | AM2: NASC (NASC) | AQ2: ROE (ROE) | AU2: VEKS-M | AY2: VSMPO (VSMPO) | BC2: Tecnodinamika (TDK) | BG2: L1 DETAILS | BJ2: ESTIMATION DETAILS | BN2: PRICE ANALYSIS
H3: Avi. Equip. | L3: Avitronic | P3: GIS | T3: IASL | X3: AEC | AB3: ADRYS | AF3: AZP | AJ3: EST | AN3: NASC | AR3: ROE | AV3: VEKS-M | AZ3: VSMPO | BD3: TDK
A4: Sl No | B4: IND. Sl. No. | C4: PART NO | D4: DESCRIPTION | E4: QTY | F4: Revised | G4: QTY | H4: Unit Price (USD) | J4: Total Price (USD) | K4: QTY | L4: Unit Price (USD) | N4: Total Price (USD) | O4: QTY | P4: Unit Price (USD) | R4: Total Price (USD) | S4: QTY | T4: Unit Price (USD) | V4: Total Price (USD) | W4: QTY | X4: Unit Price (USD) | Z4: Total Price (USD) | AA4: QTY | AB4: Unit Price (INR) | AD4: Total Price (INR) | AE4: QTY | AF4: Unit Price (USD) | AH4: Total Price (USD) | AI4: QTY | AJ4: Unit Price (INR) | AL4: Total Price (USD) | AM4: QTY | AN4: Unit Price (USD) | AP4: Total Price (USD) | AQ4: QTY | AR4: Unit Price (USD) | AT4: Total Price (USD) | AU4: QTY | AV4: VEKSM Unit Price (USD) | AX4: Total Price (USD) | AY4: QTY | AZ4: VEKSM Unit Price (USD) | BB4: Total Price (USD) | BC4: QTY | BD4: VEKSM Unit Price (USD) | BF4: Total Price (USD) | BG4: L1 AGENCY | BH4: OFFER TYPE | BI4: Total L1 PRICE (USD) | BJ4: REF Unit Price (USD) | BK4: REF SA | BL4: REF SA Date | BM4: EST Unit Basic Price (USD) @ 2024 level | BN4: L1 TOTAL BASIC VAL (USD) @ 2024 level | BO4: EST.TOTAL BASIC VAL (USD) @ 2024 level | BP4: Offered Price w.r.t Est Price (in%) | BQ4: Remarks
A5: 1 | B5: 1 | C5: X1 | D5: OPERATIONAL AMPLIFIER | E5: 7 | F5: 7 | O5: 7 | P5: 15.9 | R5: =IF(P5="TEC Rejected","",IF(P5="","",P5*IF(O5="",$E5,O5))) -> 111.3 | S5: 7 | T5: 27.5 | V5: =IF(T5="TEC Rejected","",IF(T5="","",T5*IF(S5="",$E5,S5))) -> 192.5 | Z5: =IF(X5="TEC Rejected","",IF(X5="","",X5*IF(W5="",$E5,W5))) | AA5: 7 | AB5: 915 | AD5: =IF(AB5="TEC Rejected","",IF(AB5="","",AB5*IF(AA5="",$E5,AA5))) -> 6405 | AH5: =IF(AF5="TEC Rejected","",IF(AF5="","",AF5*IF(AE5="",$E5,AE5))) | AL5: =IF(AJ5="TEC Rejected","",IF(AJ5="","",AJ5*IF(AI5="",$E5,AI5))) | AP5: =IF(AN5="TEC Rejected","",IF(AN5="","",AN5*IF(AM5="",$E5,AM5))) | AT5: =IF(AR5="TEC Rejected","",IF(AR5="","",AR5*IF(AQ5="",$E5,AQ5))) | AX5: =IF(AV5="TEC Rejected","",IF(AV5="","",AV5*IF(AU5="",$E5,AU5))) | BB5: =IF(AZ5="TEC Rejected","",IF(AZ5="","",AZ5*IF(AY5="",$E5,AY5))) | BF5: =IF(BD5="TEC Rejected","",IF(BD5="","",BD5*IF(BC5="",$E5,BC5)))
A6: 2 | B6: 2 | C6: X2 | D6: MICROCIRCUIT OF KOPYO RADAR | E6: 38 | F6: 38 | O6: 38 | P6: 17.1 | R6: =IF(P6="TEC Rejected","",IF(P6="","",P6*IF(O6="",$E6,O6))) -> 649.8 | S6: 38 | T6: 27.5 | V6: =IF(T6="TEC Rejected","",IF(T6="","",T6*IF(S6="",$E6,S6))) -> 1045 | Z6: =IF(X6="TEC Rejected","",IF(X6="","",X6*IF(W6="",$E6,W6))) | AA6: 38 | AB6: 915 | AD6: =IF(AB6="TEC Rejected","",IF(AB6="","",AB6*IF(AA6="",$E6,AA6))) -> 34770 | AH6: =IF(AF6="TEC Rejected","",IF(AF6="","",AF6*IF(AE6="",$E6,AE6))) | AL6: =IF(AJ6="TEC Rejected","",IF(AJ6="","",AJ6*IF(AI6="",$E6,AI6))) | AP6: =IF(AN6="TEC Rejected","",IF(AN6="","",AN6*IF(AM6="",$E6,AM6))) | AT6: =IF(AR6="TEC Rejected","",IF(AR6="","",AR6*IF(AQ6="",$E6,AQ6))) | AX6: =IF(AV6="TEC Rejected","",IF(AV6="","",AV6*IF(AU6="",$E6,AU6))) | BB6: =IF(AZ6="TEC Rejected","",IF(AZ6="","",AZ6*IF(AY6="",$E6,AY6))) | BF6: =IF(BD6="TEC Rejected","",IF(BD6="","",BD6*IF(BC6="",$E6,BC6)))
A7: 3 | B7: 3 | C7: X3 | D7: IC (Integrated Circuit ) | E7: 12 | F7: 12 | O7: 12 | P7: 16.5 | R7: =IF(P7="TEC Rejected","",IF(P7="","",P7*IF(O7="",$E7,O7))) -> 198 | S7: 12 | T7: 22 | V7: =IF(T7="TEC Rejected","",IF(T7="","",T7*IF(S7="",$E7,S7))) -> 264 | Z7: =IF(X7="TEC Rejected","",IF(X7="","",X7*IF(W7="",$E7,W7))) | AA7: 12 | AB7: 915 | AD7: =IF(AB7="TEC Rejected","",IF(AB7="","",AB7*IF(AA7="",$E7,AA7))) -> 10980 | AH7: =IF(AF7="TEC Rejected","",IF(AF7="","",AF7*IF(AE7="",$E7,AE7))) | AL7: =IF(AJ7="TEC Rejected","",IF(AJ7="","",AJ7*IF(AI7="",$E7,AI7))) | AP7: =IF(AN7="TEC Rejected","",IF(AN7="","",AN7*IF(AM7="",$E7,AM7))) | AT7: =IF(AR7="TEC Rejected","",IF(AR7="","",AR7*IF(AQ7="",$E7,AQ7))) | AX7: =IF(AV7="TEC Rejected","",IF(AV7="","",AV7*IF(AU7="",$E7,AU7))) | BB7: =IF(AZ7="TEC Rejected","",IF(AZ7="","",AZ7*IF(AY7="",$E7,AY7))) | BF7: =IF(BD7="TEC Rejected","",IF(BD7="","",BD7*IF(BC7="",$E7,BC7)))
A8: 4 | B8: 4 | C8: X4 | D8: MICROCIRCUIT | E8: 10 | F8: 10 | O8: 10 | P8: 12.6 | R8: =IF(P8="TEC Rejected","",IF(P8="","",P8*IF(O8="",$E8,O8))) -> 126 | S8: 10 | T8: 27.5 | V8: =IF(T8="TEC Rejected","",IF(T8="","",T8*IF(S8="",$E8,S8))) -> 275 | Z8: =IF(X8="TEC Rejected","",IF(X8="","",X8*IF(W8="",$E8,W8))) | AA8: 10 | AB8: 1215 | AD8: =IF(AB8="TEC Rejected","",IF(AB8="","",AB8*IF(AA8="",$E8,AA8))) -> 12150 | AH8: =IF(AF8="TEC Rejected","",IF(AF8="","",AF8*IF(AE8="",$E8,AE8))) | AL8: =IF(AJ8="TEC Rejected","",IF(AJ8="","",AJ8*IF(AI8="",$E8,AI8))) | AP8: =IF(AN8="TEC Rejected","",IF(AN8="","",AN8*IF(AM8="",$E8,AM8))) | AT8: =IF(AR8="TEC Rejected","",IF(AR8="","",AR8*IF(AQ8="",$E8,AQ8))) | AX8: =IF(AV8="TEC Rejected","",IF(AV8="","",AV8*IF(AU8="",$E8,AU8))) | BB8: =IF(AZ8="TEC Rejected","",IF(AZ8="","",AZ8*IF(AY8="",$E8,AY8))) | BF8: =IF(BD8="TEC Rejected","",IF(BD8="","",BD8*IF(BC8="",$E8,BC8)))
A9: 5 | B9: 5 | C9: X5 | D9: IC (Integrated Circuit ) | E9: 9 | F9: 9 | O9: 9 | P9: 15 | R9: =IF(P9="TEC Rejected","",IF(P9="","",P9*IF(O9="",$E9,O9))) -> 135 | S9: 9 | T9: 33 | V9: =IF(T9="TEC Rejected","",IF(T9="","",T9*IF(S9="",$E9,S9))) -> 297 | Z9: =IF(X9="TEC Rejected","",IF(X9="","",X9*IF(W9="",$E9,W9))) | AA9: 9 | AB9: 915 | AD9: =IF(AB9="TEC Rejected","",IF(AB9="","",AB9*IF(AA9="",$E9,AA9))) -> 8235 | AH9: =IF(AF9="TEC Rejected","",IF(AF9="","",AF9*IF(AE9="",$E9,AE9))) | AL9: =IF(AJ9="TEC Rejected","",IF(AJ9="","",AJ9*IF(AI9="",$E9,AI9))) | AP9: =IF(AN9="TEC Rejected","",IF(AN9="","",AN9*IF(AM9="",$E9,AM9))) | AT9: =IF(AR9="TEC Rejected","",IF(AR9="","",AR9*IF(AQ9="",$E9,AQ9))) | AX9: =IF(AV9="TEC Rejected","",IF(AV9="","",AV9*IF(AU9="",$E9,AU9))) | BB9: =IF(AZ9="TEC Rejected","",IF(AZ9="","",AZ9*IF(AY9="",$E9,AY9))) | BF9: =IF(BD9="TEC Rejected","",IF(BD9="","",BD9*IF(BC9="",$E9,BC9)))
A10: 6 | B10: 6 | C10: X6 | D10: DIODE | E10: 11 | F10: 11 | O10: 11 | P10: 3 | R10: =IF(P10="TEC Rejected","",IF(P10="","",P10*IF(O10="",$E10,O10))) -> 33 | S10: 11 | T10: 16.5 | V10: =IF(T10="TEC Rejected","",IF(T10="","",T10*IF(S10="",$E10,S10))) -> 181.5 | Z10: =IF(X10="TEC Rejected","",IF(X10="","",X10*IF(W10="",$E10,W10))) | AA10: 11 | AB10: 165 | AD10: =IF(AB10="TEC Rejected","",IF(AB10="","",AB10*IF(AA10="",$E10,AA10))) -> 1815 | AH10: =IF(AF10="TEC Rejected","",IF(AF10="","",AF10*IF(AE10="",$E10,AE10))) | AL10: =IF(AJ10="TEC Rejected","",IF(AJ10="","",AJ10*IF(AI10="",$E10,AI10))) | AP10: =IF(AN10="TEC Rejected","",IF(AN10="","",AN10*IF(AM10="",$E10,AM10))) | AT10: =IF(AR10="TEC Rejected","",IF(AR10="","",AR10*IF(AQ10="",$E10,AQ10))) | AX10: =IF(AV10="TEC Rejected","",IF(AV10="","",AV10*IF(AU10="",$E10,AU10))) | BB10: =IF(AZ10="TEC Rejected","",IF(AZ10="","",AZ10*IF(AY10="",$E10,AY10))) | BF10: =IF(BD10="TEC Rejected","",IF(BD10="","",BD10*IF(BC10="",$E10,BC10)))
A11: 7 | B11: 7 | C11: X7 | D11: TRANSISTOR | E11: 6 | F11: 6 | O11: 6 | P11: 9 | R11: =IF(P11="TEC Rejected","",IF(P11="","",P11*IF(O11="",$E11,O11))) -> 54 | S11: 6 | T11: 19.5 | V11: =IF(T11="TEC Rejected","",IF(T11="","",T11*IF(S11="",$E11,S11))) -> 117 | Z11: =IF(X11="TEC Rejected","",IF(X11="","",X11*IF(W11="",$E11,W11))) | AA11: 6 | AB11: 315 | AD11: =IF(AB11="TEC Rejected","",IF(AB11="","",AB11*IF(AA11="",$E11,AA11))) -> 1890 | AH11: =IF(AF11="TEC Rejected","",IF(AF11="","",AF11*IF(AE11="",$E11,AE11))) | AL11: =IF(AJ11="TEC Rejected","",IF(AJ11="","",AJ11*IF(AI11="",$E11,AI11))) | AP11: =IF(AN11="TEC Rejected","",IF(AN11="","",AN11*IF(AM11="",$E11,AM11))) | AT11: =IF(AR11="TEC Rejected","",IF(AR11="","",AR11*IF(AQ11="",$E11,AQ11))) | AX11: =IF(AV11="TEC Rejected","",IF(AV11="","",AV11*IF(AU11="",$E11,AU11))) | BB11: =IF(AZ11="TEC Rejected","",IF(AZ11="","",AZ11*IF(AY11="",$E11,AY11))) | BF11: =IF(BD11="TEC Rejected","",IF(BD11="","",BD11*IF(BC11="",$E11,BC11)))
A12: 8 | B12: 8 | C12: X8 | D12: TRANSISTOR | E12: 16 | F12: 16 | O12: 16 | P12: 18 | R12: =IF(P12="TEC Rejected","",IF(P12="","",P12*IF(O12="",$E12,O12))) -> 288 | S12: 16 | T12: 39.6 | V12: =IF(T12="TEC Rejected","",IF(T12="","",T12*IF(S12="",$E12,S12))) -> 633.6 | Z12: =IF(X12="TEC Rejected","",IF(X12="","",X12*IF(W12="",$E12,W12))) | AA12: 16 | AB12: 2865 | AD12: =IF(AB12="TEC Rejected","",IF(AB12="","",AB12*IF(AA12="",$E12,AA12))) -> 45840 | AH12: =IF(AF12="TEC Rejected","",IF(AF12="","",AF12*IF(AE12="",$E12,AE12))) | AL12: =IF(AJ12="TEC Rejected","",IF(AJ12="","",AJ12*IF(AI12="",$E12,AI12))) | AP12: =IF(AN12="TEC Rejected","",IF(AN12="","",AN12*IF(AM12="",$E12,AM12))) | AT12: =IF(AR12="TEC Rejected","",IF(AR12="","",AR12*IF(AQ12="",$E12,AQ12))) | AX12: =IF(AV12="TEC Rejected","",IF(AV12="","",AV12*IF(AU12="",$E12,AU12))) | BB12: =IF(AZ12="TEC Rejected","",IF(AZ12="","",AZ12*IF(AY12="",$E12,AY12))) | BF12: =IF(BD12="TEC Rejected","",IF(BD12="","",BD12*IF(BC12="",$E12,BC12)))
A13: 9 | B13: 9 | C13: X9 | D13: TRANSISTOR | E13: 17 | F13: 17 | O13: 17 | P13: 6.6 | R13: =IF(P13="TEC Rejected","",IF(P13="","",P13*IF(O13="",$E13,O13))) -> 112.2 | V13: =IF(T13="TEC Rejected","",IF(T13="","",T13*IF(S13="",$E13,S13))) | Z13: =IF(X13="TEC Rejected","",IF(X13="","",X13*IF(W13="",$E13,W13))) | AA13: 17 | AB13: 465 | AD13: =IF(AB13="TEC Rejected","",IF(AB13="","",AB13*IF(AA13="",$E13,AA13))) -> 7905 | AH13: =IF(AF13="TEC Rejected","",IF(AF13="","",AF13*IF(AE13="",$E13,AE13))) | AL13: =IF(AJ13="TEC Rejected","",IF(AJ13="","",AJ13*IF(AI13="",$E13,AI13))) | AP13: =IF(AN13="TEC Rejected","",IF(AN13="","",AN13*IF(AM13="",$E13,AM13))) | AT13: =IF(AR13="TEC Rejected","",IF(AR13="","",AR13*IF(AQ13="",$E13,AQ13))) | AX13: =IF(AV13="TEC Rejected","",IF(AV13="","",AV13*IF(AU13="",$E13,AU13))) | BB13: =IF(AZ13="TEC Rejected","",IF(AZ13="","",AZ13*IF(AY13="",$E13,AY13))) | BF13: =IF(BD13="TEC Rejected","",IF(BD13="","",BD13*IF(BC13="",$E13,BC13)))
A14: 10 | B14: 10 | C14: X10 | D14: IC (Integrated Circuit ) | E14: 30 | F14: 30 | O14: 30 | P14: 7.5 | R14: =IF(P14="TEC Rejected","",IF(P14="","",P14*IF(O14="",$E14,O14))) -> 225 | S14: 30 | T14: 36 | V14: =IF(T14="TEC Rejected","",IF(T14="","",T14*IF(S14="",$E14,S14))) -> 1080 | Z14: =IF(X14="TEC Rejected","",IF(X14="","",X14*IF(W14="",$E14,W14))) | AA14: 30 | AB14: 1065 | AD14: =IF(AB14="TEC Rejected","",IF(AB14="","",AB14*IF(AA14="",$E14,AA14))) -> 31950 | AH14: =IF(AF14="TEC Rejected","",IF(AF14="","",AF14*IF(AE14="",$E14,AE14))) | AL14: =IF(AJ14="TEC Rejected","",IF(AJ14="","",AJ14*IF(AI14="",$E14,AI14))) | AP14: =IF(AN14="TEC Rejected","",IF(AN14="","",AN14*IF(AM14="",$E14,AM14))) | AT14: =IF(AR14="TEC Rejected","",IF(AR14="","",AR14*IF(AQ14="",$E14,AQ14))) | AX14: =IF(AV14="TEC Rejected","",IF(AV14="","",AV14*IF(AU14="",$E14,AU14))) | BB14: =IF(AZ14="TEC Rejected","",IF(AZ14="","",AZ14*IF(AY14="",$E14,AY14))) | BF14: =IF(BD14="TEC Rejected","",IF(BD14="","",BD14*IF(BC14="",$E14,BC14)))
A15: 11 | B15: 11 | C15: X11 | D15: MOSFET | E15: 4 | F15: 4 | R15: =IF(P15="TEC Rejected","",IF(P15="","",P15*IF(O15="",$E15,O15))) | V15: =IF(T15="TEC Rejected","",IF(T15="","",T15*IF(S15="",$E15,S15))) | Z15: =IF(X15="TEC Rejected","",IF(X15="","",X15*IF(W15="",$E15,W15))) | AD15: =IF(AB15="TEC Rejected","",IF(AB15="","",AB15*IF(AA15="",$E15,AA15))) | AH15: =IF(AF15="TEC Rejected","",IF(AF15="","",AF15*IF(AE15="",$E15,AE15))) | AL15: =IF(AJ15="TEC Rejected","",IF(AJ15="","",AJ15*IF(AI15="",$E15,AI15))) | AP15: =IF(AN15="TEC Rejected","",IF(AN15="","",AN15*IF(AM15="",$E15,AM15))) | AT15: =IF(AR15="TEC Rejected","",IF(AR15="","",AR15*IF(AQ15="",$E15,AQ15))) | AX15: =IF(AV15="TEC Rejected","",IF(AV15="","",AV15*IF(AU15="",$E15,AU15))) | BB15: =IF(AZ15="TEC Rejected","",IF(AZ15="","",AZ15*IF(AY15="",$E15,AY15))) | BF15: =IF(BD15="TEC Rejected","",IF(BD15="","",BD15*IF(BC15="",$E15,BC15)))
A16: 12 | B16: 12 | C16: X12 | D16: IC (Integrated Circuit ) | E16: 12 | F16: 12 | O16: 12 | P16: 9 | R16: =IF(P16="TEC Rejected","",IF(P16="","",P16*IF(O16="",$E16,O16))) -> 108 | S16: 12 | T16: 29.7 | V16: =IF(T16="TEC Rejected","",IF(T16="","",T16*IF(S16="",$E16,S16))) -> 356.4 | Z16: =IF(X16="TEC Rejected","",IF(X16="","",X16*IF(W16="",$E16,W16))) | AA16: 12 | AB16: 765 | AD16: =IF(AB16="TEC Rejected","",IF(AB16="","",AB16*IF(AA16="",$E16,AA16))) -> 9180 | AH16: =IF(AF16="TEC Rejected","",IF(AF16="","",AF16*IF(AE16="",$E16,AE16))) | AL16: =IF(AJ16="TEC Rejected","",IF(AJ16="","",AJ16*IF(AI16="",$E16,AI16))) | AP16: =IF(AN16="TEC Rejected","",IF(AN16="","",AN16*IF(AM16="",$E16,AM16))) | AT16: =IF(AR16="TEC Rejected","",IF(AR16="","",AR16*IF(AQ16="",$E16,AQ16))) | AX16: =IF(AV16="TEC Rejected","",IF(AV16="","",AV16*IF(AU16="",$E16,AU16))) | BB16: =IF(AZ16="TEC Rejected","",IF(AZ16="","",AZ16*IF(AY16="",$E16,AY16))) | BF16: =IF(BD16="TEC Rejected","",IF(BD16="","",BD16*IF(BC16="",$E16,BC16)))
A17: 13 | B17: 13 | C17: X13 | D17: IC (Integrated Circuit ) | E17: 4 | F17: 4 | O17: 4 | P17: 8.1 | R17: =IF(P17="TEC Rejected","",IF(P17="","",P17*IF(O17="",$E17,O17))) -> 32.4 | S17: 4 | T17: 24 | V17: =IF(T17="TEC Rejected","",IF(T17="","",T17*IF(S17="",$E17,S17))) -> 96 | Z17: =IF(X17="TEC Rejected","",IF(X17="","",X17*IF(W17="",$E17,W17))) | AA17: 4 | AB17: 765 | AD17: =IF(AB17="TEC Rejected","",IF(AB17="","",AB17*IF(AA17="",$E17,AA17))) -> 3060 | AH17: =IF(AF17="TEC Rejected","",IF(AF17="","",AF17*IF(AE17="",$E17,AE17))) | AL17: =IF(AJ17="TEC Rejected","",IF(AJ17="","",AJ17*IF(AI17="",$E17,AI17))) | AP17: =IF(AN17="TEC Rejected","",IF(AN17="","",AN17*IF(AM17="",$E17,AM17))) | AT17: =IF(AR17="TEC Rejected","",IF(AR17="","",AR17*IF(AQ17="",$E17,AQ17))) | AX17: =IF(AV17="TEC Rejected","",IF(AV17="","",AV17*IF(AU17="",$E17,AU17))) | BB17: =IF(AZ17="TEC Rejected","",IF(AZ17="","",AZ17*IF(AY17="",$E17,AY17))) | BF17: =IF(BD17="TEC Rejected","",IF(BD17="","",BD17*IF(BC17="",$E17,BC17)))
A18: 14 | B18: 14 | C18: X14 | D18: IC (Integrated Circuit ) | E18: 10 | F18: 10 | O18: 10 | P18: 6 | R18: =IF(P18="TEC Rejected","",IF(P18="","",P18*IF(O18="",$E18,O18))) -> 60 | S18: 10 | T18: 24 | V18: =IF(T18="TEC Rejected","",IF(T18="","",T18*IF(S18="",$E18,S18))) -> 240 | Z18: =IF(X18="TEC Rejected","",IF(X18="","",X18*IF(W18="",$E18,W18))) | AA18: 10 | AB18: 765 | AD18: =IF(AB18="TEC Rejected","",IF(AB18="","",AB18*IF(AA18="",$E18,AA18))) -> 7650 | AH18: =IF(AF18="TEC Rejected","",IF(AF18="","",AF18*IF(AE18="",$E18,AE18))) | AL18: =IF(AJ18="TEC Rejected","",IF(AJ18="","",AJ18*IF(AI18="",$E18,AI18))) | AP18: =IF(AN18="TEC Rejected","",IF(AN18="","",AN18*IF(AM18="",$E18,AM18))) | AT18: =IF(AR18="TEC Rejected","",IF(AR18="","",AR18*IF(AQ18="",$E18,AQ18))) | AX18: =IF(AV18="TEC Rejected","",IF(AV18="","",AV18*IF(AU18="",$E18,AU18))) | BB18: =IF(AZ18="TEC Rejected","",IF(AZ18="","",AZ18*IF(AY18="",$E18,AY18))) | BF18: =IF(BD18="TEC Rejected","",IF(BD18="","",BD18*IF(BC18="",$E18,BC18)))
A19: 15 | B19: 15 | C19: X15 | D19: IC (Integrated Circuit ) | E19: 20 | F19: 20 | O19: 20 | P19: 6.6 | R19: =IF(P19="TEC Rejected","",IF(P19="","",P19*IF(O19="",$E19,O19))) -> 132 | S19: 20 | T19: 22 | V19: =IF(T19="TEC Rejected","",IF(T19="","",T19*IF(S19="",$E19,S19))) -> 440 | Z19: =IF(X19="TEC Rejected","",IF(X19="","",X19*IF(W19="",$E19,W19))) | AA19: 20 | AB19: 765 | AD19: =IF(AB19="TEC Rejected","",IF(AB19="","",AB19*IF(AA19="",$E19,AA19))) -> 15300 | AH19: =IF(AF19="TEC Rejected","",IF(AF19="","",AF19*IF(AE19="",$E19,AE19))) | AL19: =IF(AJ19="TEC Rejected","",IF(AJ19="","",AJ19*IF(AI19="",$E19,AI19))) | AP19: =IF(AN19="TEC Rejected","",IF(AN19="","",AN19*IF(AM19="",$E19,AM19))) | AT19: =IF(AR19="TEC Rejected","",IF(AR19="","",AR19*IF(AQ19="",$E19,AQ19))) | AX19: =IF(AV19="TEC Rejected","",IF(AV19="","",AV19*IF(AU19="",$E19,AU19))) | BB19: =IF(AZ19="TEC Rejected","",IF(AZ19="","",AZ19*IF(AY19="",$E19,AY19))) | BF19: =IF(BD19="TEC Rejected","",IF(BD19="","",BD19*IF(BC19="",$E19,BC19)))
A20: 16 | B20: 16 | C20: X16 | D20: IC (Integrated Circuit ) | E20: 15 | F20: 15 | O20: 15 | P20: 88 | R20: =IF(P20="TEC Rejected","",IF(P20="","",P20*IF(O20="",$E20,O20))) -> 1320 | S20: 15 | T20: 42 | V20: =IF(T20="TEC Rejected","",IF(T20="","",T20*IF(S20="",$E20,S20))) -> 630 | Z20: =IF(X20="TEC Rejected","",IF(X20="","",X20*IF(W20="",$E20,W20))) | AA20: 15 | AB20: 2265 | AD20: =IF(AB20="TEC Rejected","",IF(AB20="","",AB20*IF(AA20="",$E20,AA20))) -> 33975 | AH20: =IF(AF20="TEC Rejected","",IF(AF20="","",AF20*IF(AE20="",$E20,AE20))) | AL20: =IF(AJ20="TEC Rejected","",IF(AJ20="","",AJ20*IF(AI20="",$E20,AI20))) | AP20: =IF(AN20="TEC Rejected","",IF(AN20="","",AN20*IF(AM20="",$E20,AM20))) | AT20: =IF(AR20="TEC Rejected","",IF(AR20="","",AR20*IF(AQ20="",$E20,AQ20))) | AX20: =IF(AV20="TEC Rejected","",IF(AV20="","",AV20*IF(AU20="",$E20,AU20))) | BB20: =IF(AZ20="TEC Rejected","",IF(AZ20="","",AZ20*IF(AY20="",$E20,AY20))) | BF20: =IF(BD20="TEC Rejected","",IF(BD20="","",BD20*IF(BC20="",$E20,BC20)))
A21: 17 | B21: 17 | C21: X17 | D21: IC (Integrated Circuit ) | E21: 34 | F21: 34 | O21: 34 | P21: 15 | R21: =IF(P21="TEC Rejected","",IF(P21="","",P21*IF(O21="",$E21,O21))) -> 510 | S21: 34 | T21: 24 | V21: =IF(T21="TEC Rejected","",IF(T21="","",T21*IF(S21="",$E21,S21))) -> 816 | Z21: =IF(X21="TEC Rejected","",IF(X21="","",X21*IF(W21="",$E21,W21))) | AA21: 34 | AB21: 1215 | AD21: =IF(AB21="TEC Rejected","",IF(AB21="","",AB21*IF(AA21="",$E21,AA21))) -> 41310 | AH21: =IF(AF21="TEC Rejected","",IF(AF21="","",AF21*IF(AE21="",$E21,AE21))) | AL21: =IF(AJ21="TEC Rejected","",IF(AJ21="","",AJ21*IF(AI21="",$E21,AI21))) | AP21: =IF(AN21="TEC Rejected","",IF(AN21="","",AN21*IF(AM21="",$E21,AM21))) | AT21: =IF(AR21="TEC Rejected","",IF(AR21="","",AR21*IF(AQ21="",$E21,AQ21))) | AX21: =IF(AV21="TEC Rejected","",IF(AV21="","",AV21*IF(AU21="",$E21,AU21))) | BB21: =IF(AZ21="TEC Rejected","",IF(AZ21="","",AZ21*IF(AY21="",$E21,AY21))) | BF21: =IF(BD21="TEC Rejected","",IF(BD21="","",BD21*IF(BC21="",$E21,BC21)))
A22: 18 | B22: 18 | C22: X18 | D22: IC (Integrated Circuit ) | E22: 11 | F22: 11 | R22: =IF(P22="TEC Rejected","",IF(P22="","",P22*IF(O22="",$E22,O22))) | V22: =IF(T22="TEC Rejected","",IF(T22="","",T22*IF(S22="",$E22,S22))) | Z22: =IF(X22="TEC Rejected","",IF(X22="","",X22*IF(W22="",$E22,W22))) | AD22: =IF(AB22="TEC Rejected","",IF(AB22="","",AB22*IF(AA22="",$E22,AA22))) | AH22: =IF(AF22="TEC Rejected","",IF(AF22="","",AF22*IF(AE22="",$E22,AE22))) | AL22: =IF(AJ22="TEC Rejected","",IF(AJ22="","",AJ22*IF(AI22="",$E22,AI22))) | AP22: =IF(AN22="TEC Rejected","",IF(AN22="","",AN22*IF(AM22="",$E22,AM22))) | AT22: =IF(AR22="TEC Rejected","",IF(AR22="","",AR22*IF(AQ22="",$E22,AQ22))) | AX22: =IF(AV22="TEC Rejected","",IF(AV22="","",AV22*IF(AU22="",$E22,AU22))) | BB22: =IF(AZ22="TEC Rejected","",IF(AZ22="","",AZ22*IF(AY22="",$E22,AY22))) | BF22: =IF(BD22="TEC Rejected","",IF(BD22="","",BD22*IF(BC22="",$E22,BC22)))
A23: 19 | B23: 19 | C23: X19 | D23: CIRCUIT BREAKER | E23: 13 | F23: 13 | O23: 13 | P23: 450 | R23: =IF(P23="TEC Rejected","",IF(P23="","",P23*IF(O23="",$E23,O23))) -> 5850 | S23: 13 | T23: 377 | V23: =IF(T23="TEC Rejected","",IF(T23="","",T23*IF(S23="",$E23,S23))) -> 4901 | Z23: =IF(X23="TEC Rejected","",IF(X23="","",X23*IF(W23="",$E23,W23))) | AA23: 13 | AB23: 7365 | AD23: =IF(AB23="TEC Rejected","",IF(AB23="","",AB23*IF(AA23="",$E23,AA23))) -> 95745 | AH23: =IF(AF23="TEC Rejected","",IF(AF23="","",AF23*IF(AE23="",$E23,AE23))) | AI23: 13 | AJ23: 20750 | AL23: =IF(AJ23="TEC Rejected","",IF(AJ23="","",AJ23*IF(AI23="",$E23,AI23))) -> 269750 | AP23: =IF(AN23="TEC Rejected","",IF(AN23="","",AN23*IF(AM23="",$E23,AM23))) | AT23: =IF(AR23="TEC Rejected","",IF(AR23="","",AR23*IF(AQ23="",$E23,AQ23))) | AX23: =IF(AV23="TEC Rejected","",IF(AV23="","",AV23*IF(AU23="",$E23,AU23))) | BB23: =IF(AZ23="TEC Rejected","",IF(AZ23="","",AZ23*IF(AY23="",$E23,AY23))) | BF23: =IF(BD23="TEC Rejected","",IF(BD23="","",BD23*IF(BC23="",$E23,BC23)))
A24: 20 | B24: 20 | C24: X20 | D24: COLLIMATOR HEAD KG-3R-4M2 | E24: 4 | F24: 4 | R24: =IF(P24="TEC Rejected","",IF(P24="","",P24*IF(O24="",$E24,O24))) | V24: =IF(T24="TEC Rejected","",IF(T24="","",T24*IF(S24="",$E24,S24))) | Z24: =IF(X24="TEC Rejected","",IF(X24="","",X24*IF(W24="",$E24,W24))) | AD24: =IF(AB24="TEC Rejected","",IF(AB24="","",AB24*IF(AA24="",$E24,AA24))) | AH24: =IF(AF24="TEC Rejected","",IF(AF24="","",AF24*IF(AE24="",$E24,AE24))) | AL24: =IF(AJ24="TEC Rejected","",IF(AJ24="","",AJ24*IF(AI24="",$E24,AI24))) | AP24: =IF(AN24="TEC Rejected","",IF(AN24="","",AN24*IF(AM24="",$E24,AM24))) | AT24: =IF(AR24="TEC Rejected","",IF(AR24="","",AR24*IF(AQ24="",$E24,AQ24))) | AX24: =IF(AV24="TEC Rejected","",IF(AV24="","",AV24*IF(AU24="",$E24,AU24))) | BB24: =IF(AZ24="TEC Rejected","",IF(AZ24="","",AZ24*IF(AY24="",$E24,AY24))) | BF24: =IF(BD24="TEC Rejected","",IF(BD24="","",BD24*IF(BC24="",$E24,BC24)))
A25: 21 | B25: 21 | C25: X21 | D25: 27V LAMP FOR RET ASSIY | E25: 9 | F25: 9 | R25: =IF(P25="TEC Rejected","",IF(P25="","",P25*IF(O25="",$E25,O25))) | V25: =IF(T25="TEC Rejected","",IF(T25="","",T25*IF(S25="",$E25,S25))) | Z25: =IF(X25="TEC Rejected","",IF(X25="","",X25*IF(W25="",$E25,W25))) | AD25: =IF(AB25="TEC Rejected","",IF(AB25="","",AB25*IF(AA25="",$E25,AA25))) | AH25: =IF(AF25="TEC Rejected","",IF(AF25="","",AF25*IF(AE25="",$E25,AE25))) | AL25: =IF(AJ25="TEC Rejected","",IF(AJ25="","",AJ25*IF(AI25="",$E25,AI25))) | AP25: =IF(AN25="TEC Rejected","",IF(AN25="","",AN25*IF(AM25="",$E25,AM25))) | AT25: =IF(AR25="TEC Rejected","",IF(AR25="","",AR25*IF(AQ25="",$E25,AQ25))) | AX25: =IF(AV25="TEC Rejected","",IF(AV25="","",AV25*IF(AU25="",$E25,AU25))) | BB25: =IF(AZ25="TEC Rejected","",IF(AZ25="","",AZ25*IF(AY25="",$E25,AY25))) | BF25: =IF(BD25="TEC Rejected","",IF(BD25="","",BD25*IF(BC25="",$E25,BC25)))
A26: 22 | B26: 22 | C26: X22 | D26: PHOTO RESISTOR | E26: 9 | F26: 9 | R26: =IF(P26="TEC Rejected","",IF(P26="","",P26*IF(O26="",$E26,O26))) | V26: =IF(T26="TEC Rejected","",IF(T26="","",T26*IF(S26="",$E26,S26))) | Z26: =IF(X26="TEC Rejected","",IF(X26="","",X26*IF(W26="",$E26,W26))) | AD26: =IF(AB26="TEC Rejected","",IF(AB26="","",AB26*IF(AA26="",$E26,AA26))) | AH26: =IF(AF26="TEC Rejected","",IF(AF26="","",AF26*IF(AE26="",$E26,AE26))) | AL26: =IF(AJ26="TEC Rejected","",IF(AJ26="","",AJ26*IF(AI26="",$E26,AI26))) | AP26: =IF(AN26="TEC Rejected","",IF(AN26="","",AN26*IF(AM26="",$E26,AM26))) | AT26: =IF(AR26="TEC Rejected","",IF(AR26="","",AR26*IF(AQ26="",$E26,AQ26))) | AX26: =IF(AV26="TEC Rejected","",IF(AV26="","",AV26*IF(AU26="",$E26,AU26))) | BB26: =IF(AZ26="TEC Rejected","",IF(AZ26="","",AZ26*IF(AY26="",$E26,AY26))) | BF26: =IF(BD26="TEC Rejected","",IF(BD26="","",BD26*IF(BC26="",$E26,BC26)))
A27: 23 | B27: 23 | C27: X23 | D27: SECURING NUT | E27: 11 | F27: 11 | R27: =IF(P27="TEC Rejected","",IF(P27="","",P27*IF(O27="",$E27,O27))) | V27: =IF(T27="TEC Rejected","",IF(T27="","",T27*IF(S27="",$E27,S27))) | Z27: =IF(X27="TEC Rejected","",IF(X27="","",X27*IF(W27="",$E27,W27))) | AD27: =IF(AB27="TEC Rejected","",IF(AB27="","",AB27*IF(AA27="",$E27,AA27))) | AH27: =IF(AF27="TEC Rejected","",IF(AF27="","",AF27*IF(AE27="",$E27,AE27))) | AL27: =IF(AJ27="TEC Rejected","",IF(AJ27="","",AJ27*IF(AI27="",$E27,AI27))) | AP27: =IF(AN27="TEC Rejected","",IF(AN27="","",AN27*IF(AM27="",$E27,AM27))) | AT27: =IF(AR27="TEC Rejected","",IF(AR27="","",AR27*IF(AQ27="",$E27,AQ27))) | AX27: =IF(AV27="TEC Rejected","",IF(AV27="","",AV27*IF(AU27="",$E27,AU27))) | BB27: =IF(AZ27="TEC Rejected","",IF(AZ27="","",AZ27*IF(AY27="",$E27,AY27))) | BF27: =IF(BD27="TEC Rejected","",IF(BD27="","",BD27*IF(BC27="",$E27,BC27)))
A28: 24 | B28: 24 | C28: X24 | D28: DIODE | E28: 46 | F28: 46 | O28: 46 | P28: 3.6 | R28: =IF(P28="TEC Rejected","",IF(P28="","",P28*IF(O28="",$E28,O28))) -> 165.6 | S28: 46 | T28: 9.6 | V28: =IF(T28="TEC Rejected","",IF(T28="","",T28*IF(S28="",$E28,S28))) -> 441.6 | Z28: =IF(X28="TEC Rejected","",IF(X28="","",X28*IF(W28="",$E28,W28))) | AA28: 46 | AB28: 90 | AD28: =IF(AB28="TEC Rejected","",IF(AB28="","",AB28*IF(AA28="",$E28,AA28))) -> 4140 | AH28: =IF(AF28="TEC Rejected","",IF(AF28="","",AF28*IF(AE28="",$E28,AE28))) | AL28: =IF(AJ28="TEC Rejected","",IF(AJ28="","",AJ28*IF(AI28="",$E28,AI28))) | AP28: =IF(AN28="TEC Rejected","",IF(AN28="","",AN28*IF(AM28="",$E28,AM28))) | AT28: =IF(AR28="TEC Rejected","",IF(AR28="","",AR28*IF(AQ28="",$E28,AQ28))) | AX28: =IF(AV28="TEC Rejected","",IF(AV28="","",AV28*IF(AU28="",$E28,AU28))) | BB28: =IF(AZ28="TEC Rejected","",IF(AZ28="","",AZ28*IF(AY28="",$E28,AY28))) | BF28: =IF(BD28="TEC Rejected","",IF(BD28="","",BD28*IF(BC28="",$E28,BC28)))
A29: 25 | B29: 25 | C29: X25 | D29: DIODE | E29: 20 | F29: 20 | O29: 20 | P29: 3.6 | R29: =IF(P29="TEC Rejected","",IF(P29="","",P29*IF(O29="",$E29,O29))) -> 72 | S29: 20 | T29: 8.8 | V29: =IF(T29="TEC Rejected","",IF(T29="","",T29*IF(S29="",$E29,S29))) -> 176 | Z29: =IF(X29="TEC Rejected","",IF(X29="","",X29*IF(W29="",$E29,W29))) | AA29: 20 | AB29: 90 | AD29: =IF(AB29="TEC Rejected","",IF(AB29="","",AB29*IF(AA29="",$E29,AA29))) -> 1800 | AH29: =IF(AF29="TEC Rejected","",IF(AF29="","",AF29*IF(AE29="",$E29,AE29))) | AL29: =IF(AJ29="TEC Rejected","",IF(AJ29="","",AJ29*IF(AI29="",$E29,AI29))) | AP29: =IF(AN29="TEC Rejected","",IF(AN29="","",AN29*IF(AM29="",$E29,AM29))) | AT29: =IF(AR29="TEC Rejected","",IF(AR29="","",AR29*IF(AQ29="",$E29,AQ29))) | AX29: =IF(AV29="TEC Rejected","",IF(AV29="","",AV29*IF(AU29="",$E29,AU29))) | BB29: =IF(AZ29="TEC Rejected","",IF(AZ29="","",AZ29*IF(AY29="",$E29,AY29))) | BF29: =IF(BD29="TEC Rejected","",IF(BD29="","",BD29*IF(BC29="",$E29,BC29)))
A30: 26 | B30: 26 | C30: X26 | D30: MOTOR | E30: 5 | F30: 5 | O30: 5 | P30: 4583 | R30: =IF(P30="TEC Rejected","",IF(P30="","",P30*IF(O30="",$E30,O30))) -> 22915 | S30: 5 | T30: 4920 | V30: =IF(T30="TEC Rejected","",IF(T30="","",T30*IF(S30="",$E30,S30))) -> 24600 | Z30: =IF(X30="TEC Rejected","",IF(X30="","",X30*IF(W30="",$E30,W30))) | AD30: =IF(AB30="TEC Rejected","",IF(AB30="","",AB30*IF(AA30="",$E30,AA30))) | AH30: =IF(AF30="TEC Rejected","",IF(AF30="","",AF30*IF(AE30="",$E30,AE30))) | AL30: =IF(AJ30="TEC Rejected","",IF(AJ30="","",AJ30*IF(AI30="",$E30,AI30))) | AP30: =IF(AN30="TEC Rejected","",IF(AN30="","",AN30*IF(AM30="",$E30,AM30))) | AT30: =IF(AR30="TEC Rejected","",IF(AR30="","",AR30*IF(AQ30="",$E30,AQ30))) | AX30: =IF(AV30="TEC Rejected","",IF(AV30="","",AV30*IF(AU30="",$E30,AU30))) | BB30: =IF(AZ30="TEC Rejected","",IF(AZ30="","",AZ30*IF(AY30="",$E30,AY30))) | BF30: =IF(BD30="TEC Rejected","",IF(BD30="","",BD30*IF(BC30="",$E30,BC30)))
A31: 27 | B31: 27 | C31: X27 | D31: FUSE HOLDER | E31: 121 | F31: 121 | O31: 121 | P31: 6.5 | R31: =IF(P31="TEC Rejected","",IF(P31="","",P31*IF(O31="",$E31,O31))) -> 786.5 | S31: 121 | T31: 23.1 | V31: =IF(T31="TEC Rejected","",IF(T31="","",T31*IF(S31="",$E31,S31))) -> 2795.1 | Z31: =IF(X31="TEC Rejected","",IF(X31="","",X31*IF(W31="",$E31,W31))) | AA31: 121 | AB31: 465 | AD31: =IF(AB31="TEC Rejected","",IF(AB31="","",AB31*IF(AA31="",$E31,AA31))) -> 56265 | AH31: =IF(AF31="TEC Rejected","",IF(AF31="","",AF31*IF(AE31="",$E31,AE31))) | AI31: 121 | AJ31: 581 | AL31: =IF(AJ31="TEC Rejected","",IF(AJ31="","",AJ31*IF(AI31="",$E31,AI31))) -> 70301 | AP31: =IF(AN31="TEC Rejected","",IF(AN31="","",AN31*IF(AM31="",$E31,AM31))) | AT31: =IF(AR31="TEC Rejected","",IF(AR31="","",AR31*IF(AQ31="",$E31,AQ31))) | AX31: =IF(AV31="TEC Rejected","",IF(AV31="","",AV31*IF(AU31="",$E31,AU31))) | BB31: =IF(AZ31="TEC Rejected","",IF(AZ31="","",AZ31*IF(AY31="",$E31,AY31))) | BF31: =IF(BD31="TEC Rejected","",IF(BD31="","",BD31*IF(BC31="",$E31,BC31)))
A32: 28 | B32: 28 | C32: X28 | D32: HIGH VOLTAGE SEALENT | E32: 15 | F32: 15 | R32: =IF(P32="TEC Rejected","",IF(P32="","",P32*IF(O32="",$E32,O32))) | V32: =IF(T32="TEC Rejected","",IF(T32="","",T32*IF(S32="",$E32,S32))) | Z32: =IF(X32="TEC Rejected","",IF(X32="","",X32*IF(W32="",$E32,W32))) | AD32: =IF(AB32="TEC Rejected","",IF(AB32="","",AB32*IF(AA32="",$E32,AA32))) | AH32: =IF(AF32="TEC Rejected","",IF(AF32="","",AF32*IF(AE32="",$E32,AE32))) | AL32: =IF(AJ32="TEC Rejected","",IF(AJ32="","",AJ32*IF(AI32="",$E32,AI32))) | AP32: =IF(AN32="TEC Rejected","",IF(AN32="","",AN32*IF(AM32="",$E32,AM32))) | AT32: =IF(AR32="TEC Rejected","",IF(AR32="","",AR32*IF(AQ32="",$E32,AQ32))) | AX32: =IF(AV32="TEC Rejected","",IF(AV32="","",AV32*IF(AU32="",$E32,AU32))) | BB32: =IF(AZ32="TEC Rejected","",IF(AZ32="","",AZ32*IF(AY32="",$E32,AY32))) | BF32: =IF(BD32="TEC Rejected","",IF(BD32="","",BD32*IF(BC32="",$E32,BC32)))
A33: 29 | B33: 29 | C33: X29 | D33: ELECTRIC TIMER | E33: 3 | F33: 3 | R33: =IF(P33="TEC Rejected","",IF(P33="","",P33*IF(O33="",$E33,O33))) | V33: =IF(T33="TEC Rejected","",IF(T33="","",T33*IF(S33="",$E33,S33))) | Z33: =IF(X33="TEC Rejected","",IF(X33="","",X33*IF(W33="",$E33,W33))) | AA33: 3 | AB33: 3765 | AD33: =IF(AB33="TEC Rejected","",IF(AB33="","",AB33*IF(AA33="",$E33,AA33))) -> 11295 | AH33: =IF(AF33="TEC Rejected","",IF(AF33="","",AF33*IF(AE33="",$E33,AE33))) | AL33: =IF(AJ33="TEC Rejected","",IF(AJ33="","",AJ33*IF(AI33="",$E33,AI33))) | AP33: =IF(AN33="TEC Rejected","",IF(AN33="","",AN33*IF(AM33="",$E33,AM33))) | AT33: =IF(AR33="TEC Rejected","",IF(AR33="","",AR33*IF(AQ33="",$E33,AQ33))) | AX33: =IF(AV33="TEC Rejected","",IF(AV33="","",AV33*IF(AU33="",$E33,AU33))) | BB33: =IF(AZ33="TEC Rejected","",IF(AZ33="","",AZ33*IF(AY33="",$E33,AY33))) | BF33: =IF(BD33="TEC Rejected","",IF(BD33="","",BD33*IF(BC33="",$E33,BC33)))
A34: 30 | B34: 30 | C34: X30 | D34: UNIT 08-11 UFTI / FORMER | E34: 4 | F34: 4 | R34: =IF(P34="TEC Rejected","",IF(P34="","",P34*IF(O34="",$E34,O34))) | V34: =IF(T34="TEC Rejected","",IF(T34="","",T34*IF(S34="",$E34,S34))) | Z34: =IF(X34="TEC Rejected","",IF(X34="","",X34*IF(W34="",$E34,W34))) | AD34: =IF(AB34="TEC Rejected","",IF(AB34="","",AB34*IF(AA34="",$E34,AA34))) | AH34: =IF(AF34="TEC Rejected","",IF(AF34="","",AF34*IF(AE34="",$E34,AE34))) | AL34: =IF(AJ34="TEC Rejected","",IF(AJ34="","",AJ34*IF(AI34="",$E34,AI34))) | AP34: =IF(AN34="TEC Rejected","",IF(AN34="","",AN34*IF(AM34="",$E34,AM34))) | AT34: =IF(AR34="TEC Rejected","",IF(AR34="","",AR34*IF(AQ34="",$E34,AQ34))) | AX34: =IF(AV34="TEC Rejected","",IF(AV34="","",AV34*IF(AU34="",$E34,AU34))) | BB34: =IF(AZ34="TEC Rejected","",IF(AZ34="","",AZ34*IF(AY34="",$E34,AY34))) | BF34: =IF(BD34="TEC Rejected","",IF(BD34="","",BD34*IF(BC34="",$E34,BC34)))
A35: 31 | B35: 31 | C35: X31 | D35: CAPACITOR | E35: 10 | F35: 10 | O35: 10 | P35: 30 | R35: =IF(P35="TEC Rejected","",IF(P35="","",P35*IF(O35="",$E35,O35))) -> 300 | S35: 10 | T35: 14.4 | V35: =IF(T35="TEC Rejected","",IF(T35="","",T35*IF(S35="",$E35,S35))) -> 144 | Z35: =IF(X35="TEC Rejected","",IF(X35="","",X35*IF(W35="",$E35,W35))) | AA35: 10 | AB35: 315 | AD35: =IF(AB35="TEC Rejected","",IF(AB35="","",AB35*IF(AA35="",$E35,AA35))) -> 3150 | AH35: =IF(AF35="TEC Rejected","",IF(AF35="","",AF35*IF(AE35="",$E35,AE35))) | AL35: =IF(AJ35="TEC Rejected","",IF(AJ35="","",AJ35*IF(AI35="",$E35,AI35))) | AP35: =IF(AN35="TEC Rejected","",IF(AN35="","",AN35*IF(AM35="",$E35,AM35))) | AT35: =IF(AR35="TEC Rejected","",IF(AR35="","",AR35*IF(AQ35="",$E35,AQ35))) | AX35: =IF(AV35="TEC Rejected","",IF(AV35="","",AV35*IF(AU35="",$E35,AU35))) | BB35: =IF(AZ35="TEC Rejected","",IF(AZ35="","",AZ35*IF(AY35="",$E35,AY35))) | BF35: =IF(BD35="TEC Rejected","",IF(BD35="","",BD35*IF(BC35="",$E35,BC35)))
A36: 32 | B36: 32 | C36: X32 | D36: CAPACITOR | E36: 20 | F36: 20 | O36: 20 | P36: 30 | R36: =IF(P36="TEC Rejected","",IF(P36="","",P36*IF(O36="",$E36,O36))) -> 600 | S36: 20 | T36: 14.4 | V36: =IF(T36="TEC Rejected","",IF(T36="","",T36*IF(S36="",$E36,S36))) -> 288 | Z36: =IF(X36="TEC Rejected","",IF(X36="","",X36*IF(W36="",$E36,W36))) | AA36: 20 | AB36: 315 | AD36: =IF(AB36="TEC Rejected","",IF(AB36="","",AB36*IF(AA36="",$E36,AA36))) -> 6300 | AH36: =IF(AF36="TEC Rejected","",IF(AF36="","",AF36*IF(AE36="",$E36,AE36))) | AL36: =IF(AJ36="TEC Rejected","",IF(AJ36="","",AJ36*IF(AI36="",$E36,AI36))) | AP36: =IF(AN36="TEC Rejected","",IF(AN36="","",AN36*IF(AM36="",$E36,AM36))) | AT36: =IF(AR36="TEC Rejected","",IF(AR36="","",AR36*IF(AQ36="",$E36,AQ36))) | AX36: =IF(AV36="TEC Rejected","",IF(AV36="","",AV36*IF(AU36="",$E36,AU36))) | BB36: =IF(AZ36="TEC Rejected","",IF(AZ36="","",AZ36*IF(AY36="",$E36,AY36))) | BF36: =IF(BD36="TEC Rejected","",IF(BD36="","",BD36*IF(BC36="",$E36,BC36)))
A37: 33 | B37: 33 | C37: X33 | D37: CAPACITOR | E37: 110 | F37: 110 | O37: 110 | P37: 27 | R37: =IF(P37="TEC Rejected","",IF(P37="","",P37*IF(O37="",$E37,O37))) -> 2970 | S37: 110 | T37: 19.5 | V37: =IF(T37="TEC Rejected","",IF(T37="","",T37*IF(S37="",$E37,S37))) -> 2145 | Z37: =IF(X37="TEC Rejected","",IF(X37="","",X37*IF(W37="",$E37,W37))) | AA37: 110 | AB37: 465 | AD37: =IF(AB37="TEC Rejected","",IF(AB37="","",AB37*IF(AA37="",$E37,AA37))) -> 51150 | AH37: =IF(AF37="TEC Rejected","",IF(AF37="","",AF37*IF(AE37="",$E37,AE37))) | AL37: =IF(AJ37="TEC Rejected","",IF(AJ37="","",AJ37*IF(AI37="",$E37,AI37))) | AP37: =IF(AN37="TEC Rejected","",IF(AN37="","",AN37*IF(AM37="",$E37,AM37))) | AT37: =IF(AR37="TEC Rejected","",IF(AR37="","",AR37*IF(AQ37="",$E37,AQ37))) | AX37: =IF(AV37="TEC Rejected","",IF(AV37="","",AV37*IF(AU37="",$E37,AU37))) | BB37: =IF(AZ37="TEC Rejected","",IF(AZ37="","",AZ37*IF(AY37="",$E37,AY37))) | BF37: =IF(BD37="TEC Rejected","",IF(BD37="","",BD37*IF(BC37="",$E37,BC37)))
A38: 34 | B38: 34 | C38: X34 | D38: CAPACITOR | E38: 131 | F38: 131 | O38: 131 | P38: 45 | R38: =IF(P38="TEC Rejected","",IF(P38="","",P38*IF(O38="",$E38,O38))) -> 5895 | S38: 131 | T38: 18 | V38: =IF(T38="TEC Rejected","",IF(T38="","",T38*IF(S38="",$E38,S38))) -> 2358 | Z38: =IF(X38="TEC Rejected","",IF(X38="","",X38*IF(W38="",$E38,W38))) | AA38: 131 | AB38: 465 | AD38: =IF(AB38="TEC Rejected","",IF(AB38="","",AB38*IF(AA38="",$E38,AA38))) -> 60915 | AH38: =IF(AF38="TEC Rejected","",IF(AF38="","",AF38*IF(AE38="",$E38,AE38))) | AL38: =IF(AJ38="TEC Rejected","",IF(AJ38="","",AJ38*IF(AI38="",$E38,AI38))) | AP38: =IF(AN38="TEC Rejected","",IF(AN38="","",AN38*IF(AM38="",$E38,AM38))) | AT38: =IF(AR38="TEC Rejected","",IF(AR38="","",AR38*IF(AQ38="",$E38,AQ38))) | AX38: =IF(AV38="TEC Rejected","",IF(AV38="","",AV38*IF(AU38="",$E38,AU38))) | BB38: =IF(AZ38="TEC Rejected","",IF(AZ38="","",AZ38*IF(AY38="",$E38,AY38))) | BF38: =IF(BD38="TEC Rejected","",IF(BD38="","",BD38*IF(BC38="",$E38,BC38)))
A39: 35 | B39: 35 | C39: X35 | D39: CAPACITOR | E39: 10 | F39: 10 | O39: 10 | P39: 171 | R39: =IF(P39="TEC Rejected","",IF(P39="","",P39*IF(O39="",$E39,O39))) -> 1710 | S39: 10 | T39: 144 | V39: =IF(T39="TEC Rejected","",IF(T39="","",T39*IF(S39="",$E39,S39))) -> 1440 | Z39: =IF(X39="TEC Rejected","",IF(X39="","",X39*IF(W39="",$E39,W39))) | AA39: 10 | AB39: 9765 | AD39: =IF(AB39="TEC Rejected","",IF(AB39="","",AB39*IF(AA39="",$E39,AA39))) -> 97650 | AH39: =IF(AF39="TEC Rejected","",IF(AF39="","",AF39*IF(AE39="",$E39,AE39))) | AI39: 10 | AJ39: 14940 | AL39: =IF(AJ39="TEC Rejected","",IF(AJ39="","",AJ39*IF(AI39="",$E39,AI39))) -> 149400 | AP39: =IF(AN39="TEC Rejected","",IF(AN39="","",AN39*IF(AM39="",$E39,AM39))) | AT39: =IF(AR39="TEC Rejected","",IF(AR39="","",AR39*IF(AQ39="",$E39,AQ39))) | AX39: =IF(AV39="TEC Rejected","",IF(AV39="","",AV39*IF(AU39="",$E39,AU39))) | BB39: =IF(AZ39="TEC Rejected","",IF(AZ39="","",AZ39*IF(AY39="",$E39,AY39))) | BF39: =IF(BD39="TEC Rejected","",IF(BD39="","",BD39*IF(BC39="",$E39,BC39)))
A40: 36 | B40: 36 | C40: X36 | D40: CAPACITOR | E40: 28 | F40: 28 | O40: 28 | P40: 155 | R40: =IF(P40="TEC Rejected","",IF(P40="","",P40*IF(O40="",$E40,O40))) -> 4340 | S40: 28 | T40: 132 | V40: =IF(T40="TEC Rejected","",IF(T40="","",T40*IF(S40="",$E40,S40))) -> 3696 | Z40: =IF(X40="TEC Rejected","",IF(X40="","",X40*IF(W40="",$E40,W40))) | AA40: 28 | AB40: 9765 | AD40: =IF(AB40="TEC Rejected","",IF(AB40="","",AB40*IF(AA40="",$E40,AA40))) -> 273420 | AH40: =IF(AF40="TEC Rejected","",IF(AF40="","",AF40*IF(AE40="",$E40,AE40))) | AI40: 28 | AJ40: 14940 | AL40: =IF(AJ40="TEC Rejected","",IF(AJ40="","",AJ40*IF(AI40="",$E40,AI40))) -> 418320 | AP40: =IF(AN40="TEC Rejected","",IF(AN40="","",AN40*IF(AM40="",$E40,AM40))) | AT40: =IF(AR40="TEC Rejected","",IF(AR40="","",AR40*IF(AQ40="",$E40,AQ40))) | AX40: =IF(AV40="TEC Rejected","",IF(AV40="","",AV40*IF(AU40="",$E40,AU40))) | BB40: =IF(AZ40="TEC Rejected","",IF(AZ40="","",AZ40*IF(AY40="",$E40,AY40))) | BF40: =IF(BD40="TEC Rejected","",IF(BD40="","",BD40*IF(BC40="",$E40,BC40)))
A41: 37 | B41: 37 | C41: X37 | D41: FRAME | E41: 5 | F41: 5 | R41: =IF(P41="TEC Rejected","",IF(P41="","",P41*IF(O41="",$E41,O41))) | V41: =IF(T41="TEC Rejected","",IF(T41="","",T41*IF(S41="",$E41,S41))) | Z41: =IF(X41="TEC Rejected","",IF(X41="","",X41*IF(W41="",$E41,W41))) | AD41: =IF(AB41="TEC Rejected","",IF(AB41="","",AB41*IF(AA41="",$E41,AA41))) | AH41: =IF(AF41="TEC Rejected","",IF(AF41="","",AF41*IF(AE41="",$E41,AE41))) | AL41: =IF(AJ41="TEC Rejected","",IF(AJ41="","",AJ41*IF(AI41="",$E41,AI41))) | AP41: =IF(AN41="TEC Rejected","",IF(AN41="","",AN41*IF(AM41="",$E41,AM41))) | AT41: =IF(AR41="TEC Rejected","",IF(AR41="","",AR41*IF(AQ41="",$E41,AQ41))) | AX41: =IF(AV41="TEC Rejected","",IF(AV41="","",AV41*IF(AU41="",$E41,AU41))) | BB41: =IF(AZ41="TEC Rejected","",IF(AZ41="","",AZ41*IF(AY41="",$E41,AY41))) | BF41: =IF(BD41="TEC Rejected","",IF(BD41="","",BD41*IF(BC41="",$E41,BC41)))
A42: 38 | B42: 38 | C42: X38 | D42: CONTACTOR | E42: 12 | F42: 12 | O42: 12 | P42: 500 | R42: =IF(P42="TEC Rejected","",IF(P42="","",P42*IF(O42="",$E42,O42))) -> 6000 | S42: 12 | T42: 325 | V42: =IF(T42="TEC Rejected","",IF(T42="","",T42*IF(S42="",$E42,S42))) -> 3900 | Z42: =IF(X42="TEC Rejected","",IF(X42="","",X42*IF(W42="",$E42,W42))) | AA42: 12 | AB42: 9765 | AD42: =IF(AB42="TEC Rejected","",IF(AB42="","",AB42*IF(AA42="",$E42,AA42))) -> 117180 | AH42: =IF(AF42="TEC Rejected","",IF(AF42="","",AF42*IF(AE42="",$E42,AE42))) | AL42: =IF(AJ42="TEC Rejected","",IF(AJ42="","",AJ42*IF(AI42="",$E42,AI42))) | AP42: =IF(AN42="TEC Rejected","",IF(AN42="","",AN42*IF(AM42="",$E42,AM42))) | AT42: =IF(AR42="TEC Rejected","",IF(AR42="","",AR42*IF(AQ42="",$E42,AQ42))) | AX42: =IF(AV42="TEC Rejected","",IF(AV42="","",AV42*IF(AU42="",$E42,AU42))) | BB42: =IF(AZ42="TEC Rejected","",IF(AZ42="","",AZ42*IF(AY42="",$E42,AY42))) | BF42: =IF(BD42="TEC Rejected","",IF(BD42="","",BD42*IF(BC42="",$E42,BC42)))
A43: 39 | B43: 39 | C43: X39 | D43: ARTICLE CONDOR-1 | E43: 4 | F43: 4 | O43: 4 | P43: 93300 | R43: =IF(P43="TEC Rejected","",IF(P43="","",P43*IF(O43="",$E43,O43))) -> 373200 | S43: 4 | T43: 168000 | V43: =IF(T43="TEC Rejected","",IF(T43="","",T43*IF(S43="",$E43,S43))) -> 672000 | Z43: =IF(X43="TEC Rejected","",IF(X43="","",X43*IF(W43="",$E43,W43))) | AD43: =IF(AB43="TEC Rejected","",IF(AB43="","",AB43*IF(AA43="",$E43,AA43))) | AH43: =IF(AF43="TEC Rejected","",IF(AF43="","",AF43*IF(AE43="",$E43,AE43))) | AL43: =IF(AJ43="TEC Rejected","",IF(AJ43="","",AJ43*IF(AI43="",$E43,AI43))) | AP43: =IF(AN43="TEC Rejected","",IF(AN43="","",AN43*IF(AM43="",$E43,AM43))) | AT43: =IF(AR43="TEC Rejected","",IF(AR43="","",AR43*IF(AQ43="",$E43,AQ43))) | AX43: =IF(AV43="TEC Rejected","",IF(AV43="","",AV43*IF(AU43="",$E43,AU43))) | BB43: =IF(AZ43="TEC Rejected","",IF(AZ43="","",AZ43*IF(AY43="",$E43,AY43))) | BF43: =IF(BD43="TEC Rejected","",IF(BD43="","",BD43*IF(BC43="",$E43,BC43)))
A44: 40 | B44: 40 | C44: X40 | D44: TRUBKA PICTURE TUBE OF MFD | E44: 5 | F44: 5 | R44: =IF(P44="TEC Rejected","",IF(P44="","",P44*IF(O44="",$E44,O44))) | V44: =IF(T44="TEC Rejected","",IF(T44="","",T44*IF(S44="",$E44,S44))) | Z44: =IF(X44="TEC Rejected","",IF(X44="","",X44*IF(W44="",$E44,W44))) | AD44: =IF(AB44="TEC Rejected","",IF(AB44="","",AB44*IF(AA44="",$E44,AA44))) | AH44: =IF(AF44="TEC Rejected","",IF(AF44="","",AF44*IF(AE44="",$E44,AE44))) | AL44: =IF(AJ44="TEC Rejected","",IF(AJ44="","",AJ44*IF(AI44="",$E44,AI44))) | AP44: =IF(AN44="TEC Rejected","",IF(AN44="","",AN44*IF(AM44="",$E44,AM44))) | AT44: =IF(AR44="TEC Rejected","",IF(AR44="","",AR44*IF(AQ44="",$E44,AQ44))) | AX44: =IF(AV44="TEC Rejected","",IF(AV44="","",AV44*IF(AU44="",$E44,AU44))) | BB44: =IF(AZ44="TEC Rejected","",IF(AZ44="","",AZ44*IF(AY44="",$E44,AY44))) | BF44: =IF(BD44="TEC Rejected","",IF(BD44="","",BD44*IF(BC44="",$E44,BC44)))
A45: 41 | B45: 41 | C45: X41 | D45: MICROSWITCH | E45: 20 | F45: 20 | O45: 20 | P45: 450 | R45: =IF(P45="TEC Rejected","",IF(P45="","",P45*IF(O45="",$E45,O45))) -> 9000 | S45: 20 | T45: 325 | V45: =IF(T45="TEC Rejected","",IF(T45="","",T45*IF(S45="",$E45,S45))) -> 6500 | Z45: =IF(X45="TEC Rejected","",IF(X45="","",X45*IF(W45="",$E45,W45))) | AA45: 20 | AB45: 5265 | AD45: =IF(AB45="TEC Rejected","",IF(AB45="","",AB45*IF(AA45="",$E45,AA45))) -> 105300 | AH45: =IF(AF45="TEC Rejected","",IF(AF45="","",AF45*IF(AE45="",$E45,AE45))) | AI45: 20 | AJ45: 6640 | AL45: =IF(AJ45="TEC Rejected","",IF(AJ45="","",AJ45*IF(AI45="",$E45,AI45))) -> 132800 | AP45: =IF(AN45="TEC Rejected","",IF(AN45="","",AN45*IF(AM45="",$E45,AM45))) | AT45: =IF(AR45="TEC Rejected","",IF(AR45="","",AR45*IF(AQ45="",$E45,AQ45))) | AX45: =IF(AV45="TEC Rejected","",IF(AV45="","",AV45*IF(AU45="",$E45,AU45))) | BB45: =IF(AZ45="TEC Rejected","",IF(AZ45="","",AZ45*IF(AY45="",$E45,AY45))) | BF45: =IF(BD45="TEC Rejected","",IF(BD45="","",BD45*IF(BC45="",$E45,BC45)))
A46: 42 | B46: 42 | C46: X42 | D46: SWITCH | E46: 8 | F46: 8 | O46: 8 | P46: 620 | R46: =IF(P46="TEC Rejected","",IF(P46="","",P46*IF(O46="",$E46,O46))) -> 4960 | S46: 8 | T46: 490 | V46: =IF(T46="TEC Rejected","",IF(T46="","",T46*IF(S46="",$E46,S46))) -> 3920 | Z46: =IF(X46="TEC Rejected","",IF(X46="","",X46*IF(W46="",$E46,W46))) | AA46: 8 | AB46: 9765 | AD46: =IF(AB46="TEC Rejected","",IF(AB46="","",AB46*IF(AA46="",$E46,AA46))) -> 78120 | AH46: =IF(AF46="TEC Rejected","",IF(AF46="","",AF46*IF(AE46="",$E46,AE46))) | AI46: 8 | AJ46: 9545 | AL46: =IF(AJ46="TEC Rejected","",IF(AJ46="","",AJ46*IF(AI46="",$E46,AI46))) -> 76360 | AP46: =IF(AN46="TEC Rejected","",IF(AN46="","",AN46*IF(AM46="",$E46,AM46))) | AT46: =IF(AR46="TEC Rejected","",IF(AR46="","",AR46*IF(AQ46="",$E46,AQ46))) | AX46: =IF(AV46="TEC Rejected","",IF(AV46="","",AV46*IF(AU46="",$E46,AU46))) | BB46: =IF(AZ46="TEC Rejected","",IF(AZ46="","",AZ46*IF(AY46="",$E46,AY46))) | BF46: =IF(BD46="TEC Rejected","",IF(BD46="","",BD46*IF(BC46="",$E46,BC46)))
A47: 43 | B47: 43 | C47: X43 | D47: SWITCH | E47: 8 | F47: 8 | O47: 8 | P47: 270 | R47: =IF(P47="TEC Rejected","",IF(P47="","",P47*IF(O47="",$E47,O47))) -> 2160 | S47: 8 | T47: 192 | V47: =IF(T47="TEC Rejected","",IF(T47="","",T47*IF(S47="",$E47,S47))) -> 1536 | Z47: =IF(X47="TEC Rejected","",IF(X47="","",X47*IF(W47="",$E47,W47))) | AA47: 8 | AB47: 2865 | AD47: =IF(AB47="TEC Rejected","",IF(AB47="","",AB47*IF(AA47="",$E47,AA47))) -> 22920 | AH47: =IF(AF47="TEC Rejected","",IF(AF47="","",AF47*IF(AE47="",$E47,AE47))) | AI47: 8 | AJ47: 3735 | AL47: =IF(AJ47="TEC Rejected","",IF(AJ47="","",AJ47*IF(AI47="",$E47,AI47))) -> 29880 | AP47: =IF(AN47="TEC Rejected","",IF(AN47="","",AN47*IF(AM47="",$E47,AM47))) | AT47: =IF(AR47="TEC Rejected","",IF(AR47="","",AR47*IF(AQ47="",$E47,AQ47))) | AX47: =IF(AV47="TEC Rejected","",IF(AV47="","",AV47*IF(AU47="",$E47,AU47))) | BB47: =IF(AZ47="TEC Rejected","",IF(AZ47="","",AZ47*IF(AY47="",$E47,AY47))) | BF47: =IF(BD47="TEC Rejected","",IF(BD47="","",BD47*IF(BC47="",$E47,BC47)))
A48: 44 | B48: 44 | C48: X44 | D48: RELAY RS4.569.435-04.01 RS0.459.006 TU | E48: 5 | F48: 5 | O48: 5 | P48: 45 | R48: =IF(P48="TEC Rejected","",IF(P48="","",P48*IF(O48="",$E48,O48))) -> 225 | S48: 5 | T48: 25.2 | V48: =IF(T48="TEC Rejected","",IF(T48="","",T48*IF(S48="",$E48,S48))) -> 126 | Z48: =IF(X48="TEC Rejected","",IF(X48="","",X48*IF(W48="",$E48,W48))) | AA48: 5 | AB48: 315 | AD48: =IF(AB48="TEC Rejected","",IF(AB48="","",AB48*IF(AA48="",$E48,AA48))) -> 1575 | AH48: =IF(AF48="TEC Rejected","",IF(AF48="","",AF48*IF(AE48="",$E48,AE48))) | AL48: =IF(AJ48="TEC Rejected","",IF(AJ48="","",AJ48*IF(AI48="",$E48,AI48))) | AP48: =IF(AN48="TEC Rejected","",IF(AN48="","",AN48*IF(AM48="",$E48,AM48))) | AT48: =IF(AR48="TEC Rejected","",IF(AR48="","",AR48*IF(AQ48="",$E48,AQ48))) | AX48: =IF(AV48="TEC Rejected","",IF(AV48="","",AV48*IF(AU48="",$E48,AU48))) | BB48: =IF(AZ48="TEC Rejected","",IF(AZ48="","",AZ48*IF(AY48="",$E48,AY48))) | BF48: =IF(BD48="TEC Rejected","",IF(BD48="","",BD48*IF(BC48="",$E48,BC48)))
A49: 45 | B49: 45 | C49: X45 | D49: BACKELITE CONNECTOR | E49: 10 | F49: 10 | O49: 10 | P49: 60 | R49: =IF(P49="TEC Rejected","",IF(P49="","",P49*IF(O49="",$E49,O49))) -> 600 | S49: 10 | T49: 25.3 | V49: =IF(T49="TEC Rejected","",IF(T49="","",T49*IF(S49="",$E49,S49))) -> 253 | Z49: =IF(X49="TEC Rejected","",IF(X49="","",X49*IF(W49="",$E49,W49))) | AA49: 10 | AB49: 615 | AD49: =IF(AB49="TEC Rejected","",IF(AB49="","",AB49*IF(AA49="",$E49,AA49))) -> 6150 | AH49: =IF(AF49="TEC Rejected","",IF(AF49="","",AF49*IF(AE49="",$E49,AE49))) | AL49: =IF(AJ49="TEC Rejected","",IF(AJ49="","",AJ49*IF(AI49="",$E49,AI49))) | AP49: =IF(AN49="TEC Rejected","",IF(AN49="","",AN49*IF(AM49="",$E49,AM49))) | AT49: =IF(AR49="TEC Rejected","",IF(AR49="","",AR49*IF(AQ49="",$E49,AQ49))) | AX49: =IF(AV49="TEC Rejected","",IF(AV49="","",AV49*IF(AU49="",$E49,AU49))) | BB49: =IF(AZ49="TEC Rejected","",IF(AZ49="","",AZ49*IF(AY49="",$E49,AY49))) | BF49: =IF(BD49="TEC Rejected","",IF(BD49="","",BD49*IF(BC49="",$E49,BC49)))
A50: 46 | B50: 46 | C50: X46 | D50: CABLE | E50: 10 | F50: 10 | R50: =IF(P50="TEC Rejected","",IF(P50="","",P50*IF(O50="",$E50,O50))) | V50: =IF(T50="TEC Rejected","",IF(T50="","",T50*IF(S50="",$E50,S50))) | Z50: =IF(X50="TEC Rejected","",IF(X50="","",X50*IF(W50="",$E50,W50))) | AD50: =IF(AB50="TEC Rejected","",IF(AB50="","",AB50*IF(AA50="",$E50,AA50))) | AH50: =IF(AF50="TEC Rejected","",IF(AF50="","",AF50*IF(AE50="",$E50,AE50))) | AL50: =IF(AJ50="TEC Rejected","",IF(AJ50="","",AJ50*IF(AI50="",$E50,AI50))) | AP50: =IF(AN50="TEC Rejected","",IF(AN50="","",AN50*IF(AM50="",$E50,AM50))) | AT50: =IF(AR50="TEC Rejected","",IF(AR50="","",AR50*IF(AQ50="",$E50,AQ50))) | AX50: =IF(AV50="TEC Rejected","",IF(AV50="","",AV50*IF(AU50="",$E50,AU50))) | BB50: =IF(AZ50="TEC Rejected","",IF(AZ50="","",AZ50*IF(AY50="",$E50,AY50))) | BF50: =IF(BD50="TEC Rejected","",IF(BD50="","",BD50*IF(BC50="",$E50,BC50)))
A51: 47 | B51: 47 | C51: X47 | D51: CABLE | E51: 9 | F51: 9 | R51: =IF(P51="TEC Rejected","",IF(P51="","",P51*IF(O51="",$E51,O51))) | V51: =IF(T51="TEC Rejected","",IF(T51="","",T51*IF(S51="",$E51,S51))) | Z51: =IF(X51="TEC Rejected","",IF(X51="","",X51*IF(W51="",$E51,W51))) | AD51: =IF(AB51="TEC Rejected","",IF(AB51="","",AB51*IF(AA51="",$E51,AA51))) | AH51: =IF(AF51="TEC Rejected","",IF(AF51="","",AF51*IF(AE51="",$E51,AE51))) | AL51: =IF(AJ51="TEC Rejected","",IF(AJ51="","",AJ51*IF(AI51="",$E51,AI51))) | AP51: =IF(AN51="TEC Rejected","",IF(AN51="","",AN51*IF(AM51="",$E51,AM51))) | AT51: =IF(AR51="TEC Rejected","",IF(AR51="","",AR51*IF(AQ51="",$E51,AQ51))) | AX51: =IF(AV51="TEC Rejected","",IF(AV51="","",AV51*IF(AU51="",$E51,AU51))) | BB51: =IF(AZ51="TEC Rejected","",IF(AZ51="","",AZ51*IF(AY51="",$E51,AY51))) | BF51: =IF(BD51="TEC Rejected","",IF(BD51="","",BD51*IF(BC51="",$E51,BC51)))
A52: 48 | B52: 48 | C52: X48 | D52: RESISTOR | E52: 14 | F52: 14 | O52: 14 | P52: 3.5 | R52: =IF(P52="TEC Rejected","",IF(P52="","",P52*IF(O52="",$E52,O52))) -> 49 | S52: 14 | T52: 6.5 | V52: =IF(T52="TEC Rejected","",IF(T52="","",T52*IF(S52="",$E52,S52))) -> 91 | Z52: =IF(X52="TEC Rejected","",IF(X52="","",X52*IF(W52="",$E52,W52))) | AA52: 14 | AB52: 165 | AD52: =IF(AB52="TEC Rejected","",IF(AB52="","",AB52*IF(AA52="",$E52,AA52))) -> 2310 | AH52: =IF(AF52="TEC Rejected","",IF(AF52="","",AF52*IF(AE52="",$E52,AE52))) | AL52: =IF(AJ52="TEC Rejected","",IF(AJ52="","",AJ52*IF(AI52="",$E52,AI52))) | AP52: =IF(AN52="TEC Rejected","",IF(AN52="","",AN52*IF(AM52="",$E52,AM52))) | AT52: =IF(AR52="TEC Rejected","",IF(AR52="","",AR52*IF(AQ52="",$E52,AQ52))) | AX52: =IF(AV52="TEC Rejected","",IF(AV52="","",AV52*IF(AU52="",$E52,AU52))) | BB52: =IF(AZ52="TEC Rejected","",IF(AZ52="","",AZ52*IF(AY52="",$E52,AY52))) | BF52: =IF(BD52="TEC Rejected","",IF(BD52="","",BD52*IF(BC52="",$E52,BC52)))
A53: 49 | B53: 49 | C53: X49 | D53: RESISTOR | E53: 22 | F53: 22 | O53: 22 | P53: 2.5 | R53: =IF(P53="TEC Rejected","",IF(P53="","",P53*IF(O53="",$E53,O53))) -> 55 | S53: 22 | T53: 6.5 | V53: =IF(T53="TEC Rejected","",IF(T53="","",T53*IF(S53="",$E53,S53))) -> 143 | Z53: =IF(X53="TEC Rejected","",IF(X53="","",X53*IF(W53="",$E53,W53))) | AA53: 22 | AB53: 90 | AD53: =IF(AB53="TEC Rejected","",IF(AB53="","",AB53*IF(AA53="",$E53,AA53))) -> 1980 | AH53: =IF(AF53="TEC Rejected","",IF(AF53="","",AF53*IF(AE53="",$E53,AE53))) | AL53: =IF(AJ53="TEC Rejected","",IF(AJ53="","",AJ53*IF(AI53="",$E53,AI53))) | AP53: =IF(AN53="TEC Rejected","",IF(AN53="","",AN53*IF(AM53="",$E53,AM53))) | AT53: =IF(AR53="TEC Rejected","",IF(AR53="","",AR53*IF(AQ53="",$E53,AQ53))) | AX53: =IF(AV53="TEC Rejected","",IF(AV53="","",AV53*IF(AU53="",$E53,AU53))) | BB53: =IF(AZ53="TEC Rejected","",IF(AZ53="","",AZ53*IF(AY53="",$E53,AY53))) | BF53: =IF(BD53="TEC Rejected","",IF(BD53="","",BD53*IF(BC53="",$E53,BC53)))
A54: 50 | B54: 50 | C54: X50 | D54: RESISTOR | E54: 31 | F54: 31 | O54: 31 | P54: 2.5 | R54: =IF(P54="TEC Rejected","",IF(P54="","",P54*IF(O54="",$E54,O54))) -> 77.5 | S54: 31 | T54: 6.5 | V54: =IF(T54="TEC Rejected","",IF(T54="","",T54*IF(S54="",$E54,S54))) -> 201.5 | Z54: =IF(X54="TEC Rejected","",IF(X54="","",X54*IF(W54="",$E54,W54))) | AA54: 31 | AB54: 90 | AD54: =IF(AB54="TEC Rejected","",IF(AB54="","",AB54*IF(AA54="",$E54,AA54))) -> 2790 | AH54: =IF(AF54="TEC Rejected","",IF(AF54="","",AF54*IF(AE54="",$E54,AE54))) | AL54: =IF(AJ54="TEC Rejected","",IF(AJ54="","",AJ54*IF(AI54="",$E54,AI54))) | AP54: =IF(AN54="TEC Rejected","",IF(AN54="","",AN54*IF(AM54="",$E54,AM54))) | AT54: =IF(AR54="TEC Rejected","",IF(AR54="","",AR54*IF(AQ54="",$E54,AQ54))) | AX54: =IF(AV54="TEC Rejected","",IF(AV54="","",AV54*IF(AU54="",$E54,AU54))) | BB54: =IF(AZ54="TEC Rejected","",IF(AZ54="","",AZ54*IF(AY54="",$E54,AY54))) | BF54: =IF(BD54="TEC Rejected","",IF(BD54="","",BD54*IF(BC54="",$E54,BC54)))
A55: 51 | B55: 51 | C55: X51 | D55: RESISTOR | E55: 5 | F55: 5 | R55: =IF(P55="TEC Rejected","",IF(P55="","",P55*IF(O55="",$E55,O55))) | S55: 5 | T55: 42 | V55: =IF(T55="TEC Rejected","",IF(T55="","",T55*IF(S55="",$E55,S55))) -> 210 | Z55: =IF(X55="TEC Rejected","",IF(X55="","",X55*IF(W55="",$E55,W55))) | AA55: 5 | AB55: 1515 | AD55: =IF(AB55="TEC Rejected","",IF(AB55="","",AB55*IF(AA55="",$E55,AA55))) -> 7575 | AH55: =IF(AF55="TEC Rejected","",IF(AF55="","",AF55*IF(AE55="",$E55,AE55))) | AL55: =IF(AJ55="TEC Rejected","",IF(AJ55="","",AJ55*IF(AI55="",$E55,AI55))) | AP55: =IF(AN55="TEC Rejected","",IF(AN55="","",AN55*IF(AM55="",$E55,AM55))) | AT55: =IF(AR55="TEC Rejected","",IF(AR55="","",AR55*IF(AQ55="",$E55,AQ55))) | AX55: =IF(AV55="TEC Rejected","",IF(AV55="","",AV55*IF(AU55="",$E55,AU55))) | BB55: =IF(AZ55="TEC Rejected","",IF(AZ55="","",AZ55*IF(AY55="",$E55,AY55))) | BF55: =IF(BD55="TEC Rejected","",IF(BD55="","",BD55*IF(BC55="",$E55,BC55)))
A56: 52 | B56: 52 | C56: X52 | D56: UNIT PICTURE TUBE | E56: 3 | F56: 3 | R56: =IF(P56="TEC Rejected","",IF(P56="","",P56*IF(O56="",$E56,O56))) | V56: =IF(T56="TEC Rejected","",IF(T56="","",T56*IF(S56="",$E56,S56))) | Z56: =IF(X56="TEC Rejected","",IF(X56="","",X56*IF(W56="",$E56,W56))) | AD56: =IF(AB56="TEC Rejected","",IF(AB56="","",AB56*IF(AA56="",$E56,AA56))) | AH56: =IF(AF56="TEC Rejected","",IF(AF56="","",AF56*IF(AE56="",$E56,AE56))) | AL56: =IF(AJ56="TEC Rejected","",IF(AJ56="","",AJ56*IF(AI56="",$E56,AI56))) | AP56: =IF(AN56="TEC Rejected","",IF(AN56="","",AN56*IF(AM56="",$E56,AM56))) | AT56: =IF(AR56="TEC Rejected","",IF(AR56="","",AR56*IF(AQ56="",$E56,AQ56))) | AX56: =IF(AV56="TEC Rejected","",IF(AV56="","",AV56*IF(AU56="",$E56,AU56))) | BB56: =IF(AZ56="TEC Rejected","",IF(AZ56="","",AZ56*IF(AY56="",$E56,AY56))) | BF56: =IF(BD56="TEC Rejected","",IF(BD56="","",BD56*IF(BC56="",$E56,BC56)))
A57: 53 | B57: 53 | C57: X53 | D57: PIN | E57: 5 | F57: 5 | R57: =IF(P57="TEC Rejected","",IF(P57="","",P57*IF(O57="",$E57,O57))) | V57: =IF(T57="TEC Rejected","",IF(T57="","",T57*IF(S57="",$E57,S57))) | Z57: =IF(X57="TEC Rejected","",IF(X57="","",X57*IF(W57="",$E57,W57))) | AD57: =IF(AB57="TEC Rejected","",IF(AB57="","",AB57*IF(AA57="",$E57,AA57))) | AH57: =IF(AF57="TEC Rejected","",IF(AF57="","",AF57*IF(AE57="",$E57,AE57))) | AL57: =IF(AJ57="TEC Rejected","",IF(AJ57="","",AJ57*IF(AI57="",$E57,AI57))) | AP57: =IF(AN57="TEC Rejected","",IF(AN57="","",AN57*IF(AM57="",$E57,AM57))) | AT57: =IF(AR57="TEC Rejected","",IF(AR57="","",AR57*IF(AQ57="",$E57,AQ57))) | AX57: =IF(AV57="TEC Rejected","",IF(AV57="","",AV57*IF(AU57="",$E57,AU57))) | BB57: =IF(AZ57="TEC Rejected","",IF(AZ57="","",AZ57*IF(AY57="",$E57,AY57))) | BF57: =IF(BD57="TEC Rejected","",IF(BD57="","",BD57*IF(BC57="",$E57,BC57)))
A58: 54 | B58: 54 | C58: X54 | D58: RUBBER PART | E58: 16 | F58: 16 | R58: =IF(P58="TEC Rejected","",IF(P58="","",P58*IF(O58="",$E58,O58))) | V58: =IF(T58="TEC Rejected","",IF(T58="","",T58*IF(S58="",$E58,S58))) | Z58: =IF(X58="TEC Rejected","",IF(X58="","",X58*IF(W58="",$E58,W58))) | AD58: =IF(AB58="TEC Rejected","",IF(AB58="","",AB58*IF(AA58="",$E58,AA58))) | AH58: =IF(AF58="TEC Rejected","",IF(AF58="","",AF58*IF(AE58="",$E58,AE58))) | AL58: =IF(AJ58="TEC Rejected","",IF(AJ58="","",AJ58*IF(AI58="",$E58,AI58))) | AP58: =IF(AN58="TEC Rejected","",IF(AN58="","",AN58*IF(AM58="",$E58,AM58))) | AT58: =IF(AR58="TEC Rejected","",IF(AR58="","",AR58*IF(AQ58="",$E58,AQ58))) | AX58: =IF(AV58="TEC Rejected","",IF(AV58="","",AV58*IF(AU58="",$E58,AU58))) | BB58: =IF(AZ58="TEC Rejected","",IF(AZ58="","",AZ58*IF(AY58="",$E58,AY58))) | BF58: =IF(BD58="TEC Rejected","",IF(BD58="","",BD58*IF(BC58="",$E58,BC58)))
A59: 55 | B59: 55 | C59: X55 | D59: P1 CIRCUIT | E59: 7 | F59: 7 | O59: 7 | P59: 1290 | R59: =IF(P59="TEC Rejected","",IF(P59="","",P59*IF(O59="",$E59,O59))) -> 9030 | V59: =IF(T59="TEC Rejected","",IF(T59="","",T59*IF(S59="",$E59,S59))) | Z59: =IF(X59="TEC Rejected","",IF(X59="","",X59*IF(W59="",$E59,W59))) | AD59: =IF(AB59="TEC Rejected","",IF(AB59="","",AB59*IF(AA59="",$E59,AA59))) | AH59: =IF(AF59="TEC Rejected","",IF(AF59="","",AF59*IF(AE59="",$E59,AE59))) | AL59: =IF(AJ59="TEC Rejected","",IF(AJ59="","",AJ59*IF(AI59="",$E59,AI59))) | AP59: =IF(AN59="TEC Rejected","",IF(AN59="","",AN59*IF(AM59="",$E59,AM59))) | AT59: =IF(AR59="TEC Rejected","",IF(AR59="","",AR59*IF(AQ59="",$E59,AQ59))) | AX59: =IF(AV59="TEC Rejected","",IF(AV59="","",AV59*IF(AU59="",$E59,AU59))) | BB59: =IF(AZ59="TEC Rejected","",IF(AZ59="","",AZ59*IF(AY59="",$E59,AY59))) | BF59: =IF(BD59="TEC Rejected","",IF(BD59="","",BD59*IF(BC59="",$E59,BC59)))
A60: 56 | B60: 56 | C60: X56 | D60: PLATE P-1 | E60: 5 | F60: 5 | O60: 5 | P60: 125 | R60: =IF(P60="TEC Rejected","",IF(P60="","",P60*IF(O60="",$E60,O60))) -> 625 | V60: =IF(T60="TEC Rejected","",IF(T60="","",T60*IF(S60="",$E60,S60))) | Z60: =IF(X60="TEC Rejected","",IF(X60="","",X60*IF(W60="",$E60,W60))) | AD60: =IF(AB60="TEC Rejected","",IF(AB60="","",AB60*IF(AA60="",$E60,AA60))) | AH60: =IF(AF60="TEC Rejected","",IF(AF60="","",AF60*IF(AE60="",$E60,AE60))) | AL60: =IF(AJ60="TEC Rejected","",IF(AJ60="","",AJ60*IF(AI60="",$E60,AI60))) | AP60: =IF(AN60="TEC Rejected","",IF(AN60="","",AN60*IF(AM60="",$E60,AM60))) | AT60: =IF(AR60="TEC Rejected","",IF(AR60="","",AR60*IF(AQ60="",$E60,AQ60))) | AX60: =IF(AV60="TEC Rejected","",IF(AV60="","",AV60*IF(AU60="",$E60,AU60))) | BB60: =IF(AZ60="TEC Rejected","",IF(AZ60="","",AZ60*IF(AY60="",$E60,AY60))) | BF60: =IF(BD60="TEC Rejected","",IF(BD60="","",BD60*IF(BC60="",$E60,BC60)))
A61: 57 | B61: 57 | C61: X57 | D61: PLATE P-2 | E61: 5 | F61: 5 | O61: 5 | P61: 115 | R61: =IF(P61="TEC Rejected","",IF(P61="","",P61*IF(O61="",$E61,O61))) -> 575 | V61: =IF(T61="TEC Rejected","",IF(T61="","",T61*IF(S61="",$E61,S61))) | Z61: =IF(X61="TEC Rejected","",IF(X61="","",X61*IF(W61="",$E61,W61))) | AD61: =IF(AB61="TEC Rejected","",IF(AB61="","",AB61*IF(AA61="",$E61,AA61))) | AH61: =IF(AF61="TEC Rejected","",IF(AF61="","",AF61*IF(AE61="",$E61,AE61))) | AL61: =IF(AJ61="TEC Rejected","",IF(AJ61="","",AJ61*IF(AI61="",$E61,AI61))) | AP61: =IF(AN61="TEC Rejected","",IF(AN61="","",AN61*IF(AM61="",$E61,AM61))) | AT61: =IF(AR61="TEC Rejected","",IF(AR61="","",AR61*IF(AQ61="",$E61,AQ61))) | AX61: =IF(AV61="TEC Rejected","",IF(AV61="","",AV61*IF(AU61="",$E61,AU61))) | BB61: =IF(AZ61="TEC Rejected","",IF(AZ61="","",AZ61*IF(AY61="",$E61,AY61))) | BF61: =IF(BD61="TEC Rejected","",IF(BD61="","",BD61*IF(BC61="",$E61,BC61)))
A62: 58 | B62: 58 | C62: X58 | D62: Wave Guide Addaptor | E62: 5 | F62: 5 | O62: 5 | P62: 810 | R62: =IF(P62="TEC Rejected","",IF(P62="","",P62*IF(O62="",$E62,O62))) -> 4050 | V62: =IF(T62="TEC Rejected","",IF(T62="","",T62*IF(S62="",$E62,S62))) | Z62: =IF(X62="TEC Rejected","",IF(X62="","",X62*IF(W62="",$E62,W62))) | AD62: =IF(AB62="TEC Rejected","",IF(AB62="","",AB62*IF(AA62="",$E62,AA62))) | AH62: =IF(AF62="TEC Rejected","",IF(AF62="","",AF62*IF(AE62="",$E62,AE62))) | AL62: =IF(AJ62="TEC Rejected","",IF(AJ62="","",AJ62*IF(AI62="",$E62,AI62))) | AP62: =IF(AN62="TEC Rejected","",IF(AN62="","",AN62*IF(AM62="",$E62,AM62))) | AT62: =IF(AR62="TEC Rejected","",IF(AR62="","",AR62*IF(AQ62="",$E62,AQ62))) | AX62: =IF(AV62="TEC Rejected","",IF(AV62="","",AV62*IF(AU62="",$E62,AU62))) | BB62: =IF(AZ62="TEC Rejected","",IF(AZ62="","",AZ62*IF(AY62="",$E62,AY62))) | BF62: =IF(BD62="TEC Rejected","",IF(BD62="","",BD62*IF(BC62="",$E62,BC62)))
A63: 59 | B63: 59 | C63: X59 | D63: BACKELITE COVER | E63: 10 | F63: 10 | R63: =IF(P63="TEC Rejected","",IF(P63="","",P63*IF(O63="",$E63,O63))) | V63: =IF(T63="TEC Rejected","",IF(T63="","",T63*IF(S63="",$E63,S63))) | Z63: =IF(X63="TEC Rejected","",IF(X63="","",X63*IF(W63="",$E63,W63))) | AD63: =IF(AB63="TEC Rejected","",IF(AB63="","",AB63*IF(AA63="",$E63,AA63))) | AH63: =IF(AF63="TEC Rejected","",IF(AF63="","",AF63*IF(AE63="",$E63,AE63))) | AL63: =IF(AJ63="TEC Rejected","",IF(AJ63="","",AJ63*IF(AI63="",$E63,AI63))) | AP63: =IF(AN63="TEC Rejected","",IF(AN63="","",AN63*IF(AM63="",$E63,AM63))) | AT63: =IF(AR63="TEC Rejected","",IF(AR63="","",AR63*IF(AQ63="",$E63,AQ63))) | AX63: =IF(AV63="TEC Rejected","",IF(AV63="","",AV63*IF(AU63="",$E63,AU63))) | BB63: =IF(AZ63="TEC Rejected","",IF(AZ63="","",AZ63*IF(AY63="",$E63,AY63))) | BF63: =IF(BD63="TEC Rejected","",IF(BD63="","",BD63*IF(BC63="",$E63,BC63)))
A64: 60 | B64: 60 | C64: X60 | D64: PIPE | E64: 7 | F64: 7 | R64: =IF(P64="TEC Rejected","",IF(P64="","",P64*IF(O64="",$E64,O64))) | V64: =IF(T64="TEC Rejected","",IF(T64="","",T64*IF(S64="",$E64,S64))) | Z64: =IF(X64="TEC Rejected","",IF(X64="","",X64*IF(W64="",$E64,W64))) | AD64: =IF(AB64="TEC Rejected","",IF(AB64="","",AB64*IF(AA64="",$E64,AA64))) | AH64: =IF(AF64="TEC Rejected","",IF(AF64="","",AF64*IF(AE64="",$E64,AE64))) | AL64: =IF(AJ64="TEC Rejected","",IF(AJ64="","",AJ64*IF(AI64="",$E64,AI64))) | AP64: =IF(AN64="TEC Rejected","",IF(AN64="","",AN64*IF(AM64="",$E64,AM64))) | AT64: =IF(AR64="TEC Rejected","",IF(AR64="","",AR64*IF(AQ64="",$E64,AQ64))) | AX64: =IF(AV64="TEC Rejected","",IF(AV64="","",AV64*IF(AU64="",$E64,AU64))) | BB64: =IF(AZ64="TEC Rejected","",IF(AZ64="","",AZ64*IF(AY64="",$E64,AY64))) | BF64: =IF(BD64="TEC Rejected","",IF(BD64="","",BD64*IF(BC64="",$E64,BC64)))
A65: 61 | B65: 61 | C65: X61 | D65: TRAVELING WAVETUBE | E65: 11 | F65: 11 | R65: =IF(P65="TEC Rejected","",IF(P65="","",P65*IF(O65="",$E65,O65))) | V65: =IF(T65="TEC Rejected","",IF(T65="","",T65*IF(S65="",$E65,S65))) | Z65: =IF(X65="TEC Rejected","",IF(X65="","",X65*IF(W65="",$E65,W65))) | AD65: =IF(AB65="TEC Rejected","",IF(AB65="","",AB65*IF(AA65="",$E65,AA65))) | AH65: =IF(AF65="TEC Rejected","",IF(AF65="","",AF65*IF(AE65="",$E65,AE65))) | AL65: =IF(AJ65="TEC Rejected","",IF(AJ65="","",AJ65*IF(AI65="",$E65,AI65))) | AP65: =IF(AN65="TEC Rejected","",IF(AN65="","",AN65*IF(AM65="",$E65,AM65))) | AT65: =IF(AR65="TEC Rejected","",IF(AR65="","",AR65*IF(AQ65="",$E65,AQ65))) | AX65: =IF(AV65="TEC Rejected","",IF(AV65="","",AV65*IF(AU65="",$E65,AU65))) | BB65: =IF(AZ65="TEC Rejected","",IF(AZ65="","",AZ65*IF(AY65="",$E65,AY65))) | BF65: =IF(BD65="TEC Rejected","",IF(BD65="","",BD65*IF(BC65="",$E65,BC65)))
A66: 62 | B66: 62 | C66: X62 | D66: HIGH VOLTAGE RECTIFIER | E66: 5 | F66: 5 | O66: 5 | P66: 26750 | R66: =IF(P66="TEC Rejected","",IF(P66="","",P66*IF(O66="",$E66,O66))) -> 133750 | S66: 5 | T66: 21000 | V66: =IF(T66="TEC Rejected","",IF(T66="","",T66*IF(S66="",$E66,S66))) -> 105000 | Z66: =IF(X66="TEC Rejected","",IF(X66="","",X66*IF(W66="",$E66,W66))) | AD66: =IF(AB66="TEC Rejected","",IF(AB66="","",AB66*IF(AA66="",$E66,AA66))) | AH66: =IF(AF66="TEC Rejected","",IF(AF66="","",AF66*IF(AE66="",$E66,AE66))) | AL66: =IF(AJ66="TEC Rejected","",IF(AJ66="","",AJ66*IF(AI66="",$E66,AI66))) | AP66: =IF(AN66="TEC Rejected","",IF(AN66="","",AN66*IF(AM66="",$E66,AM66))) | AT66: =IF(AR66="TEC Rejected","",IF(AR66="","",AR66*IF(AQ66="",$E66,AQ66))) | AX66: =IF(AV66="TEC Rejected","",IF(AV66="","",AV66*IF(AU66="",$E66,AU66))) | BB66: =IF(AZ66="TEC Rejected","",IF(AZ66="","",AZ66*IF(AY66="",$E66,AY66))) | BF66: =IF(BD66="TEC Rejected","",IF(BD66="","",BD66*IF(BC66="",$E66,BC66)))
A67: 63 | B67: 63 | C67: X63 | D67: UNIT 08-01 TSG | E67: 4 | F67: 4 | R67: =IF(P67="TEC Rejected","",IF(P67="","",P67*IF(O67="",$E67,O67))) | V67: =IF(T67="TEC Rejected","",IF(T67="","",T67*IF(S67="",$E67,S67))) | Z67: =IF(X67="TEC Rejected","",IF(X67="","",X67*IF(W67="",$E67,W67))) | AD67: =IF(AB67="TEC Rejected","",IF(AB67="","",AB67*IF(AA67="",$E67,AA67))) | AH67: =IF(AF67="TEC Rejected","",IF(AF67="","",AF67*IF(AE67="",$E67,AE67))) | AL67: =IF(AJ67="TEC Rejected","",IF(AJ67="","",AJ67*IF(AI67="",$E67,AI67))) | AP67: =IF(AN67="TEC Rejected","",IF(AN67="","",AN67*IF(AM67="",$E67,AM67))) | AT67: =IF(AR67="TEC Rejected","",IF(AR67="","",AR67*IF(AQ67="",$E67,AQ67))) | AX67: =IF(AV67="TEC Rejected","",IF(AV67="","",AV67*IF(AU67="",$E67,AU67))) | BB67: =IF(AZ67="TEC Rejected","",IF(AZ67="","",AZ67*IF(AY67="",$E67,AY67))) | BF67: =IF(BD67="TEC Rejected","",IF(BD67="","",BD67*IF(BC67="",$E67,BC67)))
A68: 64 | B68: 64 | C68: X64 | D68: UNIT 08-07 US / UNIT | E68: 4 | F68: 4 | R68: =IF(P68="TEC Rejected","",IF(P68="","",P68*IF(O68="",$E68,O68))) | V68: =IF(T68="TEC Rejected","",IF(T68="","",T68*IF(S68="",$E68,S68))) | Z68: =IF(X68="TEC Rejected","",IF(X68="","",X68*IF(W68="",$E68,W68))) | AD68: =IF(AB68="TEC Rejected","",IF(AB68="","",AB68*IF(AA68="",$E68,AA68))) | AH68: =IF(AF68="TEC Rejected","",IF(AF68="","",AF68*IF(AE68="",$E68,AE68))) | AL68: =IF(AJ68="TEC Rejected","",IF(AJ68="","",AJ68*IF(AI68="",$E68,AI68))) | AP68: =IF(AN68="TEC Rejected","",IF(AN68="","",AN68*IF(AM68="",$E68,AM68))) | AT68: =IF(AR68="TEC Rejected","",IF(AR68="","",AR68*IF(AQ68="",$E68,AQ68))) | AX68: =IF(AV68="TEC Rejected","",IF(AV68="","",AV68*IF(AU68="",$E68,AU68))) | BB68: =IF(AZ68="TEC Rejected","",IF(AZ68="","",AZ68*IF(AY68="",$E68,AY68))) | BF68: =IF(BD68="TEC Rejected","",IF(BD68="","",BD68*IF(BC68="",$E68,BC68)))
A69: 65 | B69: 65 | C69: X65 | D69: UNIT 08-03 UF / UNIT | E69: 4 | F69: 4 | R69: =IF(P69="TEC Rejected","",IF(P69="","",P69*IF(O69="",$E69,O69))) | V69: =IF(T69="TEC Rejected","",IF(T69="","",T69*IF(S69="",$E69,S69))) | Z69: =IF(X69="TEC Rejected","",IF(X69="","",X69*IF(W69="",$E69,W69))) | AD69: =IF(AB69="TEC Rejected","",IF(AB69="","",AB69*IF(AA69="",$E69,AA69))) | AH69: =IF(AF69="TEC Rejected","",IF(AF69="","",AF69*IF(AE69="",$E69,AE69))) | AL69: =IF(AJ69="TEC Rejected","",IF(AJ69="","",AJ69*IF(AI69="",$E69,AI69))) | AP69: =IF(AN69="TEC Rejected","",IF(AN69="","",AN69*IF(AM69="",$E69,AM69))) | AT69: =IF(AR69="TEC Rejected","",IF(AR69="","",AR69*IF(AQ69="",$E69,AQ69))) | AX69: =IF(AV69="TEC Rejected","",IF(AV69="","",AV69*IF(AU69="",$E69,AU69))) | BB69: =IF(AZ69="TEC Rejected","",IF(AZ69="","",AZ69*IF(AY69="",$E69,AY69))) | BF69: =IF(BD69="TEC Rejected","",IF(BD69="","",BD69*IF(BC69="",$E69,BC69)))
A70: 66 | B70: 66 | C70: X66 | D70: UNIT 08-04 MOD NKN / MODULATOR | E70: 5 | F70: 5 | R70: =IF(P70="TEC Rejected","",IF(P70="","",P70*IF(O70="",$E70,O70))) | V70: =IF(T70="TEC Rejected","",IF(T70="","",T70*IF(S70="",$E70,S70))) | Z70: =IF(X70="TEC Rejected","",IF(X70="","",X70*IF(W70="",$E70,W70))) | AD70: =IF(AB70="TEC Rejected","",IF(AB70="","",AB70*IF(AA70="",$E70,AA70))) | AH70: =IF(AF70="TEC Rejected","",IF(AF70="","",AF70*IF(AE70="",$E70,AE70))) | AL70: =IF(AJ70="TEC Rejected","",IF(AJ70="","",AJ70*IF(AI70="",$E70,AI70))) | AP70: =IF(AN70="TEC Rejected","",IF(AN70="","",AN70*IF(AM70="",$E70,AM70))) | AT70: =IF(AR70="TEC Rejected","",IF(AR70="","",AR70*IF(AQ70="",$E70,AQ70))) | AX70: =IF(AV70="TEC Rejected","",IF(AV70="","",AV70*IF(AU70="",$E70,AU70))) | BB70: =IF(AZ70="TEC Rejected","",IF(AZ70="","",AZ70*IF(AY70="",$E70,AY70))) | BF70: =IF(BD70="TEC Rejected","",IF(BD70="","",BD70*IF(BC70="",$E70,BC70)))
A71: 67 | B71: 67 | C71: X67 | D71: UNIT 08-06 MP-N / UNIT | E71: 4 | F71: 4 | R71: =IF(P71="TEC Rejected","",IF(P71="","",P71*IF(O71="",$E71,O71))) | V71: =IF(T71="TEC Rejected","",IF(T71="","",T71*IF(S71="",$E71,S71))) | Z71: =IF(X71="TEC Rejected","",IF(X71="","",X71*IF(W71="",$E71,W71))) | AD71: =IF(AB71="TEC Rejected","",IF(AB71="","",AB71*IF(AA71="",$E71,AA71))) | AH71: =IF(AF71="TEC Rejected","",IF(AF71="","",AF71*IF(AE71="",$E71,AE71))) | AL71: =IF(AJ71="TEC Rejected","",IF(AJ71="","",AJ71*IF(AI71="",$E71,AI71))) | AP71: =IF(AN71="TEC Rejected","",IF(AN71="","",AN71*IF(AM71="",$E71,AM71))) | AT71: =IF(AR71="TEC Rejected","",IF(AR71="","",AR71*IF(AQ71="",$E71,AQ71))) | AX71: =IF(AV71="TEC Rejected","",IF(AV71="","",AV71*IF(AU71="",$E71,AU71))) | BB71: =IF(AZ71="TEC Rejected","",IF(AZ71="","",AZ71*IF(AY71="",$E71,AY71))) | BF71: =IF(BD71="TEC Rejected","",IF(BD71="","",BD71*IF(BC71="",$E71,BC71)))
A72: 68 | B72: 68 | C72: X68 | D72: UNIT 08-05 OZU | E72: 5 | F72: 5 | R72: =IF(P72="TEC Rejected","",IF(P72="","",P72*IF(O72="",$E72,O72))) | V72: =IF(T72="TEC Rejected","",IF(T72="","",T72*IF(S72="",$E72,S72))) | Z72: =IF(X72="TEC Rejected","",IF(X72="","",X72*IF(W72="",$E72,W72))) | AD72: =IF(AB72="TEC Rejected","",IF(AB72="","",AB72*IF(AA72="",$E72,AA72))) | AH72: =IF(AF72="TEC Rejected","",IF(AF72="","",AF72*IF(AE72="",$E72,AE72))) | AL72: =IF(AJ72="TEC Rejected","",IF(AJ72="","",AJ72*IF(AI72="",$E72,AI72))) | AP72: =IF(AN72="TEC Rejected","",IF(AN72="","",AN72*IF(AM72="",$E72,AM72))) | AT72: =IF(AR72="TEC Rejected","",IF(AR72="","",AR72*IF(AQ72="",$E72,AQ72))) | AX72: =IF(AV72="TEC Rejected","",IF(AV72="","",AV72*IF(AU72="",$E72,AU72))) | BB72: =IF(AZ72="TEC Rejected","",IF(AZ72="","",AZ72*IF(AY72="",$E72,AY72))) | BF72: =IF(BD72="TEC Rejected","",IF(BD72="","",BD72*IF(BC72="",$E72,BC72)))
A73: 69 | B73: 69 | C73: X69 | D73: UNIT 08-10 SHK / CABINET | E73: 4 | F73: 4 | R73: =IF(P73="TEC Rejected","",IF(P73="","",P73*IF(O73="",$E73,O73))) | V73: =IF(T73="TEC Rejected","",IF(T73="","",T73*IF(S73="",$E73,S73))) | Z73: =IF(X73="TEC Rejected","",IF(X73="","",X73*IF(W73="",$E73,W73))) | AD73: =IF(AB73="TEC Rejected","",IF(AB73="","",AB73*IF(AA73="",$E73,AA73))) | AH73: =IF(AF73="TEC Rejected","",IF(AF73="","",AF73*IF(AE73="",$E73,AE73))) | AL73: =IF(AJ73="TEC Rejected","",IF(AJ73="","",AJ73*IF(AI73="",$E73,AI73))) | AP73: =IF(AN73="TEC Rejected","",IF(AN73="","",AN73*IF(AM73="",$E73,AM73))) | AT73: =IF(AR73="TEC Rejected","",IF(AR73="","",AR73*IF(AQ73="",$E73,AQ73))) | AX73: =IF(AV73="TEC Rejected","",IF(AV73="","",AV73*IF(AU73="",$E73,AU73))) | BB73: =IF(AZ73="TEC Rejected","",IF(AZ73="","",AZ73*IF(AY73="",$E73,AY73))) | BF73: =IF(BD73="TEC Rejected","",IF(BD73="","",BD73*IF(BC73="",$E73,BC73)))
A74: 70 | B74: 70 | C74: X70 | D74: UNIT 08-02 SJ / UNIT | E74: 5 | F74: 5 | R74: =IF(P74="TEC Rejected","",IF(P74="","",P74*IF(O74="",$E74,O74))) | V74: =IF(T74="TEC Rejected","",IF(T74="","",T74*IF(S74="",$E74,S74))) | Z74: =IF(X74="TEC Rejected","",IF(X74="","",X74*IF(W74="",$E74,W74))) | AD74: =IF(AB74="TEC Rejected","",IF(AB74="","",AB74*IF(AA74="",$E74,AA74))) | AH74: =IF(AF74="TEC Rejected","",IF(AF74="","",AF74*IF(AE74="",$E74,AE74))) | AL74: =IF(AJ74="TEC Rejected","",IF(AJ74="","",AJ74*IF(AI74="",$E74,AI74))) | AP74: =IF(AN74="TEC Rejected","",IF(AN74="","",AN74*IF(AM74="",$E74,AM74))) | AT74: =IF(AR74="TEC Rejected","",IF(AR74="","",AR74*IF(AQ74="",$E74,AQ74))) | AX74: =IF(AV74="TEC Rejected","",IF(AV74="","",AV74*IF(AU74="",$E74,AU74))) | BB74: =IF(AZ74="TEC Rejected","",IF(AZ74="","",AZ74*IF(AY74="",$E74,AY74))) | BF74: =IF(BD74="TEC Rejected","",IF(BD74="","",BD74*IF(BC74="",$E74,BC74)))
A75: 71 | B75: 71 | C75: X71 | D75: BACKELITE PLATE | E75: 14 | F75: 14 | O75: 14 | P75: 14400 | R75: =IF(P75="TEC Rejected","",IF(P75="","",P75*IF(O75="",$E75,O75))) -> 201600 | V75: =IF(T75="TEC Rejected","",IF(T75="","",T75*IF(S75="",$E75,S75))) | Z75: =IF(X75="TEC Rejected","",IF(X75="","",X75*IF(W75="",$E75,W75))) | AD75: =IF(AB75="TEC Rejected","",IF(AB75="","",AB75*IF(AA75="",$E75,AA75))) | AH75: =IF(AF75="TEC Rejected","",IF(AF75="","",AF75*IF(AE75="",$E75,AE75))) | AL75: =IF(AJ75="TEC Rejected","",IF(AJ75="","",AJ75*IF(AI75="",$E75,AI75))) | AP75: =IF(AN75="TEC Rejected","",IF(AN75="","",AN75*IF(AM75="",$E75,AM75))) | AT75: =IF(AR75="TEC Rejected","",IF(AR75="","",AR75*IF(AQ75="",$E75,AQ75))) | AX75: =IF(AV75="TEC Rejected","",IF(AV75="","",AV75*IF(AU75="",$E75,AU75))) | BB75: =IF(AZ75="TEC Rejected","",IF(AZ75="","",AZ75*IF(AY75="",$E75,AY75))) | BF75: =IF(BD75="TEC Rejected","",IF(BD75="","",BD75*IF(BC75="",$E75,BC75)))
A76: 72 | B76: 72 | C76: X72 | D76: GASKET | E76: 18 | F76: 18 | O76: 18 | P76: 80 | R76: =IF(P76="TEC Rejected","",IF(P76="","",P76*IF(O76="",$E76,O76))) -> 1440 | S76: 18 | T76: 60.2 | V76: =IF(T76="TEC Rejected","",IF(T76="","",T76*IF(S76="",$E76,S76))) -> 1083.6 | Z76: =IF(X76="TEC Rejected","",IF(X76="","",X76*IF(W76="",$E76,W76))) | AD76: =IF(AB76="TEC Rejected","",IF(AB76="","",AB76*IF(AA76="",$E76,AA76))) | AH76: =IF(AF76="TEC Rejected","",IF(AF76="","",AF76*IF(AE76="",$E76,AE76))) | AL76: =IF(AJ76="TEC Rejected","",IF(AJ76="","",AJ76*IF(AI76="",$E76,AI76))) | AP76: =IF(AN76="TEC Rejected","",IF(AN76="","",AN76*IF(AM76="",$E76,AM76))) | AT76: =IF(AR76="TEC Rejected","",IF(AR76="","",AR76*IF(AQ76="",$E76,AQ76))) | AX76: =IF(AV76="TEC Rejected","",IF(AV76="","",AV76*IF(AU76="",$E76,AU76))) | BB76: =IF(AZ76="TEC Rejected","",IF(AZ76="","",AZ76*IF(AY76="",$E76,AY76))) | BF76: =IF(BD76="TEC Rejected","",IF(BD76="","",BD76*IF(BC76="",$E76,BC76)))
A77: 73 | B77: 73 | C77: X73 | D77: WAVEGUIDE | E77: 5 | F77: 5 | R77: =IF(P77="TEC Rejected","",IF(P77="","",P77*IF(O77="",$E77,O77))) | V77: =IF(T77="TEC Rejected","",IF(T77="","",T77*IF(S77="",$E77,S77))) | Z77: =IF(X77="TEC Rejected","",IF(X77="","",X77*IF(W77="",$E77,W77))) | AD77: =IF(AB77="TEC Rejected","",IF(AB77="","",AB77*IF(AA77="",$E77,AA77))) | AH77: =IF(AF77="TEC Rejected","",IF(AF77="","",AF77*IF(AE77="",$E77,AE77))) | AL77: =IF(AJ77="TEC Rejected","",IF(AJ77="","",AJ77*IF(AI77="",$E77,AI77))) | AP77: =IF(AN77="TEC Rejected","",IF(AN77="","",AN77*IF(AM77="",$E77,AM77))) | AT77: =IF(AR77="TEC Rejected","",IF(AR77="","",AR77*IF(AQ77="",$E77,AQ77))) | AX77: =IF(AV77="TEC Rejected","",IF(AV77="","",AV77*IF(AU77="",$E77,AU77))) | BB77: =IF(AZ77="TEC Rejected","",IF(AZ77="","",AZ77*IF(AY77="",$E77,AY77))) | BF77: =IF(BD77="TEC Rejected","",IF(BD77="","",BD77*IF(BC77="",$E77,BC77)))
A78: 74 | B78: 74 | C78: X74 | D78: CIRCULATOR | E78: 5 | F78: 5 | O78: 5 | P78: 4440 | R78: =IF(P78="TEC Rejected","",IF(P78="","",P78*IF(O78="",$E78,O78))) -> 22200 | S78: 5 | T78: 6350 | V78: =IF(T78="TEC Rejected","",IF(T78="","",T78*IF(S78="",$E78,S78))) -> 31750 | Z78: =IF(X78="TEC Rejected","",IF(X78="","",X78*IF(W78="",$E78,W78))) | AD78: =IF(AB78="TEC Rejected","",IF(AB78="","",AB78*IF(AA78="",$E78,AA78))) | AH78: =IF(AF78="TEC Rejected","",IF(AF78="","",AF78*IF(AE78="",$E78,AE78))) | AL78: =IF(AJ78="TEC Rejected","",IF(AJ78="","",AJ78*IF(AI78="",$E78,AI78))) | AP78: =IF(AN78="TEC Rejected","",IF(AN78="","",AN78*IF(AM78="",$E78,AM78))) | AT78: =IF(AR78="TEC Rejected","",IF(AR78="","",AR78*IF(AQ78="",$E78,AQ78))) | AX78: =IF(AV78="TEC Rejected","",IF(AV78="","",AV78*IF(AU78="",$E78,AU78))) | BB78: =IF(AZ78="TEC Rejected","",IF(AZ78="","",AZ78*IF(AY78="",$E78,AY78))) | BF78: =IF(BD78="TEC Rejected","",IF(BD78="","",BD78*IF(BC78="",$E78,BC78)))
A79: 75 | B79: 75 | C79: X75 | D79: THROTTLE | E79: 10 | F79: 10 | R79: =IF(P79="TEC Rejected","",IF(P79="","",P79*IF(O79="",$E79,O79))) | V79: =IF(T79="TEC Rejected","",IF(T79="","",T79*IF(S79="",$E79,S79))) | Z79: =IF(X79="TEC Rejected","",IF(X79="","",X79*IF(W79="",$E79,W79))) | AD79: =IF(AB79="TEC Rejected","",IF(AB79="","",AB79*IF(AA79="",$E79,AA79))) | AH79: =IF(AF79="TEC Rejected","",IF(AF79="","",AF79*IF(AE79="",$E79,AE79))) | AL79: =IF(AJ79="TEC Rejected","",IF(AJ79="","",AJ79*IF(AI79="",$E79,AI79))) | AP79: =IF(AN79="TEC Rejected","",IF(AN79="","",AN79*IF(AM79="",$E79,AM79))) | AT79: =IF(AR79="TEC Rejected","",IF(AR79="","",AR79*IF(AQ79="",$E79,AQ79))) | AX79: =IF(AV79="TEC Rejected","",IF(AV79="","",AV79*IF(AU79="",$E79,AU79))) | BB79: =IF(AZ79="TEC Rejected","",IF(AZ79="","",AZ79*IF(AY79="",$E79,AY79))) | BF79: =IF(BD79="TEC Rejected","",IF(BD79="","",BD79*IF(BC79="",$E79,BC79)))
A80: 76 | B80: 76 | C80: X76 | D80: PRESSURE ADAPTER | E80: 3 | F80: 3 | R80: =IF(P80="TEC Rejected","",IF(P80="","",P80*IF(O80="",$E80,O80))) | V80: =IF(T80="TEC Rejected","",IF(T80="","",T80*IF(S80="",$E80,S80))) | Z80: =IF(X80="TEC Rejected","",IF(X80="","",X80*IF(W80="",$E80,W80))) | AD80: =IF(AB80="TEC Rejected","",IF(AB80="","",AB80*IF(AA80="",$E80,AA80))) | AH80: =IF(AF80="TEC Rejected","",IF(AF80="","",AF80*IF(AE80="",$E80,AE80))) | AL80: =IF(AJ80="TEC Rejected","",IF(AJ80="","",AJ80*IF(AI80="",$E80,AI80))) | AP80: =IF(AN80="TEC Rejected","",IF(AN80="","",AN80*IF(AM80="",$E80,AM80))) | AT80: =IF(AR80="TEC Rejected","",IF(AR80="","",AR80*IF(AQ80="",$E80,AQ80))) | AX80: =IF(AV80="TEC Rejected","",IF(AV80="","",AV80*IF(AU80="",$E80,AU80))) | BB80: =IF(AZ80="TEC Rejected","",IF(AZ80="","",AZ80*IF(AY80="",$E80,AY80))) | BF80: =IF(BD80="TEC Rejected","",IF(BD80="","",BD80*IF(BC80="",$E80,BC80)))
A81: 77 | B81: 77 | C81: X77 | D81: CUP WASHER | E81: 11 | F81: 11 | R81: =IF(P81="TEC Rejected","",IF(P81="","",P81*IF(O81="",$E81,O81))) | V81: =IF(T81="TEC Rejected","",IF(T81="","",T81*IF(S81="",$E81,S81))) | Z81: =IF(X81="TEC Rejected","",IF(X81="","",X81*IF(W81="",$E81,W81))) | AD81: =IF(AB81="TEC Rejected","",IF(AB81="","",AB81*IF(AA81="",$E81,AA81))) | AH81: =IF(AF81="TEC Rejected","",IF(AF81="","",AF81*IF(AE81="",$E81,AE81))) | AL81: =IF(AJ81="TEC Rejected","",IF(AJ81="","",AJ81*IF(AI81="",$E81,AI81))) | AP81: =IF(AN81="TEC Rejected","",IF(AN81="","",AN81*IF(AM81="",$E81,AM81))) | AT81: =IF(AR81="TEC Rejected","",IF(AR81="","",AR81*IF(AQ81="",$E81,AQ81))) | AX81: =IF(AV81="TEC Rejected","",IF(AV81="","",AV81*IF(AU81="",$E81,AU81))) | BB81: =IF(AZ81="TEC Rejected","",IF(AZ81="","",AZ81*IF(AY81="",$E81,AY81))) | BF81: =IF(BD81="TEC Rejected","",IF(BD81="","",BD81*IF(BC81="",$E81,BC81)))
A82: 78 | B82: 78 | C82: X78 | D82: CONTACT PACKING | E82: 20 | F82: 20 | O82: 20 | P82: 5100 | R82: =IF(P82="TEC Rejected","",IF(P82="","",P82*IF(O82="",$E82,O82))) -> 102000 | V82: =IF(T82="TEC Rejected","",IF(T82="","",T82*IF(S82="",$E82,S82))) | Z82: =IF(X82="TEC Rejected","",IF(X82="","",X82*IF(W82="",$E82,W82))) | AD82: =IF(AB82="TEC Rejected","",IF(AB82="","",AB82*IF(AA82="",$E82,AA82))) | AH82: =IF(AF82="TEC Rejected","",IF(AF82="","",AF82*IF(AE82="",$E82,AE82))) | AL82: =IF(AJ82="TEC Rejected","",IF(AJ82="","",AJ82*IF(AI82="",$E82,AI82))) | AP82: =IF(AN82="TEC Rejected","",IF(AN82="","",AN82*IF(AM82="",$E82,AM82))) | AT82: =IF(AR82="TEC Rejected","",IF(AR82="","",AR82*IF(AQ82="",$E82,AQ82))) | AX82: =IF(AV82="TEC Rejected","",IF(AV82="","",AV82*IF(AU82="",$E82,AU82))) | BB82: =IF(AZ82="TEC Rejected","",IF(AZ82="","",AZ82*IF(AY82="",$E82,AY82))) | BF82: =IF(BD82="TEC Rejected","",IF(BD82="","",BD82*IF(BC82="",$E82,BC82)))
A83: 79 | B83: 79 | C83: X79 | D83: GASKET | E83: 16 | F83: 16 | O83: 16 | P83: 85 | R83: =IF(P83="TEC Rejected","",IF(P83="","",P83*IF(O83="",$E83,O83))) -> 1360 | S83: 16 | T83: 95 | V83: =IF(T83="TEC Rejected","",IF(T83="","",T83*IF(S83="",$E83,S83))) -> 1520 | Z83: =IF(X83="TEC Rejected","",IF(X83="","",X83*IF(W83="",$E83,W83))) | AD83: =IF(AB83="TEC Rejected","",IF(AB83="","",AB83*IF(AA83="",$E83,AA83))) | AH83: =IF(AF83="TEC Rejected","",IF(AF83="","",AF83*IF(AE83="",$E83,AE83))) | AL83: =IF(AJ83="TEC Rejected","",IF(AJ83="","",AJ83*IF(AI83="",$E83,AI83))) | AP83: =IF(AN83="TEC Rejected","",IF(AN83="","",AN83*IF(AM83="",$E83,AM83))) | AT83: =IF(AR83="TEC Rejected","",IF(AR83="","",AR83*IF(AQ83="",$E83,AQ83))) | AX83: =IF(AV83="TEC Rejected","",IF(AV83="","",AV83*IF(AU83="",$E83,AU83))) | BB83: =IF(AZ83="TEC Rejected","",IF(AZ83="","",AZ83*IF(AY83="",$E83,AY83))) | BF83: =IF(BD83="TEC Rejected","",IF(BD83="","",BD83*IF(BC83="",$E83,BC83)))
A84: 80 | B84: 80 | C84: X80 | D84: ARTICLE DOCTOR | E84: 4 | F84: 4 | R84: =IF(P84="TEC Rejected","",IF(P84="","",P84*IF(O84="",$E84,O84))) | V84: =IF(T84="TEC Rejected","",IF(T84="","",T84*IF(S84="",$E84,S84))) | Z84: =IF(X84="TEC Rejected","",IF(X84="","",X84*IF(W84="",$E84,W84))) | AD84: =IF(AB84="TEC Rejected","",IF(AB84="","",AB84*IF(AA84="",$E84,AA84))) | AH84: =IF(AF84="TEC Rejected","",IF(AF84="","",AF84*IF(AE84="",$E84,AE84))) | AL84: =IF(AJ84="TEC Rejected","",IF(AJ84="","",AJ84*IF(AI84="",$E84,AI84))) | AP84: =IF(AN84="TEC Rejected","",IF(AN84="","",AN84*IF(AM84="",$E84,AM84))) | AT84: =IF(AR84="TEC Rejected","",IF(AR84="","",AR84*IF(AQ84="",$E84,AQ84))) | AX84: =IF(AV84="TEC Rejected","",IF(AV84="","",AV84*IF(AU84="",$E84,AU84))) | BB84: =IF(AZ84="TEC Rejected","",IF(AZ84="","",AZ84*IF(AY84="",$E84,AY84))) | BF84: =IF(BD84="TEC Rejected","",IF(BD84="","",BD84*IF(BC84="",$E84,BC84)))
A85: 81 | B85: 81 | C85: X81 | D85: MAGNET AMPLIFIER | E85: 5 | F85: 5 | O85: 5 | P85: 7500 | R85: =IF(P85="TEC Rejected","",IF(P85="","",P85*IF(O85="",$E85,O85))) -> 37500 | V85: =IF(T85="TEC Rejected","",IF(T85="","",T85*IF(S85="",$E85,S85))) | Z85: =IF(X85="TEC Rejected","",IF(X85="","",X85*IF(W85="",$E85,W85))) | AD85: =IF(AB85="TEC Rejected","",IF(AB85="","",AB85*IF(AA85="",$E85,AA85))) | AH85: =IF(AF85="TEC Rejected","",IF(AF85="","",AF85*IF(AE85="",$E85,AE85))) | AL85: =IF(AJ85="TEC Rejected","",IF(AJ85="","",AJ85*IF(AI85="",$E85,AI85))) | AP85: =IF(AN85="TEC Rejected","",IF(AN85="","",AN85*IF(AM85="",$E85,AM85))) | AT85: =IF(AR85="TEC Rejected","",IF(AR85="","",AR85*IF(AQ85="",$E85,AQ85))) | AX85: =IF(AV85="TEC Rejected","",IF(AV85="","",AV85*IF(AU85="",$E85,AU85))) | BB85: =IF(AZ85="TEC Rejected","",IF(AZ85="","",AZ85*IF(AY85="",$E85,AY85))) | BF85: =IF(BD85="TEC Rejected","",IF(BD85="","",BD85*IF(BC85="",$E85,BC85)))
A86: 82 | B86: 82 | C86: X82 | D86: Bushing | E86: 6 | F86: 6 | R86: =IF(P86="TEC Rejected","",IF(P86="","",P86*IF(O86="",$E86,O86))) | V86: =IF(T86="TEC Rejected","",IF(T86="","",T86*IF(S86="",$E86,S86))) | Z86: =IF(X86="TEC Rejected","",IF(X86="","",X86*IF(W86="",$E86,W86))) | AD86: =IF(AB86="TEC Rejected","",IF(AB86="","",AB86*IF(AA86="",$E86,AA86))) | AH86: =IF(AF86="TEC Rejected","",IF(AF86="","",AF86*IF(AE86="",$E86,AE86))) | AL86: =IF(AJ86="TEC Rejected","",IF(AJ86="","",AJ86*IF(AI86="",$E86,AI86))) | AP86: =IF(AN86="TEC Rejected","",IF(AN86="","",AN86*IF(AM86="",$E86,AM86))) | AT86: =IF(AR86="TEC Rejected","",IF(AR86="","",AR86*IF(AQ86="",$E86,AQ86))) | AX86: =IF(AV86="TEC Rejected","",IF(AV86="","",AV86*IF(AU86="",$E86,AU86))) | BB86: =IF(AZ86="TEC Rejected","",IF(AZ86="","",AZ86*IF(AY86="",$E86,AY86))) | BF86: =IF(BD86="TEC Rejected","",IF(BD86="","",BD86*IF(BC86="",$E86,BC86)))
A87: 83 | B87: 83 | C87: X83 | D87: Collet | E87: 9 | F87: 9 | G87: TEC Rejected | H87: TEC Rejected | I87: TEC Rejected | J87: TEC Rejected | K87: TEC Rejected | L87: TEC Rejected | M87: TEC Rejected | N87: TEC Rejected | R87: =IF(P87="TEC Rejected","",IF(P87="","",P87*IF(O87="",$E87,O87))) | V87: =IF(T87="TEC Rejected","",IF(T87="","",T87*IF(S87="",$E87,S87))) | Z87: =IF(X87="TEC Rejected","",IF(X87="","",X87*IF(W87="",$E87,W87))) | AD87: =IF(AB87="TEC Rejected","",IF(AB87="","",AB87*IF(AA87="",$E87,AA87))) | AH87: =IF(AF87="TEC Rejected","",IF(AF87="","",AF87*IF(AE87="",$E87,AE87))) | AL87: =IF(AJ87="TEC Rejected","",IF(AJ87="","",AJ87*IF(AI87="",$E87,AI87))) | AP87: =IF(AN87="TEC Rejected","",IF(AN87="","",AN87*IF(AM87="",$E87,AM87))) | AT87: =IF(AR87="TEC Rejected","",IF(AR87="","",AR87*IF(AQ87="",$E87,AQ87))) | AX87: =IF(AV87="TEC Rejected","",IF(AV87="","",AV87*IF(AU87="",$E87,AU87))) | BB87: =IF(AZ87="TEC Rejected","",IF(AZ87="","",AZ87*IF(AY87="",$E87,AY87))) | BF87: =IF(BD87="TEC Rejected","",IF(BD87="","",BD87*IF(BC87="",$E87,BC87)))
A88: 84 | B88: 84 | C88: X84 | D88: Handle | E88: 9 | F88: 9 | R88: =IF(P88="TEC Rejected","",IF(P88="","",P88*IF(O88="",$E88,O88))) | V88: =IF(T88="TEC Rejected","",IF(T88="","",T88*IF(S88="",$E88,S88))) | Z88: =IF(X88="TEC Rejected","",IF(X88="","",X88*IF(W88="",$E88,W88))) | AD88: =IF(AB88="TEC Rejected","",IF(AB88="","",AB88*IF(AA88="",$E88,AA88))) | AH88: =IF(AF88="TEC Rejected","",IF(AF88="","",AF88*IF(AE88="",$E88,AE88))) | AL88: =IF(AJ88="TEC Rejected","",IF(AJ88="","",AJ88*IF(AI88="",$E88,AI88))) | AP88: =IF(AN88="TEC Rejected","",IF(AN88="","",AN88*IF(AM88="",$E88,AM88))) | AT88: =IF(AR88="TEC Rejected","",IF(AR88="","",AR88*IF(AQ88="",$E88,AQ88))) | AX88: =IF(AV88="TEC Rejected","",IF(AV88="","",AV88*IF(AU88="",$E88,AU88))) | BB88: =IF(AZ88="TEC Rejected","",IF(AZ88="","",AZ88*IF(AY88="",$E88,AY88))) | BF88: =IF(BD88="TEC Rejected","",IF(BD88="","",BD88*IF(BC88="",$E88,BC88)))
A89: 85 | B89: 85 | C89: X85 | D89: SCREW | E89: 10 | F89: 10 | R89: =IF(P89="TEC Rejected","",IF(P89="","",P89*IF(O89="",$E89,O89))) | V89: =IF(T89="TEC Rejected","",IF(T89="","",T89*IF(S89="",$E89,S89))) | Z89: =IF(X89="TEC Rejected","",IF(X89="","",X89*IF(W89="",$E89,W89))) | AD89: =IF(AB89="TEC Rejected","",IF(AB89="","",AB89*IF(AA89="",$E89,AA89))) | AH89: =IF(AF89="TEC Rejected","",IF(AF89="","",AF89*IF(AE89="",$E89,AE89))) | AL89: =IF(AJ89="TEC Rejected","",IF(AJ89="","",AJ89*IF(AI89="",$E89,AI89))) | AP89: =IF(AN89="TEC Rejected","",IF(AN89="","",AN89*IF(AM89="",$E89,AM89))) | AT89: =IF(AR89="TEC Rejected","",IF(AR89="","",AR89*IF(AQ89="",$E89,AQ89))) | AX89: =IF(AV89="TEC Rejected","",IF(AV89="","",AV89*IF(AU89="",$E89,AU89))) | BB89: =IF(AZ89="TEC Rejected","",IF(AZ89="","",AZ89*IF(AY89="",$E89,AY89))) | BF89: =IF(BD89="TEC Rejected","",IF(BD89="","",BD89*IF(BC89="",$E89,BC89)))
J90: =SUM(J5:J89) -> 0 | N90: =SUM(N5:N89) -> 0 | R90: =SUM(R5:R89) -> 960155.3 | V90: =SUM(V5:V89) -> 877882.8 | Z90: =SUM(Z5:Z89) -> 0 | AD90: =SUM(AD5:AD89) -> 1280145 | AH90: =SUM(AH5:AH89) -> 0 | AL90: =SUM(AL5:AL89) -> 1146811 | AP90: =SUM(AP5:AP89) -> 0 | AT90: =SUM(AT5:AT89) -> 0 | AX90: =SUM(AX5:AX89) -> 0 | BB90: =SUM(BB5:BB89) -> 0 | BF90: =SUM(BF5:BF89) -> 0 | BG90: Total | BN90: =SUM(#REF!) -> #REF! | BO90: =SUM(#REF!) -> #REF! | BP90: =(BN90-BO90)/BO90 -> #REF!
BG91: Basic Total Cost in INR @ 1USD = 75.64 INR =(A) | BN91: =ROUND(BN90*75.644399,2) -> #REF! | BO91: =ROUND(BO90*75.644399,2) -> #REF!
V92: Duty calculation under CTH :88039000 | BG92: Assessable value (100% of import value) (A X 100% in INR) =(B) | BN92: =ROUND(BN91*100%,2) -> #REF! | BO92: =ROUND(BO91*100%,2) -> #REF!
BG93: Basic Custom Duty @ 10% on assassable value (B X 10%) =(C) | BN93: =ROUND(BN92*10%,2) -> #REF! | BO93: =ROUND(BO92*10%,2) -> #REF!
BG94: Social Welfare Surcharge on Basic Cutom duty @ 10% on BCD (C X 10%) =(D) | BN94: =ROUND(BN93*10%,2) -> #REF! | BO94: =ROUND(BO93*10%,2) -> #REF!
BG95: IGST @ 5% on (B+C+D) X 5% =(E) | BN95: =ROUND((BN92+BN93+BN94)*5%,2) -> #REF! | BO95: =ROUND((BO92+BO93+BO94)*5%,2) -> #REF!
BG96: Total Customs and other duties in INR (C+D+E) =(F) | BN96: =BN93+BN94+BN95 -> #REF! | BO96: =BO93+BO94+BO95 -> #REF!
BG97: F & I (1.26% of BasicTotal Cost in INR) (A X 1.26%) =(G) (For transport from Mumbai to Ojhar, Nasik. However payment will be made on actuals) | BN97: =ROUND(BN91*1.26%,2) -> #REF! | BO97: =ROUND(BO91*1.26%,2) -> #REF!
BG98: Final Landed Cost in INR (A+F+G) =(H) | BN98: =BN91+BN96+BN97 -> #REF! | BO98: =BO91+BO96+BO97 -> #REF!
BG99: Final Landed Cost in INR Lakhs =(I) | BN99: =ROUND(BN98/100000,2) -> #REF! | BO99: =ROUND(BO98/100000,2) -> #REF!
BI106: M. H. Kokitkar DGM (IMM-O) | BM106: S.D. Pande AGM (IMM)-O

Sheet CST-Final
A1: =CONCATENATE("Price Comparision Statement Against Indent ",Form!D2) -> Price Comparision Statement Against Indent abcd001 | AZ1: =IF(MAX(A4:A430)=MAX(B4:B430),"",VLOOKUP(1,A:BB,51,FALSE)) | BP1: =IF(VLOOKUP(1,A:BY,40,FALSE)=0,"","LPP/APPROVED:") -> LPP/APPROVED: | BT1: Annex-i
A2: RFQ DETAILS | G2: ='CST-Calculation'!G2 -> Aviation Equipment | K2: ='CST-Calculation'!K2 -> Avitronic Ltd, Russia | O2: ='CST-Calculation'!O2 -> GIS | S2: ='CST-Calculation'!S2 -> INDO AVIA SERVICES LTD | W2: ='CST-Calculation'!W2 -> AEC (AEC) | AA2: ='CST-Calculation'!AA2 -> ADRYS Technologies (ADRYS) | AE2: ='CST-Calculation'!AE2 -> AVIAZAPCHAST (AZP) | AI2: ='CST-Calculation'!AI2 -> Eurasia Special Technologies (EST) | AM2: ='CST-Calculation'!AM2 -> NASC (NASC) | AQ2: ='CST-Calculation'!AQ2 -> ROE (ROE) | AU2: ='CST-Calculation'!AU2 -> VEKS-M | AY2: L1 DETAILS | BF2: ESTIMATION DETAILS (LPP) if any | BK2: APPROVED ESTIMATION DETAILS | BP2: =IF(VLOOKUP(1,A:BY,40,FALSE)=0,"PRICE ANALYSIS","ORIGINAL PRICE ANALYSIS") -> ORIGINAL PRICE ANALYSIS | BU2: PRICE ANALYSIS AFTER PNC
H3: ='CST-Calculation'!H3 -> Avi. Equip. | L3: ='CST-Calculation'!L3 -> Avitronic | P3: ='CST-Calculation'!P3 -> GIS | T3: ='CST-Calculation'!T3 -> IASL | X3: ='CST-Calculation'!X3 -> AEC | AB3: ='CST-Calculation'!AB3 -> ADRYS | AF3: ='CST-Calculation'!AF3 -> AZP | AJ3: ='CST-Calculation'!AJ3 -> EST | AN3: ='CST-Calculation'!AN3 -> NASC | AR3: ='CST-Calculation'!AR3 -> ROE | AV3: ='CST-Calculation'!AV3 -> VEKS-M
A4: Sl No | B4: IND. Sl. No. | C4: PART NO | D4: DESCRIPTION | E4: QTY | F4: Revised QTY | G4: QTY | H4: Unit Price (USD) | I4: Level Unit Cost (INR.) | J4: Total Price (CTC) (INR) | K4: QTY | L4: Unit Price (USD) | M4: Level Unit Cost (INR.) | N4: Total Price (CTC) (INR) | O4: QTY | P4: Unit Price (USD) | Q4: Level Unit Cost (INR.) | R4: Total Price (CTC) (INR) | S4: QTY | T4: Unit Price (USD) | U4: Level Unit Cost (INR.) | V4: Total Price (CTC) (INR) | W4: QTY | X4: Unit Price (USD) | Y4: Level Unit Cost (INR.) | Z4: Total Price (CTC) (INR) | AA4: QTY | AB4: Unit Price (INR) | AC4: Level Unit Cost (INR.) | AD4: Total Price (CTC) (INR) | AE4: QTY | AF4: Unit Price (USD) | AG4: Level Unit Cost (INR.) | AH4: Total Price (CTC) (INR) | AI4: QTY | AJ4: Unit Price (INR) | AK4: Level Unit Cost (INR.) | AL4: Total Price (CTC) (INR) | AM4: QTY | AN4: Unit Price (USD) | AO4: Level Unit Cost (INR.) | AP4: Total Price (CTC) (INR) | AQ4: QTY | AR4: Unit Price (USD) | AS4: Level Unit Cost (INR.) | AT4: Total Price (CTC) (INR) | AU4: QTY | AV4: Unit Price (USD) | AW4: Level Unit Cost (INR.) | AX4: Total Price (CTC) (INR) | AY4: L1 AGENCY | AZ4: OFFER TYPE | BA4: MOQ Status in Excess to Indent Qty | BB4: L1 Unit PRICE (USD/INR) | BC4: L1 Total PRICE (USD/INR) | BD4: Level L1 Unit PRICE (INR) | BE4: Level L1 Total PRICE (INR) | BF4: REF SA Price(USD) | BG4: REF SA | BH4: REF SA Date | BI4: EST Unit Price (USD/INR) @ 2024 level | BJ4: Levelled EST Unit Price (INR) @ 2024 level | BK4: REF SA Price | BL4: REF SA | BM4: REF SA Date | BN4: EST Unit Price (USD) @ 2024 level | BO4: Levelled EST Unit Price (INR) @ 2024 level | BP4: L1 TOTAL Price (USD) @ 2024 level | BQ4: EST.TOTAL Price (USD) @ 2024 level | BR4: Levelled L1 TOTAL Price (INR) @ 2024 level | BS4: Levelled EST.TOTAL Apprvd Estimated Price (INR) @ 2024 level | BT4: Offered Price w.r.t Est Price (in%) | BU4: L1 UNIT Price (USD/RS) @ 2024 level | BV4: L1 TOTAL Price (USD/Rs) @ 2024 level | BW4: Levelled L1 UNIT Price (Rs) @ 2024 level | BX4: Levelled L1 TOTAL Price (Rs) @ 2024 level | BY4: Offered Price w.r.t Est Price (in%) | BZ4: Levelled EST.TOTAL LPP Price (INR) @ 2024 level | CA4: After PNC Deleted | CB4: Reason for deletion | CC4: Price Change | CD4: Project | CE4: Remarks(Do not Delete) | CF4: Techncal Estimate File no | CG4: File No. | CH4: MPR No. | CI4: MPR Date
A5: =SUBTOTAL(2,$B$5:B5) -> 1 | B5: 1 | C5: X1 | D5: OPERATIONAL AMPLIFIER | E5: 7 | F5: ='Annexure-I'!E2 -> 7 | G5: =IF('CST-Calculation'!G5=0,"",'CST-Calculation'!G5) | H5: =IF('CST-Calculation'!H5=0,"",'CST-Calculation'!H5) | I5: =IF(G5="","",IF(H5="TEC Rejected","",IF(H5="","",ROUND(1.3224*Form!$D$10*H5,2)))) | J5: =IF(G5="","",IF(H5="TEC Rejected","",IF(H5="","",ROUND(G5*I5,2)))) | K5: =IF(L5="","",IF('Annexure-I'!$E2="Indg","",IF('Annexure-I'!$E2="TEC Del","",IF('Annexure-I'!$E2=0,"",IF('CST-Calculation'!K5<>0,'CST-Calculation'!K5,'Annexure-I'!$E2))))) | L5: =IF('CST-Calculation'!L5=0,"",'CST-Calculation'!L5) | M5: =IF(K5="","",IF(L5="TEC Rejected","",IF(L5="","",ROUND(1.3224*Form!$D$10*L5,2)))) | N5: =IF(K5="","",IF(L5="TEC Rejected","",IF(L5="","",ROUND(K5*M5,2)))) | O5: =IF(P5="","",IF('Annexure-I'!$E2="Indg","",IF('Annexure-I'!$E2="TEC Del","",IF('Annexure-I'!$E2=0,"",IF('CST-Calculation'!O5<>0,'CST-Calculation'!O5,'Annexure-I'!$E2))))) -> 7 | P5: =IF('CST-Calculation'!P5=0,"",'CST-Calculation'!P5) -> 15.9 | Q5: =IF(O5="","",IF(P5="TEC Rejected","",IF(P5="","",ROUND(1.3224*Form!$D$10*P5,2)))) -> 1740.55 | R5: =IF(O5="","",IF(P5="TEC Rejected","",IF(P5="","",ROUND(O5*Q5,2)))) -> 12183.85 | S5: =IF(T5="","",IF('Annexure-I'!$E2="Indg","",IF('Annexure-I'!$E2="TEC Del","",IF('Annexure-I'!$E2=0,"",IF('CST-Calculation'!S5<>0,'CST-Calculation'!S5,'Annexure-I'!$E2))))) -> 7 | T5: =IF('CST-Calculation'!T5=0,"",'CST-Calculation'!T5) -> 27.5 | U5: =IF(S5="","",IF(T5="TEC Rejected","",IF(T5="","",ROUND(1.3224*Form!$D$10*T5,2)))) -> 3010.38 | V5: =IF(S5="","",IF(T5="TEC Rejected","",IF(T5="","",ROUND(S5*U5,2)))) -> 21072.66 | W5: =IF(X5="","",IF('Annexure-I'!$E2="Indg","",IF('Annexure-I'!$E2="TEC Del","",IF('Annexure-I'!$E2=0,"",IF('CST-Calculation'!W5<>0,'CST-Calculation'!W5,'Annexure-I'!$E2))))) | X5: =IF('CST-Calculation'!X5=0,"",'CST-Calculation'!X5) | Y5: =IF(W5="","",IF(X5="TEC Rejected","",IF(X5="","",ROUND(1.3224*Form!$D$10*X5,2)))) | Z5: =IF(W5="","",IF(X5="TEC Rejected","",IF(X5="","",ROUND(W5*Y5,2)))) | AA5: =IF(AB5="","",IF('Annexure-I'!$E2="Indg","",IF('Annexure-I'!$E2="TEC Del","",IF('Annexure-I'!$E2=0,"",IF('CST-Calculation'!AA5<>0,'CST-Calculation'!AA5,'Annexure-I'!$E2))))) -> 7 | AB5: =IF('CST-Calculation'!AB5=0,"",'CST-Calculation'!AB5) -> 915 | AC5: =IF(AA5="","",IF(AB5="TEC Rejected","",IF(AB5="","",ROUND(1.18*AB5,2)))) -> 1079.7 | AD5: =IF(AA5="","",IF(AB5="TEC Rejected","",IF(AB5="","",ROUND(AA5*AC5,2)))) -> 7557.9 | AE5: =IF(AF5="","",IF('Annexure-I'!$E2="Indg","",IF('Annexure-I'!$E2="TEC Del","",IF('Annexure-I'!$E2=0,"",IF('CST-Calculation'!AE5<>0,'CST-Calculation'!AE5,'Annexure-I'!$E2))))) | AF5: =IF('CST-Calculation'!AF5=0,"",'CST-Calculation'!AF5) | AG5: =IF(AE5="","",IF(AF5="TEC Rejected","",IF(AF5="","",ROUND(1.3224*Form!$D$10*AF5,2)))) | AH5: =IF(AE5="","",IF(AF5="TEC Rejected","",IF(AF5="","",ROUND(AE5*AG5,2)))) | AI5: =IF(AJ5="","",IF('Annexure-I'!$E2="Indg","",IF('Annexure-I'!$E2="TEC Del","",IF('Annexure-I'!$E2=0,"",IF('CST-Calculation'!AI5<>0,'CST-Calculation'!AI5,'Annexure-I'!$E2))))) | AJ5: =IF('CST-Calculation'!AJ5=0,"",'CST-Calculation'!AJ5) | AK5: =IF(AI5="","",IF(AJ5="TEC Rejected","",IF(AJ5="","",ROUND(1.18*AJ5,2)))) | AL5: =IF(AI5="","",IF(AJ5="TEC Rejected","",IF(AJ5="","",ROUND(AI5*AK5,2)))) | AM5: =IF(AN5="","",IF('Annexure-I'!$E2="Indg","",IF('Annexure-I'!$E2="TEC Del","",IF('Annexure-I'!$E2=0,"",IF('CST-Calculation'!AM5<>0,'CST-Calculation'!AM5,'Annexure-I'!$E2))))) | AN5: =IF('CST-Calculation'!AN5=0,"",'CST-Calculation'!AN5) | AO5: =IF(AM5="","",IF(AN5="TEC Rejected","",IF(AN5="","",ROUND(1.3224*Form!$D$10*AN5,2)))) | AP5: =IF(AM5="","",IF(AN5="TEC Rejected","",IF(AN5="","",ROUND(AM5*AO5,2)))) | AQ5: =IF(AR5="","",IF('Annexure-I'!$E2="Indg","",IF('Annexure-I'!$E2="TEC Del","",IF('Annexure-I'!$E2=0,"",IF('CST-Calculation'!AQ5<>0,'CST-Calculation'!AQ5,'Annexure-I'!$E2))))) | AR5: =IF('CST-Calculation'!AR5=0,"",'CST-Calculation'!AR5) | AS5: =IF(AQ5="","",IF(AR5="TEC Rejected","",IF(AR5="","",ROUND(1.3224*Form!$D$10*AR5,2)))) | AT5: =IF(AQ5="","",IF(AR5="TEC Rejected","",IF(AR5="","",ROUND(AQ5*AS5,2)))) | AU5: =IF(AV5="","",IF('Annexure-I'!$E2="Indg","",IF('Annexure-I'!$E2="TEC Del","",IF('Annexure-I'!$E2=0,"",IF('CST-Calculation'!AU5<>0,'CST-Calculation'!AU5,'Annexure-I'!$E2))))) | AV5: =IF('CST-Calculation'!AV5=0,"",'CST-Calculation'!AV5) | AW5: =IF(AU5="","",IF(AV5="TEC Rejected","",IF(AV5="","",ROUND(1.3224*Form!$D$10*AV5,2)))) | AX5: =IF(AU5="","",IF(AV5="TEC Rejected","",IF(AV5="","",ROUND(AU5*AW5,2)))) | AY5: =IF(F5="Indg","INDG",IF(F5="TEC Del","DELETED",IF(F5=0,"DELETED",IF(BD5=0,"NO OFFER",IF(BD5=I5,$H$3,IF(BD5=M5,$L$3,IF(BD5=Q5,$P$3,IF(BD5=U5,$T$3,IF(BD5=Y5,$X$3,IF(BD5=AC5,$AB$3,IF(BD5=AG5,$AF$3,IF(BD5=AK5,$AJ$3,IF(BD5=AO5,$AN$3,IF(BD5=AS5,$AR$3,IF(BD5=AW5,$AV$3))))))))))))))) -> ADRYS | AZ5: =IF(F5=0,"DELETED",IF(COUNT(H5,L5,P5,T5,X5,AB5,AF5,AJ5,AN5,AR5,AV5)=0,"NO OFFER",IF(COUNT(H5,L5,P5,T5,X5,AB5,AF5,AJ5,AN5,AR5,AV5)=1,"SINGLE","MULTIPLE"))) -> MULTIPLE | BA5: =IF(AND(IF(G5="",TRUE,G5<=ROUNDUP(1.2*F5,0)),IF(K5="",TRUE,K5<=ROUNDUP(1.2*F5,0)),IF(O5="",TRUE,O5<=ROUNDUP(1.2*F5,0)),IF(S5="",TRUE,S5<=ROUNDUP(1.2*F5,0)),IF(W5="",TRUE,W5<=ROUNDUP(1.2*F5,0)),IF(AA5="",TRUE,AA5<=ROUNDUP(1.2*F5,0)),IF(AE5="",TRUE,AE5<=ROUNDUP(1.2*F5,0)),IF(AI5="",TRUE,AI5<=ROUNDUP(1.2*F5,0)),IF(AM5="",TRUE,AM5<=ROUNDUP(1.2*F5,0)),IF(AQ5="",TRUE,AQ5<=ROUNDUP(1.2*F5,0)),IF(AU5="",TRUE,AU5<=ROUNDUP(1.2*F5,0))),"<= 20%","> 20%") -> <= 20% | BB5: =IF(AY5="EST",ROUND(BD5/1.18,2),IF(AY5="ADRYS",ROUND(BD5/1.18,2),ROUND(BD5/(1.3224*Form!$D$10),2))) -> 915 | BC5: =IF(OR(AY5="EST",AY5="ADRYS"),ROUND(BE5/1.18,2),ROUND(BE5/(1.3224*Form!$D$10),2)) -> 6405 | BD5: =IF(F5="Indg",0,IF(F5="TEC Del",0,IF(AND(IF(G5="",TRUE,G5<=ROUNDUP(1.2*F5,0)),IF(K5="",TRUE,K5<=ROUNDUP(1.2*F5,0)),IF(O5="",TRUE,O5<=ROUNDUP(1.2*F5,0)),IF(S5="",TRUE,S5<=ROUNDUP(1.2*F5,0)),IF(W5="",TRUE,W5<=ROUNDUP(1.2*F5,0)),IF(AA5="",TRUE,AA5<=ROUNDUP(1.2*F5,0)),IF(AE5="",TRUE,AE5<=ROUNDUP(1.2*F5,0)),IF(AI5="",TRUE,AI5<=ROUNDUP(1.2*F5,0)),IF(AM5="",TRUE,AM5<=ROUNDUP(1.2*F5,0)),IF(AQ5="",TRUE,AQ5<=ROUNDUP(1.2*F5,0)),IF(AU5="",TRUE,AU5<=ROUNDUP(1.2*F5,0))),IF(F5=0,0,(IF(SUM(I5,M5,Q5,U5,Y5,AC5,AG5,AK5,AO5,AS5,AW5)=0,0,SMALL((I5,M5,Q5,U5,Y5,AC5,AG5,AK5,AO5,AS5,AW5),COUNTIF((I5:AW5),0)+1)))),IF(BE5=J5,I5,IF(BE5=N5,M5,IF(BE5=R5,Q5,IF(BE5=V5,U5,IF(BE5=Z5,Y5,IF(BE5=AD5,AC5,IF(BE5=AH5,AG5,IF(BE5=AL5,AK5,IF(BE5=AP5,AO5,IF(BE5=AT5,AS5,IF(BE5=AX5,AW5)))))))))))))) -> 1079.7 | BE5: =IF(F5="Indg",0,IF(F5="TEC Del",0,IF(AND(IF(G5="",TRUE,G5<=ROUNDUP(1.2*F5,0)),IF(K5="",TRUE,K5<=ROUNDUP(1.2*F5,0)),IF(O5="",TRUE,O5<=ROUNDUP(1.2*F5,0)),IF(S5="",TRUE,S5<=ROUNDUP(1.2*F5,0)),IF(W5="",TRUE,W5<=ROUNDUP(1.2*F5,0)),IF(AA5="",TRUE,AA5<=ROUNDUP(1.2*F5,0)),IF(AE5="",TRUE,AE5<=ROUNDUP(1.2*F5,0)),IF(AI5="",TRUE,AI5<=ROUNDUP(1.2*F5,0)),IF(AM5="",TRUE,AM5<=ROUNDUP(1.2*F5,0)),IF(AQ5="",TRUE,AQ5<=ROUNDUP(1.2*F5,0)),IF(AU5="",TRUE,AU5<=ROUNDUP(1.2*F5,0))),ROUND(BD5*IF(BD5=I5,G5,IF(BD5=M5,K5,IF(BD5=Q5,O5,IF(BD5=U5,S5,IF(BD5=Y5,W5,IF(BD5=AC5,AA5,IF(BD5=AG5,AE5,IF(BD5=AK5,AI5,IF(BD5=AO5,AM5,IF(BD5=AS5,AQ5,IF(BD5=AW5,AU5))))))))))),2),(IF(SUM(J5,N5,R5,V5,Z5,AD5,AH5,AL5,AP5,AT5,AX5)=0,0,SMALL((J5,N5,R5,V5,Z5,AD5,AH5,AL5,AP5,AT5,AX5),COUNTIF((J5:AX5),0)+1)))))) -> 7557.9 | BF5: =IF('Annexure-I'!L2="",'Annexure-I'!F2,'Annexure-I'!L2) -> 11 | BG5: =IF('Annexure-I'!M2="",'Annexure-I'!G2,'Annexure-I'!M2) -> CONTRACT-A1 | BH5: =IF('Annexure-I'!N2="",'Annexure-I'!H2,'Annexure-I'!N2) -> 43298 | BI5: =IF('Annexure-I'!P2="",'Annexure-I'!J2,'Annexure-I'!P2) -> 14.83 | BJ5: =IF('Annexure-I'!Q2="",'Annexure-I'!K2,'Annexure-I'!Q2) -> 1623.4145 | BK5: ='Annexure-I'!F2 -> 11 | BL5: ='Annexure-I'!G2 -> CONTRACT-A1 | BM5: =IF('Annexure-I'!H2=0,"",'Annexure-I'!H2) -> 43298 | BN5: ='Annexure-I'!J2 -> 14.83 | BO5: ='Annexure-I'!K2 -> 1623.4145 | BP5: =IF(OR(AY5="EST",AY5="ADRYS"),ROUND((BC5*1.18)/(1.3224*Form!$D$10),2),BC5) -> 69.04 | BQ5: =ROUND(BS5/(1.3224*Form!$D$10),2) -> 103.81 | BR5: =IF(AY5="DELETED",0,BE5) -> 7557.9 | BS5: =IF(BR5=0,0,ROUND(IF($BQ$1="LPP",ROUND(BJ5*F5,2),ROUND(BO5*F5,2)),2)) -> 11363.9 | BT5: =IF(SUM(BR5:BS5)=0,0,(BR5-BS5)/BS5) -> -0.33492023 | BV5: =IF(F5="Indg",0,IF(F5="TEC Del",0,IF(CA5="Deleted",0,ROUND(F5*BU5,2)))) -> 0 | BW5: =IF(OR(AY5="EST",AY5="ADRYS"),ROUND(1.18*BU5,2),ROUND(BU5*1.3224*Form!$D$10,2)) -> 0 | BX5: =IF(F5="Indg",0,IF(F5="TEC Del",0,IF(CA5="Deleted",0,ROUND(BW5*F5,2)))) -> 0 | BY5: =IF((BX5)=0,0,(BX5-BS5)/BS5) -> 0 | BZ5: =IF(CA5="Deleted",0,ROUND(BO5*F5,2)) -> 11363.9
A6: =SUBTOTAL(2,$B$5:B6) -> 2 | B6: 2 | C6: X2 | D6: MICROCIRCUIT OF KOPYO RADAR | E6: 38 | F6: ='Annexure-I'!E3 -> 38 | G6: =IF('CST-Calculation'!G6=0,"",'CST-Calculation'!G6) | H6: =IF('CST-Calculation'!H6=0,"",'CST-Calculation'!H6) | I6: =IF(G6="","",IF(H6="TEC Rejected","",IF(H6="","",ROUND(1.3224*Form!$D$10*H6,2)))) | J6: =IF(G6="","",IF(H6="TEC Rejected","",IF(H6="","",ROUND(G6*I6,2)))) | K6: =IF(L6="","",IF('CST-Calculation'!$F6="Indg","",IF('CST-Calculation'!$F6="TEC Del","",IF('CST-Calculation'!K6>0,'CST-Calculation'!K6,IF('CST-Calculation'!$F6=0,"",'CST-Calculation'!$F6))))) | L6: =IF('CST-Calculation'!L6=0,"",'CST-Calculation'!L6) | M6: =IF(K6="","",IF(L6="TEC Rejected","",IF(L6="","",ROUND(1.3224*Form!$D$10*L6,2)))) | N6: =IF(K6="","",IF(L6="TEC Rejected","",IF(L6="","",ROUND(K6*M6,2)))) | O6: =IF(P6="","",IF('CST-Calculation'!$F6="Indg","",IF('CST-Calculation'!$F6="TEC Del","",IF('CST-Calculation'!O6>0,'CST-Calculation'!O6,IF('CST-Calculation'!$F6=0,"",'CST-Calculation'!$F6))))) -> 38 | P6: =IF('CST-Calculation'!P6=0,"",'CST-Calculation'!P6) -> 17.1 | Q6: =IF(O6="","",IF(P6="TEC Rejected","",IF(P6="","",ROUND(1.3224*Form!$D$10*P6,2)))) -> 1871.91 | R6: =IF(O6="","",IF(P6="TEC Rejected","",IF(P6="","",ROUND(O6*Q6,2)))) -> 71132.58 | S6: =IF(T6="","",IF('CST-Calculation'!$F6="Indg","",IF('CST-Calculation'!$F6="TEC Del","",IF('CST-Calculation'!S6>0,'CST-Calculation'!S6,IF('CST-Calculation'!$F6=0,"",'CST-Calculation'!$F6))))) -> 38 | T6: =IF('CST-Calculation'!T6=0,"",'CST-Calculation'!T6) -> 27.5 | U6: =IF(S6="","",IF(T6="TEC Rejected","",IF(T6="","",ROUND(1.3224*Form!$D$10*T6,2)))) -> 3010.38 | V6: =IF(S6="","",IF(T6="TEC Rejected","",IF(T6="","",ROUND(S6*U6,2)))) -> 114394.44 | W6: =IF(X6="","",IF('CST-Calculation'!$F6="Indg","",IF('CST-Calculation'!$F6="TEC Del","",IF('CST-Calculation'!W6>0,'CST-Calculation'!W6,IF('CST-Calculation'!$F6=0,"",'CST-Calculation'!$F6))))) | X6: =IF('CST-Calculation'!X6=0,"",'CST-Calculation'!X6) | Y6: =IF(W6="","",IF(X6="TEC Rejected","",IF(X6="","",ROUND(1.3224*Form!$D$10*X6,2)))) | Z6: =IF(W6="","",IF(X6="TEC Rejected","",IF(X6="","",ROUND(W6*Y6,2)))) | AA6: =IF(AB6="","",IF('CST-Calculation'!$F6="Indg","",IF('CST-Calculation'!$F6="TEC Del","",IF('CST-Calculation'!AA6>0,'CST-Calculation'!AA6,IF('CST-Calculation'!$F6=0,"",'CST-Calculation'!$F6))))) -> 38 | AB6: =IF('CST-Calculation'!AB6=0,"",'CST-Calculation'!AB6) -> 915 | AC6: =IF(AA6="","",IF(AB6="TEC Rejected","",IF(AB6="","",ROUND(1.18*AB6,2)))) -> 1079.7 | AD6: =IF(AA6="","",IF(AB6="TEC Rejected","",IF(AB6="","",ROUND(AA6*AC6,2)))) -> 41028.6 | AE6: =IF(AF6="","",IF('CST-Calculation'!$F6="Indg","",IF('CST-Calculation'!$F6="TEC Del","",IF('CST-Calculation'!AE6>0,'CST-Calculation'!AE6,IF('CST-Calculation'!$F6=0,"",'CST-Calculation'!$F6))))) | AF6: =IF('CST-Calculation'!AF6=0,"",'CST-Calculation'!AF6) | AG6: =IF(AE6="","",IF(AF6="TEC Rejected","",IF(AF6="","",ROUND(1.3224*Form!$D$10*AF6,2)))) | AH6: =IF(AE6="","",IF(AF6="TEC Rejected","",IF(AF6="","",ROUND(AE6*AG6,2)))) | AI6: =IF(AJ6="","",IF('CST-Calculation'!$F6="Indg","",IF('CST-Calculation'!$F6="TEC Del","",IF('CST-Calculation'!AI6>0,'CST-Calculation'!AI6,IF('CST-Calculation'!$F6=0,"",'CST-Calculation'!$F6))))) | AJ6: =IF('CST-Calculation'!AJ6=0,"",'CST-Calculation'!AJ6) | AK6: =IF(AI6="","",IF(AJ6="TEC Rejected","",IF(AJ6="","",ROUND(1.18*AJ6,2)))) | AL6: =IF(AI6="","",IF(AJ6="TEC Rejected","",IF(AJ6="","",ROUND(AI6*AK6,2)))) | AM6: =IF(AN6="","",IF('CST-Calculation'!$F6="Indg","",IF('CST-Calculation'!$F6="TEC Del","",IF('CST-Calculation'!AM6>0,'CST-Calculation'!AM6,IF('CST-Calculation'!$F6=0,"",'CST-Calculation'!$F6))))) | AN6: =IF('CST-Calculation'!AN6=0,"",'CST-Calculation'!AN6) | AO6: =IF(AM6="","",IF(AN6="TEC Rejected","",IF(AN6="","",ROUND(1.3224*Form!$D$10*AN6,2)))) | AP6: =IF(AM6="","",IF(AN6="TEC Rejected","",IF(AN6="","",ROUND(AM6*AO6,2)))) | AQ6: =IF(AR6="","",IF('CST-Calculation'!$F6="Indg","",IF('CST-Calculation'!$F6="TEC Del","",IF('CST-Calculation'!AQ6>0,'CST-Calculation'!AQ6,IF('CST-Calculation'!$F6=0,"",'CST-Calculation'!$F6))))) | AR6: =IF('CST-Calculation'!AR6=0,"",'CST-Calculation'!AR6) | AS6: =IF(AQ6="","",IF(AR6="TEC Rejected","",IF(AR6="","",ROUND(1.3224*Form!$D$10*AR6,2)))) | AT6: =IF(AQ6="","",IF(AR6="TEC Rejected","",IF(AR6="","",ROUND(AQ6*AS6,2)))) | AU6: =IF(AV6="","",IF('CST-Calculation'!$F6="Indg","",IF('CST-Calculation'!$F6="TEC Del","",IF('CST-Calculation'!AU6>0,'CST-Calculation'!AU6,IF('CST-Calculation'!$F6=0,"",'CST-Calculation'!$F6))))) | AV6: =IF('CST-Calculation'!AV6=0,"",'CST-Calculation'!AV6) | AW6: =IF(AU6="","",IF(AV6="TEC Rejected","",IF(AV6="","",ROUND(1.3224*Form!$D$10*AV6,2)))) | AX6: =IF(AU6="","",IF(AV6="TEC Rejected","",IF(AV6="","",ROUND(AU6*AW6,2)))) | AY6: =IF(F6="Indg","INDG",IF(F6="TEC Del","DELETED",IF(F6=0,"DELETED",IF(BD6=0,"NO OFFER",IF(BD6=I6,$H$3,IF(BD6=M6,$L$3,IF(BD6=Q6,$P$3,IF(BD6=U6,$T$3,IF(BD6=Y6,$X$3,IF(BD6=AC6,$AB$3,IF(BD6=AG6,$AF$3,IF(BD6=AK6,$AJ$3,IF(BD6=AO6,$AN$3,IF(BD6=AS6,$AR$3,IF(BD6=AW6,$AV$3))))))))))))))) -> ADRYS | AZ6: =IF(F6=0,"DELETED",IF(COUNT(H6,L6,P6,T6,X6,AB6,AF6,AJ6,AN6,AR6,AV6)=0,"NO OFFER",IF(COUNT(H6,L6,P6,T6,X6,AB6,AF6,AJ6,AN6,AR6,AV6)=1,"SINGLE","MULTIPLE"))) -> MULTIPLE | BA6: =IF(AND(IF(G6="",TRUE,G6<=ROUNDUP(1.2*F6,0)),IF(K6="",TRUE,K6<=ROUNDUP(1.2*F6,0)),IF(O6="",TRUE,O6<=ROUNDUP(1.2*F6,0)),IF(S6="",TRUE,S6<=ROUNDUP(1.2*F6,0)),IF(W6="",TRUE,W6<=ROUNDUP(1.2*F6,0)),IF(AA6="",TRUE,AA6<=ROUNDUP(1.2*F6,0)),IF(AE6="",TRUE,AE6<=ROUNDUP(1.2*F6,0)),IF(AI6="",TRUE,AI6<=ROUNDUP(1.2*F6,0)),IF(AM6="",TRUE,AM6<=ROUNDUP(1.2*F6,0)),IF(AQ6="",TRUE,AQ6<=ROUNDUP(1.2*F6,0)),IF(AU6="",TRUE,AU6<=ROUNDUP(1.2*F6,0))),"<= 20%","> 20%") -> <= 20% | BB6: =IF(AY6="EST",ROUND(BD6/1.18,2),IF(AY6="ADRYS",ROUND(BD6/1.18,2),ROUND(BD6/(1.3224*Form!$D$10),2))) -> 915 | BC6: =IF(OR(AY6="EST",AY6="ADRYS"),ROUND(BE6/1.18,2),ROUND(BE6/(1.3224*Form!$D$10),2)) -> 34770 | BD6: =IF(F6="Indg",0,IF(F6="TEC Del",0,IF(AND(IF(G6="",TRUE,G6<=ROUNDUP(1.2*F6,0)),IF(K6="",TRUE,K6<=ROUNDUP(1.2*F6,0)),IF(O6="",TRUE,O6<=ROUNDUP(1.2*F6,0)),IF(S6="",TRUE,S6<=ROUNDUP(1.2*F6,0)),IF(W6="",TRUE,W6<=ROUNDUP(1.2*F6,0)),IF(AA6="",TRUE,AA6<=ROUNDUP(1.2*F6,0)),IF(AE6="",TRUE,AE6<=ROUNDUP(1.2*F6,0)),IF(AI6="",TRUE,AI6<=ROUNDUP(1.2*F6,0)),IF(AM6="",TRUE,AM6<=ROUNDUP(1.2*F6,0)),IF(AQ6="",TRUE,AQ6<=ROUNDUP(1.2*F6,0)),IF(AU6="",TRUE,AU6<=ROUNDUP(1.2*F6,0))),IF(F6=0,0,(IF(SUM(I6,M6,Q6,U6,Y6,AC6,AG6,AK6,AO6,AS6,AW6)=0,0,SMALL((I6,M6,Q6,U6,Y6,AC6,AG6,AK6,AO6,AS6,AW6),COUNTIF((I6:AW6),0)+1)))),IF(BE6=J6,I6,IF(BE6=N6,M6,IF(BE6=R6,Q6,IF(BE6=V6,U6,IF(BE6=Z6,Y6,IF(BE6=AD6,AC6,IF(BE6=AH6,AG6,IF(BE6=AL6,AK6,IF(BE6=AP6,AO6,IF(BE6=AT6,AS6,IF(BE6=AX6,AW6)))))))))))))) -> 1079.7 | BE6: =IF(F6="Indg",0,IF(F6="TEC Del",0,IF(AND(IF(G6="",TRUE,G6<=ROUNDUP(1.2*F6,0)),IF(K6="",TRUE,K6<=ROUNDUP(1.2*F6,0)),IF(O6="",TRUE,O6<=ROUNDUP(1.2*F6,0)),IF(S6="",TRUE,S6<=ROUNDUP(1.2*F6,0)),IF(W6="",TRUE,W6<=ROUNDUP(1.2*F6,0)),IF(AA6="",TRUE,AA6<=ROUNDUP(1.2*F6,0)),IF(AE6="",TRUE,AE6<=ROUNDUP(1.2*F6,0)),IF(AI6="",TRUE,AI6<=ROUNDUP(1.2*F6,0)),IF(AM6="",TRUE,AM6<=ROUNDUP(1.2*F6,0)),IF(AQ6="",TRUE,AQ6<=ROUNDUP(1.2*F6,0)),IF(AU6="",TRUE,AU6<=ROUNDUP(1.2*F6,0))),ROUND(BD6*IF(BD6=I6,G6,IF(BD6=M6,K6,IF(BD6=Q6,O6,IF(BD6=U6,S6,IF(BD6=Y6,W6,IF(BD6=AC6,AA6,IF(BD6=AG6,AE6,IF(BD6=AK6,AI6,IF(BD6=AO6,AM6,IF(BD6=AS6,AQ6,IF(BD6=AW6,AU6))))))))))),2),(IF(SUM(J6,N6,R6,V6,Z6,AD6,AH6,AL6,AP6,AT6,AX6)=0,0,SMALL((J6,N6,R6,V6,Z6,AD6,AH6,AL6,AP6,AT6,AX6),COUNTIF((J6:AX6),0)+1)))))) -> 41028.6 | BF6: =IF('Annexure-I'!L3="",'Annexure-I'!F3,'Annexure-I'!L3) -> 16.16 | BG6: =IF('Annexure-I'!M3="",'Annexure-I'!G3,'Annexure-I'!M3) -> CONTRACT-A2 | BH6: =IF('Annexure-I'!N3="",'Annexure-I'!H3,'Annexure-I'!N3) -> 40967 | BI6: =IF('Annexure-I'!P3="",'Annexure-I'!J3,'Annexure-I'!P3) -> 29.61 | BJ6: =IF('Annexure-I'!Q3="",'Annexure-I'!K3,'Annexure-I'!Q3) -> 3241.3555 | BK6: ='Annexure-I'!F3 -> 16.16 | BL6: ='Annexure-I'!G3 -> CONTRACT-A2 | BM6: =IF('Annexure-I'!H3=0,"",'Annexure-I'!H3) -> 40967 | BN6: ='Annexure-I'!J3 -> 29.61 | BO6: ='Annexure-I'!K3 -> 3241.3555 | BP6: =IF(OR(AY6="EST",AY6="ADRYS"),ROUND((BC6*1.18)/(1.3224*Form!$D$10),2),BC6) -> 374.8 | BQ6: =ROUND(BS6/(1.3224*Form!$D$10),2) -> 1125.18 | BR6: =IF(AY6="DELETED",0,BE6) -> 41028.6 | BS6: =IF(BR6=0,0,ROUND(IF($BQ$1="LPP",ROUND(BJ6*F6,2),ROUND(BO6*F6,2)),2)) -> 123171.51 | BT6: =IF(SUM(BR6:BS6)=0,0,(BR6-BS6)/BS6) -> -0.66689862 | BV6: =IF(F6="Indg",0,IF(F6="TEC Del",0,IF(CA6="Deleted",0,ROUND(F6*BU6,2)))) -> 0 | BW6: =IF(OR(AY6="EST",AY6="ADRYS"),ROUND(1.18*BU6,2),ROUND(BU6*1.3224*Form!$D$10,2)) -> 0 | BX6: =IF(F6="Indg",0,IF(F6="TEC Del",0,IF(CA6="Deleted",0,ROUND(BW6*F6,2)))) -> 0 | BY6: =IF((BX6)=0,0,(BX6-BS6)/BS6) -> 0 | BZ6: =IF(CA6="Deleted",0,ROUND(BO6*F6,2)) -> 123171.51
A7: =SUBTOTAL(2,$B$5:B7) -> 3 | B7: 3 | C7: X3 | D7: IC (Integrated Circuit ) | E7: 12 | F7: ='Annexure-I'!E4 -> 12 | G7: =IF('CST-Calculation'!G7=0,"",'CST-Calculation'!G7) | H7: =IF('CST-Calculation'!H7=0,"",'CST-Calculation'!H7) | I7: =IF(G7="","",IF(H7="TEC Rejected","",IF(H7="","",ROUND(1.3224*Form!$D$10*H7,2)))) | J7: =IF(G7="","",IF(H7="TEC Rejected","",IF(H7="","",ROUND(G7*I7,2)))) | K7: =IF(L7="","",IF('CST-Calculation'!$F7="Indg","",IF('CST-Calculation'!$F7="TEC Del","",IF('CST-Calculation'!K7>0,'CST-Calculation'!K7,IF('CST-Calculation'!$F7=0,"",'CST-Calculation'!$F7))))) | L7: =IF('CST-Calculation'!L7=0,"",'CST-Calculation'!L7) | M7: =IF(K7="","",IF(L7="TEC Rejected","",IF(L7="","",ROUND(1.3224*Form!$D$10*L7,2)))) | N7: =IF(K7="","",IF(L7="TEC Rejected","",IF(L7="","",ROUND(K7*M7,2)))) | O7: =IF(P7="","",IF('CST-Calculation'!$F7="Indg","",IF('CST-Calculation'!$F7="TEC Del","",IF('CST-Calculation'!O7>0,'CST-Calculation'!O7,IF('CST-Calculation'!$F7=0,"",'CST-Calculation'!$F7))))) -> 12 | P7: =IF('CST-Calculation'!P7=0,"",'CST-Calculation'!P7) -> 16.5 | Q7: =IF(O7="","",IF(P7="TEC Rejected","",IF(P7="","",ROUND(1.3224*Form!$D$10*P7,2)))) -> 1806.23 | R7: =IF(O7="","",IF(P7="TEC Rejected","",IF(P7="","",ROUND(O7*Q7,2)))) -> 21674.76 | S7: =IF(T7="","",IF('CST-Calculation'!$F7="Indg","",IF('CST-Calculation'!$F7="TEC Del","",IF('CST-Calculation'!S7>0,'CST-Calculation'!S7,IF('CST-Calculation'!$F7=0,"",'CST-Calculation'!$F7))))) -> 12 | T7: =IF('CST-Calculation'!T7=0,"",'CST-Calculation'!T7) -> 22 | U7: =IF(S7="","",IF(T7="TEC Rejected","",IF(T7="","",ROUND(1.3224*Form!$D$10*T7,2)))) -> 2408.3 | V7: =IF(S7="","",IF(T7="TEC Rejected","",IF(T7="","",ROUND(S7*U7,2)))) -> 28899.6 | W7: =IF(X7="","",IF('CST-Calculation'!$F7="Indg","",IF('CST-Calculation'!$F7="TEC Del","",IF('CST-Calculation'!W7>0,'CST-Calculation'!W7,IF('CST-Calculation'!$F7=0,"",'CST-Calculation'!$F7))))) | X7: =IF('CST-Calculation'!X7=0,"",'CST-Calculation'!X7) | Y7: =IF(W7="","",IF(X7="TEC Rejected","",IF(X7="","",ROUND(1.3224*Form!$D$10*X7,2)))) | Z7: =IF(W7="","",IF(X7="TEC Rejected","",IF(X7="","",ROUND(W7*Y7,2)))) | AA7: =IF(AB7="","",IF('CST-Calculation'!$F7="Indg","",IF('CST-Calculation'!$F7="TEC Del","",IF('CST-Calculation'!AA7>0,'CST-Calculation'!AA7,IF('CST-Calculation'!$F7=0,"",'CST-Calculation'!$F7))))) -> 12 | AB7: =IF('CST-Calculation'!AB7=0,"",'CST-Calculation'!AB7) -> 915 | AC7: =IF(AA7="","",IF(AB7="TEC Rejected","",IF(AB7="","",ROUND(1.18*AB7,2)))) -> 1079.7 | AD7: =IF(AA7="","",IF(AB7="TEC Rejected","",IF(AB7="","",ROUND(AA7*AC7,2)))) -> 12956.4 | AE7: =IF(AF7="","",IF('CST-Calculation'!$F7="Indg","",IF('CST-Calculation'!$F7="TEC Del","",IF('CST-Calculation'!AE7>0,'CST-Calculation'!AE7,IF('CST-Calculation'!$F7=0,"",'CST-Calculation'!$F7))))) | AF7: =IF('CST-Calculation'!AF7=0,"",'CST-Calculation'!AF7) | AG7: =IF(AE7="","",IF(AF7="TEC Rejected","",IF(AF7="","",ROUND(1.3224*Form!$D$10*AF7,2)))) | AH7: =IF(AE7="","",IF(AF7="TEC Rejected","",IF(AF7="","",ROUND(AE7*AG7,2)))) | AI7: =IF(AJ7="","",IF('CST-Calculation'!$F7="Indg","",IF('CST-Calculation'!$F7="TEC Del","",IF('CST-Calculation'!AI7>0,'CST-Calculation'!AI7,IF('CST-Calculation'!$F7=0,"",'CST-Calculation'!$F7))))) | AJ7: =IF('CST-Calculation'!AJ7=0,"",'CST-Calculation'!AJ7) | AK7: =IF(AI7="","",IF(AJ7="TEC Rejected","",IF(AJ7="","",ROUND(1.18*AJ7,2)))) | AL7: =IF(AI7="","",IF(AJ7="TEC Rejected","",IF(AJ7="","",ROUND(AI7*AK7,2)))) | AM7: =IF(AN7="","",IF('CST-Calculation'!$F7="Indg","",IF('CST-Calculation'!$F7="TEC Del","",IF('CST-Calculation'!AM7>0,'CST-Calculation'!AM7,IF('CST-Calculation'!$F7=0,"",'CST-Calculation'!$F7))))) | AN7: =IF('CST-Calculation'!AN7=0,"",'CST-Calculation'!AN7) | AO7: =IF(AM7="","",IF(AN7="TEC Rejected","",IF(AN7="","",ROUND(1.3224*Form!$D$10*AN7,2)))) | AP7: =IF(AM7="","",IF(AN7="TEC Rejected","",IF(AN7="","",ROUND(AM7*AO7,2)))) | AQ7: =IF(AR7="","",IF('CST-Calculation'!$F7="Indg","",IF('CST-Calculation'!$F7="TEC Del","",IF('CST-Calculation'!AQ7>0,'CST-Calculation'!AQ7,IF('CST-Calculation'!$F7=0,"",'CST-Calculation'!$F7))))) | AR7: =IF('CST-Calculation'!AR7=0,"",'CST-Calculation'!AR7) | AS7: =IF(AQ7="","",IF(AR7="TEC Rejected","",IF(AR7="","",ROUND(1.3224*Form!$D$10*AR7,2)))) | AT7: =IF(AQ7="","",IF(AR7="TEC Rejected","",IF(AR7="","",ROUND(AQ7*AS7,2)))) | AU7: =IF(AV7="","",IF('CST-Calculation'!$F7="Indg","",IF('CST-Calculation'!$F7="TEC Del","",IF('CST-Calculation'!AU7>0,'CST-Calculation'!AU7,IF('CST-Calculation'!$F7=0,"",'CST-Calculation'!$F7))))) | AV7: =IF('CST-Calculation'!AV7=0,"",'CST-Calculation'!AV7) | AW7: =IF(AU7="","",IF(AV7="TEC Rejected","",IF(AV7="","",ROUND(1.3224*Form!$D$10*AV7,2)))) | AX7: =IF(AU7="","",IF(AV7="TEC Rejected","",IF(AV7="","",ROUND(AU7*AW7,2)))) | AY7: =IF(F7="Indg","INDG",IF(F7="TEC Del","DELETED",IF(F7=0,"DELETED",IF(BD7=0,"NO OFFER",IF(BD7=I7,$H$3,IF(BD7=M7,$L$3,IF(BD7=Q7,$P$3,IF(BD7=U7,$T$3,IF(BD7=Y7,$X$3,IF(BD7=AC7,$AB$3,IF(BD7=AG7,$AF$3,IF(BD7=AK7,$AJ$3,IF(BD7=AO7,$AN$3,IF(BD7=AS7,$AR$3,IF(BD7=AW7,$AV$3))))))))))))))) -> ADRYS | AZ7: =IF(F7=0,"DELETED",IF(COUNT(H7,L7,P7,T7,X7,AB7,AF7,AJ7,AN7,AR7,AV7)=0,"NO OFFER",IF(COUNT(H7,L7,P7,T7,X7,AB7,AF7,AJ7,AN7,AR7,AV7)=1,"SINGLE","MULTIPLE"))) -> MULTIPLE | BA7: =IF(AND(IF(G7="",TRUE,G7<=ROUNDUP(1.2*F7,0)),IF(K7="",TRUE,K7<=ROUNDUP(1.2*F7,0)),IF(O7="",TRUE,O7<=ROUNDUP(1.2*F7,0)),IF(S7="",TRUE,S7<=ROUNDUP(1.2*F7,0)),IF(W7="",TRUE,W7<=ROUNDUP(1.2*F7,0)),IF(AA7="",TRUE,AA7<=ROUNDUP(1.2*F7,0)),IF(AE7="",TRUE,AE7<=ROUNDUP(1.2*F7,0)),IF(AI7="",TRUE,AI7<=ROUNDUP(1.2*F7,0)),IF(AM7="",TRUE,AM7<=ROUNDUP(1.2*F7,0)),IF(AQ7="",TRUE,AQ7<=ROUNDUP(1.2*F7,0)),IF(AU7="",TRUE,AU7<=ROUNDUP(1.2*F7,0))),"<= 20%","> 20%") -> <= 20% | BB7: =IF(AY7="EST",ROUND(BD7/1.18,2),IF(AY7="ADRYS",ROUND(BD7/1.18,2),ROUND(BD7/(1.3224*Form!$D$10),2))) -> 915 | BC7: =IF(OR(AY7="EST",AY7="ADRYS"),ROUND(BE7/1.18,2),ROUND(BE7/(1.3224*Form!$D$10),2)) -> 10980 | BD7: =IF(F7="Indg",0,IF(F7="TEC Del",0,IF(AND(IF(G7="",TRUE,G7<=ROUNDUP(1.2*F7,0)),IF(K7="",TRUE,K7<=ROUNDUP(1.2*F7,0)),IF(O7="",TRUE,O7<=ROUNDUP(1.2*F7,0)),IF(S7="",TRUE,S7<=ROUNDUP(1.2*F7,0)),IF(W7="",TRUE,W7<=ROUNDUP(1.2*F7,0)),IF(AA7="",TRUE,AA7<=ROUNDUP(1.2*F7,0)),IF(AE7="",TRUE,AE7<=ROUNDUP(1.2*F7,0)),IF(AI7="",TRUE,AI7<=ROUNDUP(1.2*F7,0)),IF(AM7="",TRUE,AM7<=ROUNDUP(1.2*F7,0)),IF(AQ7="",TRUE,AQ7<=ROUNDUP(1.2*F7,0)),IF(AU7="",TRUE,AU7<=ROUNDUP(1.2*F7,0))),IF(F7=0,0,(IF(SUM(I7,M7,Q7,U7,Y7,AC7,AG7,AK7,AO7,AS7,AW7)=0,0,SMALL((I7,M7,Q7,U7,Y7,AC7,AG7,AK7,AO7,AS7,AW7),COUNTIF((I7:AW7),0)+1)))),IF(BE7=J7,I7,IF(BE7=N7,M7,IF(BE7=R7,Q7,IF(BE7=V7,U7,IF(BE7=Z7,Y7,IF(BE7=AD7,AC7,IF(BE7=AH7,AG7,IF(BE7=AL7,AK7,IF(BE7=AP7,AO7,IF(BE7=AT7,AS7,IF(BE7=AX7,AW7)))))))))))))) -> 1079.7 | BE7: =IF(F7="Indg",0,IF(F7="TEC Del",0,IF(AND(IF(G7="",TRUE,G7<=ROUNDUP(1.2*F7,0)),IF(K7="",TRUE,K7<=ROUNDUP(1.2*F7,0)),IF(O7="",TRUE,O7<=ROUNDUP(1.2*F7,0)),IF(S7="",TRUE,S7<=ROUNDUP(1.2*F7,0)),IF(W7="",TRUE,W7<=ROUNDUP(1.2*F7,0)),IF(AA7="",TRUE,AA7<=ROUNDUP(1.2*F7,0)),IF(AE7="",TRUE,AE7<=ROUNDUP(1.2*F7,0)),IF(AI7="",TRUE,AI7<=ROUNDUP(1.2*F7,0)),IF(AM7="",TRUE,AM7<=ROUNDUP(1.2*F7,0)),IF(AQ7="",TRUE,AQ7<=ROUNDUP(1.2*F7,0)),IF(AU7="",TRUE,AU7<=ROUNDUP(1.2*F7,0))),ROUND(BD7*IF(BD7=I7,G7,IF(BD7=M7,K7,IF(BD7=Q7,O7,IF(BD7=U7,S7,IF(BD7=Y7,W7,IF(BD7=AC7,AA7,IF(BD7=AG7,AE7,IF(BD7=AK7,AI7,IF(BD7=AO7,AM7,IF(BD7=AS7,AQ7,IF(BD7=AW7,AU7))))))))))),2),(IF(SUM(J7,N7,R7,V7,Z7,AD7,AH7,AL7,AP7,AT7,AX7)=0,0,SMALL((J7,N7,R7,V7,Z7,AD7,AH7,AL7,AP7,AT7,AX7),COUNTIF((J7:AX7),0)+1)))))) -> 12956.4 | BF7: =IF('Annexure-I'!L4="",'Annexure-I'!F4,'Annexure-I'!L4) -> 22 | BG7: =IF('Annexure-I'!M4="",'Annexure-I'!G4,'Annexure-I'!M4) -> CONTRACT-A3 | BH7: =IF('Annexure-I'!N4="",'Annexure-I'!H4,'Annexure-I'!N4) -> 43298 | BI7: =IF('Annexure-I'!P4="",'Annexure-I'!J4,'Annexure-I'!P4) -> 29.65 | BJ7: =IF('Annexure-I'!Q4="",'Annexure-I'!K4,'Annexure-I'!Q4) -> 3245.7343 | BK7: ='Annexure-I'!F4 -> 22 | BL7: ='Annexure-I'!G4 -> CONTRACT-A3 | BM7: 2021 | BN7: ='Annexure-I'!J4 -> 29.65 | BO7: ='Annexure-I'!K4 -> 3245.7343 | BP7: =IF(OR(AY7="EST",AY7="ADRYS"),ROUND((BC7*1.18)/(1.3224*Form!$D$10),2),BC7) -> 118.36 | BQ7: =ROUND(BS7/(1.3224*Form!$D$10),2) -> 355.8 | BR7: =IF(AY7="DELETED",0,BE7) -> 12956.4 | BS7: =IF(BR7=0,0,ROUND(IF($BQ$1="LPP",ROUND(BJ7*F7,2),ROUND(BO7*F7,2)),2)) -> 38948.81 | BT7: =IF(SUM(BR7:BS7)=0,0,(BR7-BS7)/BS7) -> -0.66734799 | BV7: =IF(F7="Indg",0,IF(F7="TEC Del",0,IF(CA7="Deleted",0,ROUND(F7*BU7,2)))) -> 0 | BW7: =IF(OR(AY7="EST",AY7="ADRYS"),ROUND(1.18*BU7,2),ROUND(BU7*1.3224*Form!$D$10,2)) -> 0 | BX7: =IF(F7="Indg",0,IF(F7="TEC Del",0,IF(CA7="Deleted",0,ROUND(BW7*F7,2)))) -> 0 | BY7: =IF((BX7)=0,0,(BX7-BS7)/BS7) -> 0 | BZ7: =IF(CA7="Deleted",0,ROUND(BO7*F7,2)) -> 38948.81
A8: =SUBTOTAL(2,$B$5:B8) -> 4 | B8: 4 | C8: X4 | D8: MICROCIRCUIT | E8: 10 | F8: ='Annexure-I'!E5 -> 10 | G8: =IF('CST-Calculation'!G8=0,"",'CST-Calculation'!G8) | H8: =IF('CST-Calculation'!H8=0,"",'CST-Calculation'!H8) | I8: =IF(G8="","",IF(H8="TEC Rejected","",IF(H8="","",ROUND(1.3224*Form!$D$10*H8,2)))) | J8: =IF(G8="","",IF(H8="TEC Rejected","",IF(H8="","",ROUND(G8*I8,2)))) | K8: =IF(L8="","",IF('CST-Calculation'!$F8="Indg","",IF('CST-Calculation'!$F8="TEC Del","",IF('CST-Calculation'!K8>0,'CST-Calculation'!K8,IF('CST-Calculation'!$F8=0,"",'CST-Calculation'!$F8))))) | L8: =IF('CST-Calculation'!L8=0,"",'CST-Calculation'!L8) | M8: =IF(K8="","",IF(L8="TEC Rejected","",IF(L8="","",ROUND(1.3224*Form!$D$10*L8,2)))) | N8: =IF(K8="","",IF(L8="TEC Rejected","",IF(L8="","",ROUND(K8*M8,2)))) | O8: =IF(P8="","",IF('CST-Calculation'!$F8="Indg","",IF('CST-Calculation'!$F8="TEC Del","",IF('CST-Calculation'!O8>0,'CST-Calculation'!O8,IF('CST-Calculation'!$F8=0,"",'CST-Calculation'!$F8))))) -> 10 | P8: =IF('CST-Calculation'!P8=0,"",'CST-Calculation'!P8) -> 12.6 | Q8: =IF(O8="","",IF(P8="TEC Rejected","",IF(P8="","",ROUND(1.3224*Form!$D$10*P8,2)))) -> 1379.3 | R8: =IF(O8="","",IF(P8="TEC Rejected","",IF(P8="","",ROUND(O8*Q8,2)))) -> 13793 | S8: =IF(T8="","",IF('CST-Calculation'!$F8="Indg","",IF('CST-Calculation'!$F8="TEC Del","",IF('CST-Calculation'!S8>0,'CST-Calculation'!S8,IF('CST-Calculation'!$F8=0,"",'CST-Calculation'!$F8))))) -> 10 | T8: =IF('CST-Calculation'!T8=0,"",'CST-Calculation'!T8) -> 27.5 | U8: =IF(S8="","",IF(T8="TEC Rejected","",IF(T8="","",ROUND(1.3224*Form!$D$10*T8,2)))) -> 3010.38 | V8: =IF(S8="","",IF(T8="TEC Rejected","",IF(T8="","",ROUND(S8*U8,2)))) -> 30103.8 | W8: =IF(X8="","",IF('CST-Calculation'!$F8="Indg","",IF('CST-Calculation'!$F8="TEC Del","",IF('CST-Calculation'!W8>0,'CST-Calculation'!W8,IF('CST-Calculation'!$F8=0,"",'CST-Calculation'!$F8))))) | X8: =IF('CST-Calculation'!X8=0,"",'CST-Calculation'!X8) | Y8: =IF(W8="","",IF(X8="TEC Rejected","",IF(X8="","",ROUND(1.3224*Form!$D$10*X8,2)))) | Z8: =IF(W8="","",IF(X8="TEC Rejected","",IF(X8="","",ROUND(W8*Y8,2)))) | AA8: =IF(AB8="","",IF('CST-Calculation'!$F8="Indg","",IF('CST-Calculation'!$F8="TEC Del","",IF('CST-Calculation'!AA8>0,'CST-Calculation'!AA8,IF('CST-Calculation'!$F8=0,"",'CST-Calculation'!$F8))))) -> 10 | AB8: =IF('CST-Calculation'!AB8=0,"",'CST-Calculation'!AB8) -> 1215 | AC8: =IF(AA8="","",IF(AB8="TEC Rejected","",IF(AB8="","",ROUND(1.18*AB8,2)))) -> 1433.7 | AD8: =IF(AA8="","",IF(AB8="TEC Rejected","",IF(AB8="","",ROUND(AA8*AC8,2)))) -> 14337 | AE8: =IF(AF8="","",IF('CST-Calculation'!$F8="Indg","",IF('CST-Calculation'!$F8="TEC Del","",IF('CST-Calculation'!AE8>0,'CST-Calculation'!AE8,IF('CST-Calculation'!$F8=0,"",'CST-Calculation'!$F8))))) | AF8: =IF('CST-Calculation'!AF8=0,"",'CST-Calculation'!AF8) | AG8: =IF(AE8="","",IF(AF8="TEC Rejected","",IF(AF8="","",ROUND(1.3224*Form!$D$10*AF8,2)))) | AH8: =IF(AE8="","",IF(AF8="TEC Rejected","",IF(AF8="","",ROUND(AE8*AG8,2)))) | AI8: =IF(AJ8="","",IF('CST-Calculation'!$F8="Indg","",IF('CST-Calculation'!$F8="TEC Del","",IF('CST-Calculation'!AI8>0,'CST-Calculation'!AI8,IF('CST-Calculation'!$F8=0,"",'CST-Calculation'!$F8))))) | AJ8: =IF('CST-Calculation'!AJ8=0,"",'CST-Calculation'!AJ8) | AK8: =IF(AI8="","",IF(AJ8="TEC Rejected","",IF(AJ8="","",ROUND(1.18*AJ8,2)))) | AL8: =IF(AI8="","",IF(AJ8="TEC Rejected","",IF(AJ8="","",ROUND(AI8*AK8,2)))) | AM8: =IF(AN8="","",IF('CST-Calculation'!$F8="Indg","",IF('CST-Calculation'!$F8="TEC Del","",IF('CST-Calculation'!AM8>0,'CST-Calculation'!AM8,IF('CST-Calculation'!$F8=0,"",'CST-Calculation'!$F8))))) | AN8: =IF('CST-Calculation'!AN8=0,"",'CST-Calculation'!AN8) | AO8: =IF(AM8="","",IF(AN8="TEC Rejected","",IF(AN8="","",ROUND(1.3224*Form!$D$10*AN8,2)))) | AP8: =IF(AM8="","",IF(AN8="TEC Rejected","",IF(AN8="","",ROUND(AM8*AO8,2)))) | AQ8: =IF(AR8="","",IF('CST-Calculation'!$F8="Indg","",IF('CST-Calculation'!$F8="TEC Del","",IF('CST-Calculation'!AQ8>0,'CST-Calculation'!AQ8,IF('CST-Calculation'!$F8=0,"",'CST-Calculation'!$F8))))) | AR8: =IF('CST-Calculation'!AR8=0,"",'CST-Calculation'!AR8) | AS8: =IF(AQ8="","",IF(AR8="TEC Rejected","",IF(AR8="","",ROUND(1.3224*Form!$D$10*AR8,2)))) | AT8: =IF(AQ8="","",IF(AR8="TEC Rejected","",IF(AR8="","",ROUND(AQ8*AS8,2)))) | AU8: =IF(AV8="","",IF('CST-Calculation'!$F8="Indg","",IF('CST-Calculation'!$F8="TEC Del","",IF('CST-Calculation'!AU8>0,'CST-Calculation'!AU8,IF('CST-Calculation'!$F8=0,"",'CST-Calculation'!$F8))))) | AV8: =IF('CST-Calculation'!AV8=0,"",'CST-Calculation'!AV8) | AW8: =IF(AU8="","",IF(AV8="TEC Rejected","",IF(AV8="","",ROUND(1.3224*Form!$D$10*AV8,2)))) | AX8: =IF(AU8="","",IF(AV8="TEC Rejected","",IF(AV8="","",ROUND(AU8*AW8,2)))) | AY8: =IF(F8="Indg","INDG",IF(F8="TEC Del","DELETED",IF(F8=0,"DELETED",IF(BD8=0,"NO OFFER",IF(BD8=I8,$H$3,IF(BD8=M8,$L$3,IF(BD8=Q8,$P$3,IF(BD8=U8,$T$3,IF(BD8=Y8,$X$3,IF(BD8=AC8,$AB$3,IF(BD8=AG8,$AF$3,IF(BD8=AK8,$AJ$3,IF(BD8=AO8,$AN$3,IF(BD8=AS8,$AR$3,IF(BD8=AW8,$AV$3))))))))))))))) -> GIS | AZ8: =IF(F8=0,"DELETED",IF(COUNT(H8,L8,P8,T8,X8,AB8,AF8,AJ8,AN8,AR8,AV8)=0,"NO OFFER",IF(COUNT(H8,L8,P8,T8,X8,AB8,AF8,AJ8,AN8,AR8,AV8)=1,"SINGLE","MULTIPLE"))) -> MULTIPLE | BA8: =IF(AND(IF(G8="",TRUE,G8<=ROUNDUP(1.2*F8,0)),IF(K8="",TRUE,K8<=ROUNDUP(1.2*F8,0)),IF(O8="",TRUE,O8<=ROUNDUP(1.2*F8,0)),IF(S8="",TRUE,S8<=ROUNDUP(1.2*F8,0)),IF(W8="",TRUE,W8<=ROUNDUP(1.2*F8,0)),IF(AA8="",TRUE,AA8<=ROUNDUP(1.2*F8,0)),IF(AE8="",TRUE,AE8<=ROUNDUP(1.2*F8,0)),IF(AI8="",TRUE,AI8<=ROUNDUP(1.2*F8,0)),IF(AM8="",TRUE,AM8<=ROUNDUP(1.2*F8,0)),IF(AQ8="",TRUE,AQ8<=ROUNDUP(1.2*F8,0)),IF(AU8="",TRUE,AU8<=ROUNDUP(1.2*F8,0))),"<= 20%","> 20%") -> <= 20% | BB8: =IF(AY8="EST",ROUND(BD8/1.18,2),IF(AY8="ADRYS",ROUND(BD8/1.18,2),ROUND(BD8/(1.3224*Form!$D$10),2))) -> 12.6 | BC8: =IF(OR(AY8="EST",AY8="ADRYS"),ROUND(BE8/1.18,2),ROUND(BE8/(1.3224*Form!$D$10),2)) -> 126 | BD8: =IF(F8="Indg",0,IF(F8="TEC Del",0,IF(AND(IF(G8="",TRUE,G8<=ROUNDUP(1.2*F8,0)),IF(K8="",TRUE,K8<=ROUNDUP(1.2*F8,0)),IF(O8="",TRUE,O8<=ROUNDUP(1.2*F8,0)),IF(S8="",TRUE,S8<=ROUNDUP(1.2*F8,0)),IF(W8="",TRUE,W8<=ROUNDUP(1.2*F8,0)),IF(AA8="",TRUE,AA8<=ROUNDUP(1.2*F8,0)),IF(AE8="",TRUE,AE8<=ROUNDUP(1.2*F8,0)),IF(AI8="",TRUE,AI8<=ROUNDUP(1.2*F8,0)),IF(AM8="",TRUE,AM8<=ROUNDUP(1.2*F8,0)),IF(AQ8="",TRUE,AQ8<=ROUNDUP(1.2*F8,0)),IF(AU8="",TRUE,AU8<=ROUNDUP(1.2*F8,0))),IF(F8=0,0,(IF(SUM(I8,M8,Q8,U8,Y8,AC8,AG8,AK8,AO8,AS8,AW8)=0,0,SMALL((I8,M8,Q8,U8,Y8,AC8,AG8,AK8,AO8,AS8,AW8),COUNTIF((I8:AW8),0)+1)))),IF(BE8=J8,I8,IF(BE8=N8,M8,IF(BE8=R8,Q8,IF(BE8=V8,U8,IF(BE8=Z8,Y8,IF(BE8=AD8,AC8,IF(BE8=AH8,AG8,IF(BE8=AL8,AK8,IF(BE8=AP8,AO8,IF(BE8=AT8,AS8,IF(BE8=AX8,AW8)))))))))))))) -> 1379.3 | BE8: =IF(F8="Indg",0,IF(F8="TEC Del",0,IF(AND(IF(G8="",TRUE,G8<=ROUNDUP(1.2*F8,0)),IF(K8="",TRUE,K8<=ROUNDUP(1.2*F8,0)),IF(O8="",TRUE,O8<=ROUNDUP(1.2*F8,0)),IF(S8="",TRUE,S8<=ROUNDUP(1.2*F8,0)),IF(W8="",TRUE,W8<=ROUNDUP(1.2*F8,0)),IF(AA8="",TRUE,AA8<=ROUNDUP(1.2*F8,0)),IF(AE8="",TRUE,AE8<=ROUNDUP(1.2*F8,0)),IF(AI8="",TRUE,AI8<=ROUNDUP(1.2*F8,0)),IF(AM8="",TRUE,AM8<=ROUNDUP(1.2*F8,0)),IF(AQ8="",TRUE,AQ8<=ROUNDUP(1.2*F8,0)),IF(AU8="",TRUE,AU8<=ROUNDUP(1.2*F8,0))),ROUND(BD8*IF(BD8=I8,G8,IF(BD8=M8,K8,IF(BD8=Q8,O8,IF(BD8=U8,S8,IF(BD8=Y8,W8,IF(BD8=AC8,AA8,IF(BD8=AG8,AE8,IF(BD8=AK8,AI8,IF(BD8=AO8,AM8,IF(BD8=AS8,AQ8,IF(BD8=AW8,AU8))))))))))),2),(IF(SUM(J8,N8,R8,V8,Z8,AD8,AH8,AL8,AP8,AT8,AX8)=0,0,SMALL((J8,N8,R8,V8,Z8,AD8,AH8,AL8,AP8,AT8,AX8),COUNTIF((J8:AX8),0)+1)))))) -> 13793 | BF8: =IF('Annexure-I'!L5="",'Annexure-I'!F5,'Annexure-I'!L5) -> 7.93 | BG8: =IF('Annexure-I'!M5="",'Annexure-I'!G5,'Annexure-I'!M5) -> CONTRACT-A4 | BH8: =IF('Annexure-I'!N5="",'Annexure-I'!H5,'Annexure-I'!N5) -> 40967 | BI8: =IF('Annexure-I'!P5="",'Annexure-I'!J5,'Annexure-I'!P5) -> 14.53 | BJ8: =IF('Annexure-I'!Q5="",'Annexure-I'!K5,'Annexure-I'!Q5) -> 1590.574 | BK8: ='Annexure-I'!F5 -> 7.93 | BL8: ='Annexure-I'!G5 -> CONTRACT-A4 | BM8: =IF('Annexure-I'!H5=0,"",'Annexure-I'!H5) -> 40967 | BN8: ='Annexure-I'!J5 -> 14.53 | BO8: ='Annexure-I'!K5 -> 1590.574 | BP8: =IF(OR(AY8="EST",AY8="ADRYS"),ROUND((BC8*1.18)/(1.3224*Form!$D$10),2),BC8) -> 126 | BQ8: =ROUND(BS8/(1.3224*Form!$D$10),2) -> 145.3 | BR8: =IF(AY8="DELETED",0,BE8) -> 13793 | BS8: =IF(BR8=0,0,ROUND(IF($BQ$1="LPP",ROUND(BJ8*F8,2),ROUND(BO8*F8,2)),2)) -> 15905.74 | BT8: =IF(SUM(BR8:BS8)=0,0,(BR8-BS8)/BS8) -> -0.13282878 | BV8: =IF(F8="Indg",0,IF(F8="TEC Del",0,IF(CA8="Deleted",0,ROUND(F8*BU8,2)))) -> 0 | BW8: =IF(OR(AY8="EST",AY8="ADRYS"),ROUND(1.18*BU8,2),ROUND(BU8*1.3224*Form!$D$10,2)) -> 0 | BX8: =IF(F8="Indg",0,IF(F8="TEC Del",0,IF(CA8="Deleted",0,ROUND(BW8*F8,2)))) -> 0 | BY8: =IF((BX8)=0,0,(BX8-BS8)/BS8) -> 0 | BZ8: =IF(CA8="Deleted",0,ROUND(BO8*F8,2)) -> 15905.74
A9: =SUBTOTAL(2,$B$5:B9) -> 5 | B9: 5 | C9: X5 | D9: IC (Integrated Circuit ) | E9: 9 | F9: ='Annexure-I'!E6 -> 9 | G9: =IF('CST-Calculation'!G9=0,"",'CST-Calculation'!G9) | H9: =IF('CST-Calculation'!H9=0,"",'CST-Calculation'!H9) | I9: =IF(G9="","",IF(H9="TEC Rejected","",IF(H9="","",ROUND(1.3224*Form!$D$10*H9,2)))) | J9: =IF(G9="","",IF(H9="TEC Rejected","",IF(H9="","",ROUND(G9*I9,2)))) | K9: =IF(L9="","",IF('CST-Calculation'!$F9="Indg","",IF('CST-Calculation'!$F9="TEC Del","",IF('CST-Calculation'!K9>0,'CST-Calculation'!K9,IF('CST-Calculation'!$F9=0,"",'CST-Calculation'!$F9))))) | L9: =IF('CST-Calculation'!L9=0,"",'CST-Calculation'!L9) | M9: =IF(K9="","",IF(L9="TEC Rejected","",IF(L9="","",ROUND(1.3224*Form!$D$10*L9,2)))) | N9: =IF(K9="","",IF(L9="TEC Rejected","",IF(L9="","",ROUND(K9*M9,2)))) | O9: =IF(P9="","",IF('CST-Calculation'!$F9="Indg","",IF('CST-Calculation'!$F9="TEC Del","",IF('CST-Calculation'!O9>0,'CST-Calculation'!O9,IF('CST-Calculation'!$F9=0,"",'CST-Calculation'!$F9))))) -> 9 | P9: =IF('CST-Calculation'!P9=0,"",'CST-Calculation'!P9) -> 15 | Q9: =IF(O9="","",IF(P9="TEC Rejected","",IF(P9="","",ROUND(1.3224*Form!$D$10*P9,2)))) -> 1642.02 | R9: =IF(O9="","",IF(P9="TEC Rejected","",IF(P9="","",ROUND(O9*Q9,2)))) -> 14778.18 | S9: =IF(T9="","",IF('CST-Calculation'!$F9="Indg","",IF('CST-Calculation'!$F9="TEC Del","",IF('CST-Calculation'!S9>0,'CST-Calculation'!S9,IF('CST-Calculation'!$F9=0,"",'CST-Calculation'!$F9))))) -> 9 | T9: =IF('CST-Calculation'!T9=0,"",'CST-Calculation'!T9) -> 33 | U9: =IF(S9="","",IF(T9="TEC Rejected","",IF(T9="","",ROUND(1.3224*Form!$D$10*T9,2)))) -> 3612.45 | V9: =IF(S9="","",IF(T9="TEC Rejected","",IF(T9="","",ROUND(S9*U9,2)))) -> 32512.05 | W9: =IF(X9="","",IF('CST-Calculation'!$F9="Indg","",IF('CST-Calculation'!$F9="TEC Del","",IF('CST-Calculation'!W9>0,'CST-Calculation'!W9,IF('CST-Calculation'!$F9=0,"",'CST-Calculation'!$F9))))) | X9: =IF('CST-Calculation'!X9=0,"",'CST-Calculation'!X9) | Y9: =IF(W9="","",IF(X9="TEC Rejected","",IF(X9="","",ROUND(1.3224*Form!$D$10*X9,2)))) | Z9: =IF(W9="","",IF(X9="TEC Rejected","",IF(X9="","",ROUND(W9*Y9,2)))) | AA9: =IF(AB9="","",IF('CST-Calculation'!$F9="Indg","",IF('CST-Calculation'!$F9="TEC Del","",IF('CST-Calculation'!AA9>0,'CST-Calculation'!AA9,IF('CST-Calculation'!$F9=0,"",'CST-Calculation'!$F9))))) -> 9 | AB9: =IF('CST-Calculation'!AB9=0,"",'CST-Calculation'!AB9) -> 915 | AC9: =IF(AA9="","",IF(AB9="TEC Rejected","",IF(AB9="","",ROUND(1.18*AB9,2)))) -> 1079.7 | AD9: =IF(AA9="","",IF(AB9="TEC Rejected","",IF(AB9="","",ROUND(AA9*AC9,2)))) -> 9717.3 | AE9: =IF(AF9="","",IF('CST-Calculation'!$F9="Indg","",IF('CST-Calculation'!$F9="TEC Del","",IF('CST-Calculation'!AE9>0,'CST-Calculation'!AE9,IF('CST-Calculation'!$F9=0,"",'CST-Calculation'!$F9))))) | AF9: =IF('CST-Calculation'!AF9=0,"",'CST-Calculation'!AF9) | AG9: =IF(AE9="","",IF(AF9="TEC Rejected","",IF(AF9="","",ROUND(1.3224*Form!$D$10*AF9,2)))) | AH9: =IF(AE9="","",IF(AF9="TEC Rejected","",IF(AF9="","",ROUND(AE9*AG9,2)))) | AI9: =IF(AJ9="","",IF('CST-Calculation'!$F9="Indg","",IF('CST-Calculation'!$F9="TEC Del","",IF('CST-Calculation'!AI9>0,'CST-Calculation'!AI9,IF('CST-Calculation'!$F9=0,"",'CST-Calculation'!$F9))))) | AJ9: =IF('CST-Calculation'!AJ9=0,"",'CST-Calculation'!AJ9) | AK9: =IF(AI9="","",IF(AJ9="TEC Rejected","",IF(AJ9="","",ROUND(1.18*AJ9,2)))) | AL9: =IF(AI9="","",IF(AJ9="TEC Rejected","",IF(AJ9="","",ROUND(AI9*AK9,2)))) | AM9: =IF(AN9="","",IF('CST-Calculation'!$F9="Indg","",IF('CST-Calculation'!$F9="TEC Del","",IF('CST-Calculation'!AM9>0,'CST-Calculation'!AM9,IF('CST-Calculation'!$F9=0,"",'CST-Calculation'!$F9))))) | AN9: =IF('CST-Calculation'!AN9=0,"",'CST-Calculation'!AN9) | AO9: =IF(AM9="","",IF(AN9="TEC Rejected","",IF(AN9="","",ROUND(1.3224*Form!$D$10*AN9,2)))) | AP9: =IF(AM9="","",IF(AN9="TEC Rejected","",IF(AN9="","",ROUND(AM9*AO9,2)))) | AQ9: =IF(AR9="","",IF('CST-Calculation'!$F9="Indg","",IF('CST-Calculation'!$F9="TEC Del","",IF('CST-Calculation'!AQ9>0,'CST-Calculation'!AQ9,IF('CST-Calculation'!$F9=0,"",'CST-Calculation'!$F9))))) | AR9: =IF('CST-Calculation'!AR9=0,"",'CST-Calculation'!AR9) | AS9: =IF(AQ9="","",IF(AR9="TEC Rejected","",IF(AR9="","",ROUND(1.3224*Form!$D$10*AR9,2)))) | AT9: =IF(AQ9="","",IF(AR9="TEC Rejected","",IF(AR9="","",ROUND(AQ9*AS9,2)))) | AU9: =IF(AV9="","",IF('CST-Calculation'!$F9="Indg","",IF('CST-Calculation'!$F9="TEC Del","",IF('CST-Calculation'!AU9>0,'CST-Calculation'!AU9,IF('CST-Calculation'!$F9=0,"",'CST-Calculation'!$F9))))) | AV9: =IF('CST-Calculation'!AV9=0,"",'CST-Calculation'!AV9) | AW9: =IF(AU9="","",IF(AV9="TEC Rejected","",IF(AV9="","",ROUND(1.3224*Form!$D$10*AV9,2)))) | AX9: =IF(AU9="","",IF(AV9="TEC Rejected","",IF(AV9="","",ROUND(AU9*AW9,2)))) | AY9: =IF(F9="Indg","INDG",IF(F9="TEC Del","DELETED",IF(F9=0,"DELETED",IF(BD9=0,"NO OFFER",IF(BD9=I9,$H$3,IF(BD9=M9,$L$3,IF(BD9=Q9,$P$3,IF(BD9=U9,$T$3,IF(BD9=Y9,$X$3,IF(BD9=AC9,$AB$3,IF(BD9=AG9,$AF$3,IF(BD9=AK9,$AJ$3,IF(BD9=AO9,$AN$3,IF(BD9=AS9,$AR$3,IF(BD9=AW9,$AV$3))))))))))))))) -> ADRYS | AZ9: =IF(F9=0,"DELETED",IF(COUNT(H9,L9,P9,T9,X9,AB9,AF9,AJ9,AN9,AR9,AV9)=0,"NO OFFER",IF(COUNT(H9,L9,P9,T9,X9,AB9,AF9,AJ9,AN9,AR9,AV9)=1,"SINGLE","MULTIPLE"))) -> MULTIPLE | BA9: =IF(AND(IF(G9="",TRUE,G9<=ROUNDUP(1.2*F9,0)),IF(K9="",TRUE,K9<=ROUNDUP(1.2*F9,0)),IF(O9="",TRUE,O9<=ROUNDUP(1.2*F9,0)),IF(S9="",TRUE,S9<=ROUNDUP(1.2*F9,0)),IF(W9="",TRUE,W9<=ROUNDUP(1.2*F9,0)),IF(AA9="",TRUE,AA9<=ROUNDUP(1.2*F9,0)),IF(AE9="",TRUE,AE9<=ROUNDUP(1.2*F9,0)),IF(AI9="",TRUE,AI9<=ROUNDUP(1.2*F9,0)),IF(AM9="",TRUE,AM9<=ROUNDUP(1.2*F9,0)),IF(AQ9="",TRUE,AQ9<=ROUNDUP(1.2*F9,0)),IF(AU9="",TRUE,AU9<=ROUNDUP(1.2*F9,0))),"<= 20%","> 20%") -> <= 20% | BB9: =IF(AY9="EST",ROUND(BD9/1.18,2),IF(AY9="ADRYS",ROUND(BD9/1.18,2),ROUND(BD9/(1.3224*Form!$D$10),2))) -> 915 | BC9: =IF(OR(AY9="EST",AY9="ADRYS"),ROUND(BE9/1.18,2),ROUND(BE9/(1.3224*Form!$D$10),2)) -> 8235 | BD9: =IF(F9="Indg",0,IF(F9="TEC Del",0,IF(AND(IF(G9="",TRUE,G9<=ROUNDUP(1.2*F9,0)),IF(K9="",TRUE,K9<=ROUNDUP(1.2*F9,0)),IF(O9="",TRUE,O9<=ROUNDUP(1.2*F9,0)),IF(S9="",TRUE,S9<=ROUNDUP(1.2*F9,0)),IF(W9="",TRUE,W9<=ROUNDUP(1.2*F9,0)),IF(AA9="",TRUE,AA9<=ROUNDUP(1.2*F9,0)),IF(AE9="",TRUE,AE9<=ROUNDUP(1.2*F9,0)),IF(AI9="",TRUE,AI9<=ROUNDUP(1.2*F9,0)),IF(AM9="",TRUE,AM9<=ROUNDUP(1.2*F9,0)),IF(AQ9="",TRUE,AQ9<=ROUNDUP(1.2*F9,0)),IF(AU9="",TRUE,AU9<=ROUNDUP(1.2*F9,0))),IF(F9=0,0,(IF(SUM(I9,M9,Q9,U9,Y9,AC9,AG9,AK9,AO9,AS9,AW9)=0,0,SMALL((I9,M9,Q9,U9,Y9,AC9,AG9,AK9,AO9,AS9,AW9),COUNTIF((I9:AW9),0)+1)))),IF(BE9=J9,I9,IF(BE9=N9,M9,IF(BE9=R9,Q9,IF(BE9=V9,U9,IF(BE9=Z9,Y9,IF(BE9=AD9,AC9,IF(BE9=AH9,AG9,IF(BE9=AL9,AK9,IF(BE9=AP9,AO9,IF(BE9=AT9,AS9,IF(BE9=AX9,AW9)))))))))))))) -> 1079.7 | BE9: =IF(F9="Indg",0,IF(F9="TEC Del",0,IF(AND(IF(G9="",TRUE,G9<=ROUNDUP(1.2*F9,0)),IF(K9="",TRUE,K9<=ROUNDUP(1.2*F9,0)),IF(O9="",TRUE,O9<=ROUNDUP(1.2*F9,0)),IF(S9="",TRUE,S9<=ROUNDUP(1.2*F9,0)),IF(W9="",TRUE,W9<=ROUNDUP(1.2*F9,0)),IF(AA9="",TRUE,AA9<=ROUNDUP(1.2*F9,0)),IF(AE9="",TRUE,AE9<=ROUNDUP(1.2*F9,0)),IF(AI9="",TRUE,AI9<=ROUNDUP(1.2*F9,0)),IF(AM9="",TRUE,AM9<=ROUNDUP(1.2*F9,0)),IF(AQ9="",TRUE,AQ9<=ROUNDUP(1.2*F9,0)),IF(AU9="",TRUE,AU9<=ROUNDUP(1.2*F9,0))),ROUND(BD9*IF(BD9=I9,G9,IF(BD9=M9,K9,IF(BD9=Q9,O9,IF(BD9=U9,S9,IF(BD9=Y9,W9,IF(BD9=AC9,AA9,IF(BD9=AG9,AE9,IF(BD9=AK9,AI9,IF(BD9=AO9,AM9,IF(BD9=AS9,AQ9,IF(BD9=AW9,AU9))))))))))),2),(IF(SUM(J9,N9,R9,V9,Z9,AD9,AH9,AL9,AP9,AT9,AX9)=0,0,SMALL((J9,N9,R9,V9,Z9,AD9,AH9,AL9,AP9,AT9,AX9),COUNTIF((J9:AX9),0)+1)))))) -> 9717.3 | BF9: =IF('Annexure-I'!L6="",'Annexure-I'!F6,'Annexure-I'!L6) -> 14 | BG9: =IF('Annexure-I'!M6="",'Annexure-I'!G6,'Annexure-I'!M6) -> CONTRACT-A5 | BH9: =IF('Annexure-I'!N6="",'Annexure-I'!H6,'Annexure-I'!N6) -> 43298 | BI9: =IF('Annexure-I'!P6="",'Annexure-I'!J6,'Annexure-I'!P6) -> 18.87 | BJ9: =IF('Annexure-I'!Q6="",'Annexure-I'!K6,'Annexure-I'!Q6) -> 2065.6663 | BK9: ='Annexure-I'!F6 -> 14 | BL9: ='Annexure-I'!G6 -> CONTRACT-A5 | BM9: =IF('Annexure-I'!H6=0,"",'Annexure-I'!H6) -> 43298 | BN9: ='Annexure-I'!J6 -> 18.87 | BO9: ='Annexure-I'!K6 -> 2065.6663 | BP9: =IF(OR(AY9="EST",AY9="ADRYS"),ROUND((BC9*1.18)/(1.3224*Form!$D$10),2),BC9) -> 88.77 | BQ9: =ROUND(BS9/(1.3224*Form!$D$10),2) -> 169.83 | BR9: =IF(AY9="DELETED",0,BE9) -> 9717.3 | BS9: =IF(BR9=0,0,ROUND(IF($BQ$1="LPP",ROUND(BJ9*F9,2),ROUND(BO9*F9,2)),2)) -> 18591 | BT9: =IF(SUM(BR9:BS9)=0,0,(BR9-BS9)/BS9) -> -0.4773116 | BV9: =IF(F9="Indg",0,IF(F9="TEC Del",0,IF(CA9="Deleted",0,ROUND(F9*BU9,2)))) -> 0 | BW9: =IF(OR(AY9="EST",AY9="ADRYS"),ROUND(1.18*BU9,2),ROUND(BU9*1.3224*Form!$D$10,2)) -> 0 | BX9: =IF(F9="Indg",0,IF(F9="TEC Del",0,IF(CA9="Deleted",0,ROUND(BW9*F9,2)))) -> 0 | BY9: =IF((BX9)=0,0,(BX9-BS9)/BS9) -> 0 | BZ9: =IF(CA9="Deleted",0,ROUND(BO9*F9,2)) -> 18591
A10: =SUBTOTAL(2,$B$5:B10) -> 6 | B10: 6 | C10: X6 | D10: DIODE | E10: 11 | F10: ='Annexure-I'!E7 -> 11 | G10: =IF('CST-Calculation'!G10=0,"",'CST-Calculation'!G10) | H10: =IF('CST-Calculation'!H10=0,"",'CST-Calculation'!H10) | I10: =IF(G10="","",IF(H10="TEC Rejected","",IF(H10="","",ROUND(1.3224*Form!$D$10*H10,2)))) | J10: =IF(G10="","",IF(H10="TEC Rejected","",IF(H10="","",ROUND(G10*I10,2)))) | K10: =IF(L10="","",IF('CST-Calculation'!$F10="Indg","",IF('CST-Calculation'!$F10="TEC Del","",IF('CST-Calculation'!K10>0,'CST-Calculation'!K10,IF('CST-Calculation'!$F10=0,"",'CST-Calculation'!$F10))))) | L10: =IF('CST-Calculation'!L10=0,"",'CST-Calculation'!L10) | M10: =IF(K10="","",IF(L10="TEC Rejected","",IF(L10="","",ROUND(1.3224*Form!$D$10*L10,2)))) | N10: =IF(K10="","",IF(L10="TEC Rejected","",IF(L10="","",ROUND(K10*M10,2)))) | O10: =IF(P10="","",IF('CST-Calculation'!$F10="Indg","",IF('CST-Calculation'!$F10="TEC Del","",IF('CST-Calculation'!O10>0,'CST-Calculation'!O10,IF('CST-Calculation'!$F10=0,"",'CST-Calculation'!$F10))))) -> 11 | P10: =IF('CST-Calculation'!P10=0,"",'CST-Calculation'!P10) -> 3 | Q10: =IF(O10="","",IF(P10="TEC Rejected","",IF(P10="","",ROUND(1.3224*Form!$D$10*P10,2)))) -> 328.4 | R10: =IF(O10="","",IF(P10="TEC Rejected","",IF(P10="","",ROUND(O10*Q10,2)))) -> 3612.4 | S10: =IF(T10="","",IF('CST-Calculation'!$F10="Indg","",IF('CST-Calculation'!$F10="TEC Del","",IF('CST-Calculation'!S10>0,'CST-Calculation'!S10,IF('CST-Calculation'!$F10=0,"",'CST-Calculation'!$F10))))) -> 11 | T10: =IF('CST-Calculation'!T10=0,"",'CST-Calculation'!T10) -> 16.5 | U10: =IF(S10="","",IF(T10="TEC Rejected","",IF(T10="","",ROUND(1.3224*Form!$D$10*T10,2)))) -> 1806.23 | V10: =IF(S10="","",IF(T10="TEC Rejected","",IF(T10="","",ROUND(S10*U10,2)))) -> 19868.53 | W10: =IF(X10="","",IF('CST-Calculation'!$F10="Indg","",IF('CST-Calculation'!$F10="TEC Del","",IF('CST-Calculation'!W10>0,'CST-Calculation'!W10,IF('CST-Calculation'!$F10=0,"",'CST-Calculation'!$F10))))) | X10: =IF('CST-Calculation'!X10=0,"",'CST-Calculation'!X10) | Y10: =IF(W10="","",IF(X10="TEC Rejected","",IF(X10="","",ROUND(1.3224*Form!$D$10*X10,2)))) | Z10: =IF(W10="","",IF(X10="TEC Rejected","",IF(X10="","",ROUND(W10*Y10,2)))) | AA10: =IF(AB10="","",IF('CST-Calculation'!$F10="Indg","",IF('CST-Calculation'!$F10="TEC Del","",IF('CST-Calculation'!AA10>0,'CST-Calculation'!AA10,IF('CST-Calculation'!$F10=0,"",'CST-Calculation'!$F10))))) -> 11 | AB10: =IF('CST-Calculation'!AB10=0,"",'CST-Calculation'!AB10) -> 165 | AC10: =IF(AA10="","",IF(AB10="TEC Rejected","",IF(AB10="","",ROUND(1.18*AB10,2)))) -> 194.7 | AD10: =IF(AA10="","",IF(AB10="TEC Rejected","",IF(AB10="","",ROUND(AA10*AC10,2)))) -> 2141.7 | AE10: =IF(AF10="","",IF('CST-Calculation'!$F10="Indg","",IF('CST-Calculation'!$F10="TEC Del","",IF('CST-Calculation'!AE10>0,'CST-Calculation'!AE10,IF('CST-Calculation'!$F10=0,"",'CST-Calculation'!$F10))))) | AF10: =IF('CST-Calculation'!AF10=0,"",'CST-Calculation'!AF10) | AG10: =IF(AE10="","",IF(AF10="TEC Rejected","",IF(AF10="","",ROUND(1.3224*Form!$D$10*AF10,2)))) | AH10: =IF(AE10="","",IF(AF10="TEC Rejected","",IF(AF10="","",ROUND(AE10*AG10,2)))) | AI10: =IF(AJ10="","",IF('CST-Calculation'!$F10="Indg","",IF('CST-Calculation'!$F10="TEC Del","",IF('CST-Calculation'!AI10>0,'CST-Calculation'!AI10,IF('CST-Calculation'!$F10=0,"",'CST-Calculation'!$F10))))) | AJ10: =IF('CST-Calculation'!AJ10=0,"",'CST-Calculation'!AJ10) | AK10: =IF(AI10="","",IF(AJ10="TEC Rejected","",IF(AJ10="","",ROUND(1.18*AJ10,2)))) | AL10: =IF(AI10="","",IF(AJ10="TEC Rejected","",IF(AJ10="","",ROUND(AI10*AK10,2)))) | AM10: =IF(AN10="","",IF('CST-Calculation'!$F10="Indg","",IF('CST-Calculation'!$F10="TEC Del","",IF('CST-Calculation'!AM10>0,'CST-Calculation'!AM10,IF('CST-Calculation'!$F10=0,"",'CST-Calculation'!$F10))))) | AN10: =IF('CST-Calculation'!AN10=0,"",'CST-Calculation'!AN10) | AO10: =IF(AM10="","",IF(AN10="TEC Rejected","",IF(AN10="","",ROUND(1.3224*Form!$D$10*AN10,2)))) | AP10: =IF(AM10="","",IF(AN10="TEC Rejected","",IF(AN10="","",ROUND(AM10*AO10,2)))) | AQ10: =IF(AR10="","",IF('CST-Calculation'!$F10="Indg","",IF('CST-Calculation'!$F10="TEC Del","",IF('CST-Calculation'!AQ10>0,'CST-Calculation'!AQ10,IF('CST-Calculation'!$F10=0,"",'CST-Calculation'!$F10))))) | AR10: =IF('CST-Calculation'!AR10=0,"",'CST-Calculation'!AR10) | AS10: =IF(AQ10="","",IF(AR10="TEC Rejected","",IF(AR10="","",ROUND(1.3224*Form!$D$10*AR10,2)))) | AT10: =IF(AQ10="","",IF(AR10="TEC Rejected","",IF(AR10="","",ROUND(AQ10*AS10,2)))) | AU10: =IF(AV10="","",IF('CST-Calculation'!$F10="Indg","",IF('CST-Calculation'!$F10="TEC Del","",IF('CST-Calculation'!AU10>0,'CST-Calculation'!AU10,IF('CST-Calculation'!$F10=0,"",'CST-Calculation'!$F10))))) | AV10: =IF('CST-Calculation'!AV10=0,"",'CST-Calculation'!AV10) | AW10: =IF(AU10="","",IF(AV10="TEC Rejected","",IF(AV10="","",ROUND(1.3224*Form!$D$10*AV10,2)))) | AX10: =IF(AU10="","",IF(AV10="TEC Rejected","",IF(AV10="","",ROUND(AU10*AW10,2)))) | AY10: =IF(F10="Indg","INDG",IF(F10="TEC Del","DELETED",IF(F10=0,"DELETED",IF(BD10=0,"NO OFFER",IF(BD10=I10,$H$3,IF(BD10=M10,$L$3,IF(BD10=Q10,$P$3,IF(BD10=U10,$T$3,IF(BD10=Y10,$X$3,IF(BD10=AC10,$AB$3,IF(BD10=AG10,$AF$3,IF(BD10=AK10,$AJ$3,IF(BD10=AO10,$AN$3,IF(BD10=AS10,$AR$3,IF(BD10=AW10,$AV$3))))))))))))))) -> ADRYS | AZ10: =IF(F10=0,"DELETED",IF(COUNT(H10,L10,P10,T10,X10,AB10,AF10,AJ10,AN10,AR10,AV10)=0,"NO OFFER",IF(COUNT(H10,L10,P10,T10,X10,AB10,AF10,AJ10,AN10,AR10,AV10)=1,"SINGLE","MULTIPLE"))) -> MULTIPLE | BA10: =IF(AND(IF(G10="",TRUE,G10<=ROUNDUP(1.2*F10,0)),IF(K10="",TRUE,K10<=ROUNDUP(1.2*F10,0)),IF(O10="",TRUE,O10<=ROUNDUP(1.2*F10,0)),IF(S10="",TRUE,S10<=ROUNDUP(1.2*F10,0)),IF(W10="",TRUE,W10<=ROUNDUP(1.2*F10,0)),IF(AA10="",TRUE,AA10<=ROUNDUP(1.2*F10,0)),IF(AE10="",TRUE,AE10<=ROUNDUP(1.2*F10,0)),IF(AI10="",TRUE,AI10<=ROUNDUP(1.2*F10,0)),IF(AM10="",TRUE,AM10<=ROUNDUP(1.2*F10,0)),IF(AQ10="",TRUE,AQ10<=ROUNDUP(1.2*F10,0)),IF(AU10="",TRUE,AU10<=ROUNDUP(1.2*F10,0))),"<= 20%","> 20%") -> <= 20% | BB10: =IF(AY10="EST",ROUND(BD10/1.18,2),IF(AY10="ADRYS",ROUND(BD10/1.18,2),ROUND(BD10/(1.3224*Form!$D$10),2))) -> 165 | BC10: =IF(OR(AY10="EST",AY10="ADRYS"),ROUND(BE10/1.18,2),ROUND(BE10/(1.3224*Form!$D$10),2)) -> 1815 | BD10: =IF(F10="Indg",0,IF(F10="TEC Del",0,IF(AND(IF(G10="",TRUE,G10<=ROUNDUP(1.2*F10,0)),IF(K10="",TRUE,K10<=ROUNDUP(1.2*F10,0)),IF(O10="",TRUE,O10<=ROUNDUP(1.2*F10,0)),IF(S10="",TRUE,S10<=ROUNDUP(1.2*F10,0)),IF(W10="",TRUE,W10<=ROUNDUP(1.2*F10,0)),IF(AA10="",TRUE,AA10<=ROUNDUP(1.2*F10,0)),IF(AE10="",TRUE,AE10<=ROUNDUP(1.2*F10,0)),IF(AI10="",TRUE,AI10<=ROUNDUP(1.2*F10,0)),IF(AM10="",TRUE,AM10<=ROUNDUP(1.2*F10,0)),IF(AQ10="",TRUE,AQ10<=ROUNDUP(1.2*F10,0)),IF(AU10="",TRUE,AU10<=ROUNDUP(1.2*F10,0))),IF(F10=0,0,(IF(SUM(I10,M10,Q10,U10,Y10,AC10,AG10,AK10,AO10,AS10,AW10)=0,0,SMALL((I10,M10,Q10,U10,Y10,AC10,AG10,AK10,AO10,AS10,AW10),COUNTIF((I10:AW10),0)+1)))),IF(BE10=J10,I10,IF(BE10=N10,M10,IF(BE10=R10,Q10,IF(BE10=V10,U10,IF(BE10=Z10,Y10,IF(BE10=AD10,AC10,IF(BE10=AH10,AG10,IF(BE10=AL10,AK10,IF(BE10=AP10,AO10,IF(BE10=AT10,AS10,IF(BE10=AX10,AW10)))))))))))))) -> 194.7 | BE10: =IF(F10="Indg",0,IF(F10="TEC Del",0,IF(AND(IF(G10="",TRUE,G10<=ROUNDUP(1.2*F10,0)),IF(K10="",TRUE,K10<=ROUNDUP(1.2*F10,0)),IF(O10="",TRUE,O10<=ROUNDUP(1.2*F10,0)),IF(S10="",TRUE,S10<=ROUNDUP(1.2*F10,0)),IF(W10="",TRUE,W10<=ROUNDUP(1.2*F10,0)),IF(AA10="",TRUE,AA10<=ROUNDUP(1.2*F10,0)),IF(AE10="",TRUE,AE10<=ROUNDUP(1.2*F10,0)),IF(AI10="",TRUE,AI10<=ROUNDUP(1.2*F10,0)),IF(AM10="",TRUE,AM10<=ROUNDUP(1.2*F10,0)),IF(AQ10="",TRUE,AQ10<=ROUNDUP(1.2*F10,0)),IF(AU10="",TRUE,AU10<=ROUNDUP(1.2*F10,0))),ROUND(BD10*IF(BD10=I10,G10,IF(BD10=M10,K10,IF(BD10=Q10,O10,IF(BD10=U10,S10,IF(BD10=Y10,W10,IF(BD10=AC10,AA10,IF(BD10=AG10,AE10,IF(BD10=AK10,AI10,IF(BD10=AO10,AM10,IF(BD10=AS10,AQ10,IF(BD10=AW10,AU10))))))))))),2),(IF(SUM(J10,N10,R10,V10,Z10,AD10,AH10,AL10,AP10,AT10,AX10)=0,0,SMALL((J10,N10,R10,V10,Z10,AD10,AH10,AL10,AP10,AT10,AX10),COUNTIF((J10:AX10),0)+1)))))) -> 2141.7 | BF10: =IF('Annexure-I'!L7="",'Annexure-I'!F7,'Annexure-I'!L7) -> 12.02 | BG10: =IF('Annexure-I'!M7="",'Annexure-I'!G7,'Annexure-I'!M7) -> CONTRACT-A6 | BH10: =IF('Annexure-I'!N7="",'Annexure-I'!H7,'Annexure-I'!N7) -> 41789 | BI10: =IF('Annexure-I'!P7="",'Annexure-I'!J7,'Annexure-I'!P7) -> 19.79 | BJ10: =IF('Annexure-I'!Q7="",'Annexure-I'!K7,'Annexure-I'!Q7) -> 2166.3771 | BK10: ='Annexure-I'!F7 -> 12.02 | BL10: ='Annexure-I'!G7 -> CONTRACT-A6 | BM10: =IF('Annexure-I'!H7=0,"",'Annexure-I'!H7) -> 41789 | BN10: ='Annexure-I'!J7 -> 19.79 | BO10: ='Annexure-I'!K7 -> 2166.3771 | BP10: =IF(OR(AY10="EST",AY10="ADRYS"),ROUND((BC10*1.18)/(1.3224*Form!$D$10),2),BC10) -> 19.56 | BQ10: =ROUND(BS10/(1.3224*Form!$D$10),2) -> 217.69 | BR10: =IF(AY10="DELETED",0,BE10) -> 2141.7 | BS10: =IF(BR10=0,0,ROUND(IF($BQ$1="LPP",ROUND(BJ10*F10,2),ROUND(BO10*F10,2)),2)) -> 23830.15 | BT10: =IF(SUM(BR10:BS10)=0,0,(BR10-BS10)/BS10) -> -0.91012646 | BV10: =IF(F10="Indg",0,IF(F10="TEC Del",0,IF(CA10="Deleted",0,ROUND(F10*BU10,2)))) -> 0 | BW10: =IF(OR(AY10="EST",AY10="ADRYS"),ROUND(1.18*BU10,2),ROUND(BU10*1.3224*Form!$D$10,2)) -> 0 | BX10: =IF(F10="Indg",0,IF(F10="TEC Del",0,IF(CA10="Deleted",0,ROUND(BW10*F10,2)))) -> 0 | BY10: =IF((BX10)=0,0,(BX10-BS10)/BS10) -> 0 | BZ10: =IF(CA10="Deleted",0,ROUND(BO10*F10,2)) -> 23830.15
A11: =SUBTOTAL(2,$B$5:B11) -> 7 | B11: 7 | C11: X7 | D11: TRANSISTOR | E11: 6 | F11: ='Annexure-I'!E8 -> 6 | G11: =IF('CST-Calculation'!G11=0,"",'CST-Calculation'!G11) | H11: =IF('CST-Calculation'!H11=0,"",'CST-Calculation'!H11) | I11: =IF(G11="","",IF(H11="TEC Rejected","",IF(H11="","",ROUND(1.3224*Form!$D$10*H11,2)))) | J11: =IF(G11="","",IF(H11="TEC Rejected","",IF(H11="","",ROUND(G11*I11,2)))) | K11: =IF(L11="","",IF('CST-Calculation'!$F11="Indg","",IF('CST-Calculation'!$F11="TEC Del","",IF('CST-Calculation'!K11>0,'CST-Calculation'!K11,IF('CST-Calculation'!$F11=0,"",'CST-Calculation'!$F11))))) | L11: =IF('CST-Calculation'!L11=0,"",'CST-Calculation'!L11) | M11: =IF(K11="","",IF(L11="TEC Rejected","",IF(L11="","",ROUND(1.3224*Form!$D$10*L11,2)))) | N11: =IF(K11="","",IF(L11="TEC Rejected","",IF(L11="","",ROUND(K11*M11,2)))) | O11: =IF(P11="","",IF('CST-Calculation'!$F11="Indg","",IF('CST-Calculation'!$F11="TEC Del","",IF('CST-Calculation'!O11>0,'CST-Calculation'!O11,IF('CST-Calculation'!$F11=0,"",'CST-Calculation'!$F11))))) -> 6 | P11: =IF('CST-Calculation'!P11=0,"",'CST-Calculation'!P11) -> 9 | Q11: =IF(O11="","",IF(P11="TEC Rejected","",IF(P11="","",ROUND(1.3224*Form!$D$10*P11,2)))) -> 985.21 | R11: =IF(O11="","",IF(P11="TEC Rejected","",IF(P11="","",ROUND(O11*Q11,2)))) -> 5911.26 | S11: =IF(T11="","",IF('CST-Calculation'!$F11="Indg","",IF('CST-Calculation'!$F11="TEC Del","",IF('CST-Calculation'!S11>0,'CST-Calculation'!S11,IF('CST-Calculation'!$F11=0,"",'CST-Calculation'!$F11))))) -> 6 | T11: =IF('CST-Calculation'!T11=0,"",'CST-Calculation'!T11) -> 19.5 | U11: =IF(S11="","",IF(T11="TEC Rejected","",IF(T11="","",ROUND(1.3224*Form!$D$10*T11,2)))) -> 2134.63 | V11: =IF(S11="","",IF(T11="TEC Rejected","",IF(T11="","",ROUND(S11*U11,2)))) -> 12807.78 | W11: =IF(X11="","",IF('CST-Calculation'!$F11="Indg","",IF('CST-Calculation'!$F11="TEC Del","",IF('CST-Calculation'!W11>0,'CST-Calculation'!W11,IF('CST-Calculation'!$F11=0,"",'CST-Calculation'!$F11))))) | X11: =IF('CST-Calculation'!X11=0,"",'CST-Calculation'!X11) | Y11: =IF(W11="","",IF(X11="TEC Rejected","",IF(X11="","",ROUND(1.3224*Form!$D$10*X11,2)))) | Z11: =IF(W11="","",IF(X11="TEC Rejected","",IF(X11="","",ROUND(W11*Y11,2)))) | AA11: =IF(AB11="","",IF('CST-Calculation'!$F11="Indg","",IF('CST-Calculation'!$F11="TEC Del","",IF('CST-Calculation'!AA11>0,'CST-Calculation'!AA11,IF('CST-Calculation'!$F11=0,"",'CST-Calculation'!$F11))))) -> 6 | AB11: =IF('CST-Calculation'!AB11=0,"",'CST-Calculation'!AB11) -> 315 | AC11: =IF(AA11="","",IF(AB11="TEC Rejected","",IF(AB11="","",ROUND(1.18*AB11,2)))) -> 371.7 | AD11: =IF(AA11="","",IF(AB11="TEC Rejected","",IF(AB11="","",ROUND(AA11*AC11,2)))) -> 2230.2 | AE11: =IF(AF11="","",IF('CST-Calculation'!$F11="Indg","",IF('CST-Calculation'!$F11="TEC Del","",IF('CST-Calculation'!AE11>0,'CST-Calculation'!AE11,IF('CST-Calculation'!$F11=0,"",'CST-Calculation'!$F11))))) | AF11: =IF('CST-Calculation'!AF11=0,"",'CST-Calculation'!AF11) | AG11: =IF(AE11="","",IF(AF11="TEC Rejected","",IF(AF11="","",ROUND(1.3224*Form!$D$10*AF11,2)))) | AH11: =IF(AE11="","",IF(AF11="TEC Rejected","",IF(AF11="","",ROUND(AE11*AG11,2)))) | AI11: =IF(AJ11="","",IF('CST-Calculation'!$F11="Indg","",IF('CST-Calculation'!$F11="TEC Del","",IF('CST-Calculation'!AI11>0,'CST-Calculation'!AI11,IF('CST-Calculation'!$F11=0,"",'CST-Calculation'!$F11))))) | AJ11: =IF('CST-Calculation'!AJ11=0,"",'CST-Calculation'!AJ11) | AK11: =IF(AI11="","",IF(AJ11="TEC Rejected","",IF(AJ11="","",ROUND(1.18*AJ11,2)))) | AL11: =IF(AI11="","",IF(AJ11="TEC Rejected","",IF(AJ11="","",ROUND(AI11*AK11,2)))) | AM11: =IF(AN11="","",IF('CST-Calculation'!$F11="Indg","",IF('CST-Calculation'!$F11="TEC Del","",IF('CST-Calculation'!AM11>0,'CST-Calculation'!AM11,IF('CST-Calculation'!$F11=0,"",'CST-Calculation'!$F11))))) | AN11: =IF('CST-Calculation'!AN11=0,"",'CST-Calculation'!AN11) | AO11: =IF(AM11="","",IF(AN11="TEC Rejected","",IF(AN11="","",ROUND(1.3224*Form!$D$10*AN11,2)))) | AP11: =IF(AM11="","",IF(AN11="TEC Rejected","",IF(AN11="","",ROUND(AM11*AO11,2)))) | AQ11: =IF(AR11="","",IF('CST-Calculation'!$F11="Indg","",IF('CST-Calculation'!$F11="TEC Del","",IF('CST-Calculation'!AQ11>0,'CST-Calculation'!AQ11,IF('CST-Calculation'!$F11=0,"",'CST-Calculation'!$F11))))) | AR11: =IF('CST-Calculation'!AR11=0,"",'CST-Calculation'!AR11) | AS11: =IF(AQ11="","",IF(AR11="TEC Rejected","",IF(AR11="","",ROUND(1.3224*Form!$D$10*AR11,2)))) | AT11: =IF(AQ11="","",IF(AR11="TEC Rejected","",IF(AR11="","",ROUND(AQ11*AS11,2)))) | AU11: =IF(AV11="","",IF('CST-Calculation'!$F11="Indg","",IF('CST-Calculation'!$F11="TEC Del","",IF('CST-Calculation'!AU11>0,'CST-Calculation'!AU11,IF('CST-Calculation'!$F11=0,"",'CST-Calculation'!$F11))))) | AV11: =IF('CST-Calculation'!AV11=0,"",'CST-Calculation'!AV11) | AW11: =IF(AU11="","",IF(AV11="TEC Rejected","",IF(AV11="","",ROUND(1.3224*Form!$D$10*AV11,2)))) | AX11: =IF(AU11="","",IF(AV11="TEC Rejected","",IF(AV11="","",ROUND(AU11*AW11,2)))) | AY11: =IF(F11="Indg","INDG",IF(F11="TEC Del","DELETED",IF(F11=0,"DELETED",IF(BD11=0,"NO OFFER",IF(BD11=I11,$H$3,IF(BD11=M11,$L$3,IF(BD11=Q11,$P$3,IF(BD11=U11,$T$3,IF(BD11=Y11,$X$3,IF(BD11=AC11,$AB$3,IF(BD11=AG11,$AF$3,IF(BD11=AK11,$AJ$3,IF(BD11=AO11,$AN$3,IF(BD11=AS11,$AR$3,IF(BD11=AW11,$AV$3))))))))))))))) -> ADRYS | AZ11: =IF(F11=0,"DELETED",IF(COUNT(H11,L11,P11,T11,X11,AB11,AF11,AJ11,AN11,AR11,AV11)=0,"NO OFFER",IF(COUNT(H11,L11,P11,T11,X11,AB11,AF11,AJ11,AN11,AR11,AV11)=1,"SINGLE","MULTIPLE"))) -> MULTIPLE | BA11: =IF(AND(IF(G11="",TRUE,G11<=ROUNDUP(1.2*F11,0)),IF(K11="",TRUE,K11<=ROUNDUP(1.2*F11,0)),IF(O11="",TRUE,O11<=ROUNDUP(1.2*F11,0)),IF(S11="",TRUE,S11<=ROUNDUP(1.2*F11,0)),IF(W11="",TRUE,W11<=ROUNDUP(1.2*F11,0)),IF(AA11="",TRUE,AA11<=ROUNDUP(1.2*F11,0)),IF(AE11="",TRUE,AE11<=ROUNDUP(1.2*F11,0)),IF(AI11="",TRUE,AI11<=ROUNDUP(1.2*F11,0)),IF(AM11="",TRUE,AM11<=ROUNDUP(1.2*F11,0)),IF(AQ11="",TRUE,AQ11<=ROUNDUP(1.2*F11,0)),IF(AU11="",TRUE,AU11<=ROUNDUP(1.2*F11,0))),"<= 20%","> 20%") -> <= 20% | BB11: =IF(AY11="EST",ROUND(BD11/1.18,2),IF(AY11="ADRYS",ROUND(BD11/1.18,2),ROUND(BD11/(1.3224*Form!$D$10),2))) -> 315 | BC11: =IF(OR(AY11="EST",AY11="ADRYS"),ROUND(BE11/1.18,2),ROUND(BE11/(1.3224*Form!$D$10),2)) -> 1890 | BD11: =IF(F11="Indg",0,IF(F11="TEC Del",0,IF(AND(IF(G11="",TRUE,G11<=ROUNDUP(1.2*F11,0)),IF(K11="",TRUE,K11<=ROUNDUP(1.2*F11,0)),IF(O11="",TRUE,O11<=ROUNDUP(1.2*F11,0)),IF(S11="",TRUE,S11<=ROUNDUP(1.2*F11,0)),IF(W11="",TRUE,W11<=ROUNDUP(1.2*F11,0)),IF(AA11="",TRUE,AA11<=ROUNDUP(1.2*F11,0)),IF(AE11="",TRUE,AE11<=ROUNDUP(1.2*F11,0)),IF(AI11="",TRUE,AI11<=ROUNDUP(1.2*F11,0)),IF(AM11="",TRUE,AM11<=ROUNDUP(1.2*F11,0)),IF(AQ11="",TRUE,AQ11<=ROUNDUP(1.2*F11,0)),IF(AU11="",TRUE,AU11<=ROUNDUP(1.2*F11,0))),IF(F11=0,0,(IF(SUM(I11,M11,Q11,U11,Y11,AC11,AG11,AK11,AO11,AS11,AW11)=0,0,SMALL((I11,M11,Q11,U11,Y11,AC11,AG11,AK11,AO11,AS11,AW11),COUNTIF((I11:AW11),0)+1)))),IF(BE11=J11,I11,IF(BE11=N11,M11,IF(BE11=R11,Q11,IF(BE11=V11,U11,IF(BE11=Z11,Y11,IF(BE11=AD11,AC11,IF(BE11=AH11,AG11,IF(BE11=AL11,AK11,IF(BE11=AP11,AO11,IF(BE11=AT11,AS11,IF(BE11=AX11,AW11)))))))))))))) -> 371.7 | BE11: =IF(F11="Indg",0,IF(F11="TEC Del",0,IF(AND(IF(G11="",TRUE,G11<=ROUNDUP(1.2*F11,0)),IF(K11="",TRUE,K11<=ROUNDUP(1.2*F11,0)),IF(O11="",TRUE,O11<=ROUNDUP(1.2*F11,0)),IF(S11="",TRUE,S11<=ROUNDUP(1.2*F11,0)),IF(W11="",TRUE,W11<=ROUNDUP(1.2*F11,0)),IF(AA11="",TRUE,AA11<=ROUNDUP(1.2*F11,0)),IF(AE11="",TRUE,AE11<=ROUNDUP(1.2*F11,0)),IF(AI11="",TRUE,AI11<=ROUNDUP(1.2*F11,0)),IF(AM11="",TRUE,AM11<=ROUNDUP(1.2*F11,0)),IF(AQ11="",TRUE,AQ11<=ROUNDUP(1.2*F11,0)),IF(AU11="",TRUE,AU11<=ROUNDUP(1.2*F11,0))),ROUND(BD11*IF(BD11=I11,G11,IF(BD11=M11,K11,IF(BD11=Q11,O11,IF(BD11=U11,S11,IF(BD11=Y11,W11,IF(BD11=AC11,AA11,IF(BD11=AG11,AE11,IF(BD11=AK11,AI11,IF(BD11=AO11,AM11,IF(BD11=AS11,AQ11,IF(BD11=AW11,AU11))))))))))),2),(IF(SUM(J11,N11,R11,V11,Z11,AD11,AH11,AL11,AP11,AT11,AX11)=0,0,SMALL((J11,N11,R11,V11,Z11,AD11,AH11,AL11,AP11,AT11,AX11),COUNTIF((J11:AX11),0)+1)))))) -> 2230.2 | BF11: =IF('Annexure-I'!L8="",'Annexure-I'!F8,'Annexure-I'!L8) -> 280 | BG11: =IF('Annexure-I'!M8="",'Annexure-I'!G8,'Annexure-I'!M8) -> CONTRACT-A7 | BH11: =IF('Annexure-I'!N8="",'Annexure-I'!H8,'Annexure-I'!N8) -> 44760 | BI11: =IF('Annexure-I'!P8="",'Annexure-I'!J8,'Annexure-I'!P8) -> 309.29 | BJ11: =IF('Annexure-I'!Q8="",'Annexure-I'!K8,'Annexure-I'!Q8) -> 364.9622 | BK11: ='Annexure-I'!F8 -> 280 | BL11: ='Annexure-I'!G8 -> CONTRACT-A7 | BM11: =IF('Annexure-I'!H8=0,"",'Annexure-I'!H8) -> 44760 | BN11: ='Annexure-I'!J8 -> 309.29 | BO11: ='Annexure-I'!K8 -> 364.9622 | BP11: =IF(OR(AY11="EST",AY11="ADRYS"),ROUND((BC11*1.18)/(1.3224*Form!$D$10),2),BC11) -> 20.37 | BQ11: =ROUND(BS11/(1.3224*Form!$D$10),2) -> 20 | BR11: =IF(AY11="DELETED",0,BE11) -> 2230.2 | BS11: =IF(BR11=0,0,ROUND(IF($BQ$1="LPP",ROUND(BJ11*F11,2),ROUND(BO11*F11,2)),2)) -> 2189.77 | BT11: =IF(SUM(BR11:BS11)=0,0,(BR11-BS11)/BS11) -> 0.018463126 | BV11: =IF(F11="Indg",0,IF(F11="TEC Del",0,IF(CA11="Deleted",0,ROUND(F11*BU11,2)))) -> 0 | BW11: =IF(OR(AY11="EST",AY11="ADRYS"),ROUND(1.18*BU11,2),ROUND(BU11*1.3224*Form!$D$10,2)) -> 0 | BX11: =IF(F11="Indg",0,IF(F11="TEC Del",0,IF(CA11="Deleted",0,ROUND(BW11*F11,2)))) -> 0 | BY11: =IF((BX11)=0,0,(BX11-BS11)/BS11) -> 0 | BZ11: =IF(CA11="Deleted",0,ROUND(BO11*F11,2)) -> 2189.77
A12: =SUBTOTAL(2,$B$5:B12) -> 8 | B12: 8 | C12: X8 | D12: TRANSISTOR | E12: 16 | F12: ='Annexure-I'!E9 -> 16 | G12: =IF('CST-Calculation'!G12=0,"",'CST-Calculation'!G12) | H12: =IF('CST-Calculation'!H12=0,"",'CST-Calculation'!H12) | I12: =IF(G12="","",IF(H12="TEC Rejected","",IF(H12="","",ROUND(1.3224*Form!$D$10*H12,2)))) | J12: =IF(G12="","",IF(H12="TEC Rejected","",IF(H12="","",ROUND(G12*I12,2)))) | K12: =IF(L12="","",IF('CST-Calculation'!$F12="Indg","",IF('CST-Calculation'!$F12="TEC Del","",IF('CST-Calculation'!K12>0,'CST-Calculation'!K12,IF('CST-Calculation'!$F12=0,"",'CST-Calculation'!$F12))))) | L12: =IF('CST-Calculation'!L12=0,"",'CST-Calculation'!L12) | M12: =IF(K12="","",IF(L12="TEC Rejected","",IF(L12="","",ROUND(1.3224*Form!$D$10*L12,2)))) | N12: =IF(K12="","",IF(L12="TEC Rejected","",IF(L12="","",ROUND(K12*M12,2)))) | O12: =IF(P12="","",IF('CST-Calculation'!$F12="Indg","",IF('CST-Calculation'!$F12="TEC Del","",IF('CST-Calculation'!O12>0,'CST-Calculation'!O12,IF('CST-Calculation'!$F12=0,"",'CST-Calculation'!$F12))))) -> 16 | P12: =IF('CST-Calculation'!P12=0,"",'CST-Calculation'!P12) -> 18 | Q12: =IF(O12="","",IF(P12="TEC Rejected","",IF(P12="","",ROUND(1.3224*Form!$D$10*P12,2)))) -> 1970.43 | R12: =IF(O12="","",IF(P12="TEC Rejected","",IF(P12="","",ROUND(O12*Q12,2)))) -> 31526.88 | S12: =IF(T12="","",IF('CST-Calculation'!$F12="Indg","",IF('CST-Calculation'!$F12="TEC Del","",IF('CST-Calculation'!S12>0,'CST-Calculation'!S12,IF('CST-Calculation'!$F12=0,"",'CST-Calculation'!$F12))))) -> 16 | T12: =IF('CST-Calculation'!T12=0,"",'CST-Calculation'!T12) -> 39.6 | U12: =IF(S12="","",IF(T12="TEC Rejected","",IF(T12="","",ROUND(1.3224*Form!$D$10*T12,2)))) -> 4334.94 | V12: =IF(S12="","",IF(T12="TEC Rejected","",IF(T12="","",ROUND(S12*U12,2)))) -> 69359.04 | W12: =IF(X12="","",IF('CST-Calculation'!$F12="Indg","",IF('CST-Calculation'!$F12="TEC Del","",IF('CST-Calculation'!W12>0,'CST-Calculation'!W12,IF('CST-Calculation'!$F12=0,"",'CST-Calculation'!$F12))))) | X12: =IF('CST-Calculation'!X12=0,"",'CST-Calculation'!X12) | Y12: =IF(W12="","",IF(X12="TEC Rejected","",IF(X12="","",ROUND(1.3224*Form!$D$10*X12,2)))) | Z12: =IF(W12="","",IF(X12="TEC Rejected","",IF(X12="","",ROUND(W12*Y12,2)))) | AA12: =IF(AB12="","",IF('CST-Calculation'!$F12="Indg","",IF('CST-Calculation'!$F12="TEC Del","",IF('CST-Calculation'!AA12>0,'CST-Calculation'!AA12,IF('CST-Calculation'!$F12=0,"",'CST-Calculation'!$F12))))) -> 16 | AB12: =IF('CST-Calculation'!AB12=0,"",'CST-Calculation'!AB12) -> 2865 | AC12: =IF(AA12="","",IF(AB12="TEC Rejected","",IF(AB12="","",ROUND(1.18*AB12,2)))) -> 3380.7 | AD12: =IF(AA12="","",IF(AB12="TEC Rejected","",IF(AB12="","",ROUND(AA12*AC12,2)))) -> 54091.2 | AE12: =IF(AF12="","",IF('CST-Calculation'!$F12="Indg","",IF('CST-Calculation'!$F12="TEC Del","",IF('CST-Calculation'!AE12>0,'CST-Calculation'!AE12,IF('CST-Calculation'!$F12=0,"",'CST-Calculation'!$F12))))) | AF12: =IF('CST-Calculation'!AF12=0,"",'CST-Calculation'!AF12) | AG12: =IF(AE12="","",IF(AF12="TEC Rejected","",IF(AF12="","",ROUND(1.3224*Form!$D$10*AF12,2)))) | AH12: =IF(AE12="","",IF(AF12="TEC Rejected","",IF(AF12="","",ROUND(AE12*AG12,2)))) | AI12: =IF(AJ12="","",IF('CST-Calculation'!$F12="Indg","",IF('CST-Calculation'!$F12="TEC Del","",IF('CST-Calculation'!AI12>0,'CST-Calculation'!AI12,IF('CST-Calculation'!$F12=0,"",'CST-Calculation'!$F12))))) | AJ12: =IF('CST-Calculation'!AJ12=0,"",'CST-Calculation'!AJ12) | AK12: =IF(AI12="","",IF(AJ12="TEC Rejected","",IF(AJ12="","",ROUND(1.18*AJ12,2)))) | AL12: =IF(AI12="","",IF(AJ12="TEC Rejected","",IF(AJ12="","",ROUND(AI12*AK12,2)))) | AM12: =IF(AN12="","",IF('CST-Calculation'!$F12="Indg","",IF('CST-Calculation'!$F12="TEC Del","",IF('CST-Calculation'!AM12>0,'CST-Calculation'!AM12,IF('CST-Calculation'!$F12=0,"",'CST-Calculation'!$F12))))) | AN12: =IF('CST-Calculation'!AN12=0,"",'CST-Calculation'!AN12) | AO12: =IF(AM12="","",IF(AN12="TEC Rejected","",IF(AN12="","",ROUND(1.3224*Form!$D$10*AN12,2)))) | AP12: =IF(AM12="","",IF(AN12="TEC Rejected","",IF(AN12="","",ROUND(AM12*AO12,2)))) | AQ12: =IF(AR12="","",IF('CST-Calculation'!$F12="Indg","",IF('CST-Calculation'!$F12="TEC Del","",IF('CST-Calculation'!AQ12>0,'CST-Calculation'!AQ12,IF('CST-Calculation'!$F12=0,"",'CST-Calculation'!$F12))))) | AR12: =IF('CST-Calculation'!AR12=0,"",'CST-Calculation'!AR12) | AS12: =IF(AQ12="","",IF(AR12="TEC Rejected","",IF(AR12="","",ROUND(1.3224*Form!$D$10*AR12,2)))) | AT12: =IF(AQ12="","",IF(AR12="TEC Rejected","",IF(AR12="","",ROUND(AQ12*AS12,2)))) | AU12: =IF(AV12="","",IF('CST-Calculation'!$F12="Indg","",IF('CST-Calculation'!$F12="TEC Del","",IF('CST-Calculation'!AU12>0,'CST-Calculation'!AU12,IF('CST-Calculation'!$F12=0,"",'CST-Calculation'!$F12))))) | AV12: =IF('CST-Calculation'!AV12=0,"",'CST-Calculation'!AV12) | AW12: =IF(AU12="","",IF(AV12="TEC Rejected","",IF(AV12="","",ROUND(1.3224*Form!$D$10*AV12,2)))) | AX12: =IF(AU12="","",IF(AV12="TEC Rejected","",IF(AV12="","",ROUND(AU12*AW12,2)))) | AY12: =IF(F12="Indg","INDG",IF(F12="TEC Del","DELETED",IF(F12=0,"DELETED",IF(BD12=0,"NO OFFER",IF(BD12=I12,$H$3,IF(BD12=M12,$L$3,IF(BD12=Q12,$P$3,IF(BD12=U12,$T$3,IF(BD12=Y12,$X$3,IF(BD12=AC12,$AB$3,IF(BD12=AG12,$AF$3,IF(BD12=AK12,$AJ$3,IF(BD12=AO12,$AN$3,IF(BD12=AS12,$AR$3,IF(BD12=AW12,$AV$3))))))))))))))) -> GIS | AZ12: =IF(F12=0,"DELETED",IF(COUNT(H12,L12,P12,T12,X12,AB12,AF12,AJ12,AN12,AR12,AV12)=0,"NO OFFER",IF(COUNT(H12,L12,P12,T12,X12,AB12,AF12,AJ12,AN12,AR12,AV12)=1,"SINGLE","MULTIPLE"))) -> MULTIPLE | BA12: =IF(AND(IF(G12="",TRUE,G12<=ROUNDUP(1.2*F12,0)),IF(K12="",TRUE,K12<=ROUNDUP(1.2*F12,0)),IF(O12="",TRUE,O12<=ROUNDUP(1.2*F12,0)),IF(S12="",TRUE,S12<=ROUNDUP(1.2*F12,0)),IF(W12="",TRUE,W12<=ROUNDUP(1.2*F12,0)),IF(AA12="",TRUE,AA12<=ROUNDUP(1.2*F12,0)),IF(AE12="",TRUE,AE12<=ROUNDUP(1.2*F12,0)),IF(AI12="",TRUE,AI12<=ROUNDUP(1.2*F12,0)),IF(AM12="",TRUE,AM12<=ROUNDUP(1.2*F12,0)),IF(AQ12="",TRUE,AQ12<=ROUNDUP(1.2*F12,0)),IF(AU12="",TRUE,AU12<=ROUNDUP(1.2*F12,0))),"<= 20%","> 20%") -> <= 20% | BB12: =IF(AY12="EST",ROUND(BD12/1.18,2),IF(AY12="ADRYS",ROUND(BD12/1.18,2),ROUND(BD12/(1.3224*Form!$D$10),2))) -> 18 | BC12: =IF(OR(AY12="EST",AY12="ADRYS"),ROUND(BE12/1.18,2),ROUND(BE12/(1.3224*Form!$D$10),2)) -> 288 | BD12: =IF(F12="Indg",0,IF(F12="TEC Del",0,IF(AND(IF(G12="",TRUE,G12<=ROUNDUP(1.2*F12,0)),IF(K12="",TRUE,K12<=ROUNDUP(1.2*F12,0)),IF(O12="",TRUE,O12<=ROUNDUP(1.2*F12,0)),IF(S12="",TRUE,S12<=ROUNDUP(1.2*F12,0)),IF(W12="",TRUE,W12<=ROUNDUP(1.2*F12,0)),IF(AA12="",TRUE,AA12<=ROUNDUP(1.2*F12,0)),IF(AE12="",TRUE,AE12<=ROUNDUP(1.2*F12,0)),IF(AI12="",TRUE,AI12<=ROUNDUP(1.2*F12,0)),IF(AM12="",TRUE,AM12<=ROUNDUP(1.2*F12,0)),IF(AQ12="",TRUE,AQ12<=ROUNDUP(1.2*F12,0)),IF(AU12="",TRUE,AU12<=ROUNDUP(1.2*F12,0))),IF(F12=0,0,(IF(SUM(I12,M12,Q12,U12,Y12,AC12,AG12,AK12,AO12,AS12,AW12)=0,0,SMALL((I12,M12,Q12,U12,Y12,AC12,AG12,AK12,AO12,AS12,AW12),COUNTIF((I12:AW12),0)+1)))),IF(BE12=J12,I12,IF(BE12=N12,M12,IF(BE12=R12,Q12,IF(BE12=V12,U12,IF(BE12=Z12,Y12,IF(BE12=AD12,AC12,IF(BE12=AH12,AG12,IF(BE12=AL12,AK12,IF(BE12=AP12,AO12,IF(BE12=AT12,AS12,IF(BE12=AX12,AW12)))))))))))))) -> 1970.43 | BE12: =IF(F12="Indg",0,IF(F12="TEC Del",0,IF(AND(IF(G12="",TRUE,G12<=ROUNDUP(1.2*F12,0)),IF(K12="",TRUE,K12<=ROUNDUP(1.2*F12,0)),IF(O12="",TRUE,O12<=ROUNDUP(1.2*F12,0)),IF(S12="",TRUE,S12<=ROUNDUP(1.2*F12,0)),IF(W12="",TRUE,W12<=ROUNDUP(1.2*F12,0)),IF(AA12="",TRUE,AA12<=ROUNDUP(1.2*F12,0)),IF(AE12="",TRUE,AE12<=ROUNDUP(1.2*F12,0)),IF(AI12="",TRUE,AI12<=ROUNDUP(1.2*F12,0)),IF(AM12="",TRUE,AM12<=ROUNDUP(1.2*F12,0)),IF(AQ12="",TRUE,AQ12<=ROUNDUP(1.2*F12,0)),IF(AU12="",TRUE,AU12<=ROUNDUP(1.2*F12,0))),ROUND(BD12*IF(BD12=I12,G12,IF(BD12=M12,K12,IF(BD12=Q12,O12,IF(BD12=U12,S12,IF(BD12=Y12,W12,IF(BD12=AC12,AA12,IF(BD12=AG12,AE12,IF(BD12=AK12,AI12,IF(BD12=AO12,AM12,IF(BD12=AS12,AQ12,IF(BD12=AW12,AU12))))))))))),2),(IF(SUM(J12,N12,R12,V12,Z12,AD12,AH12,AL12,AP12,AT12,AX12)=0,0,SMALL((J12,N12,R12,V12,Z12,AD12,AH12,AL12,AP12,AT12,AX12),COUNTIF((J12:AX12),0)+1)))))) -> 31526.88 | BF12: =IF('Annexure-I'!L9="",'Annexure-I'!F9,'Annexure-I'!L9) -> 57.75 | BG12: =IF('Annexure-I'!M9="",'Annexure-I'!G9,'Annexure-I'!M9) -> CONTRACT-A8 | BH12: =IF('Annexure-I'!N9="",'Annexure-I'!H9,'Annexure-I'!N9) -> 40724 | BI12: =IF('Annexure-I'!P9="",'Annexure-I'!J9,'Annexure-I'!P9) -> 111.94 | BJ12: =IF('Annexure-I'!Q9="",'Annexure-I'!K9,'Annexure-I'!Q9) -> 12253.878 | BK12: ='Annexure-I'!F9 -> 57.75 | BL12: ='Annexure-I'!G9 -> CONTRACT-A8 | BM12: =IF('Annexure-I'!H9=0,"",'Annexure-I'!H9) -> 40724 | BN12: ='Annexure-I'!J9 -> 111.94 | BO12: ='Annexure-I'!K9 -> 12253.878 | BP12: =IF(OR(AY12="EST",AY12="ADRYS"),ROUND((BC12*1.18)/(1.3224*Form!$D$10),2),BC12) -> 288 | BQ12: =ROUND(BS12/(1.3224*Form!$D$10),2) -> 1791.04 | BR12: =IF(AY12="DELETED",0,BE12) -> 31526.88 | BS12: =IF(BR12=0,0,ROUND(IF($BQ$1="LPP",ROUND(BJ12*F12,2),ROUND(BO12*F12,2)),2)) -> 196062.05 | BT12: =IF(SUM(BR12:BS12)=0,0,(BR12-BS12)/BS12) -> -0.83919948 | BV12: =IF(F12="Indg",0,IF(F12="TEC Del",0,IF(CA12="Deleted",0,ROUND(F12*BU12,2)))) -> 0 | BW12: =IF(OR(AY12="EST",AY12="ADRYS"),ROUND(1.18*BU12,2),ROUND(BU12*1.3224*Form!$D$10,2)) -> 0 | BX12: =IF(F12="Indg",0,IF(F12="TEC Del",0,IF(CA12="Deleted",0,ROUND(BW12*F12,2)))) -> 0 | BY12: =IF((BX12)=0,0,(BX12-BS12)/BS12) -> 0 | BZ12: =IF(CA12="Deleted",0,ROUND(BO12*F12,2)) -> 196062.05
A13: =SUBTOTAL(2,$B$5:B13) -> 9 | B13: 9 | C13: X9 | D13: TRANSISTOR | E13: 17 | F13: ='Annexure-I'!E10 -> 17 | G13: =IF('CST-Calculation'!G13=0,"",'CST-Calculation'!G13) | H13: =IF('CST-Calculation'!H13=0,"",'CST-Calculation'!H13) | I13: =IF(G13="","",IF(H13="TEC Rejected","",IF(H13="","",ROUND(1.3224*Form!$D$10*H13,2)))) | J13: =IF(G13="","",IF(H13="TEC Rejected","",IF(H13="","",ROUND(G13*I13,2)))) | K13: =IF(L13="","",IF('CST-Calculation'!$F13="Indg","",IF('CST-Calculation'!$F13="TEC Del","",IF('CST-Calculation'!K13>0,'CST-Calculation'!K13,IF('CST-Calculation'!$F13=0,"",'CST-Calculation'!$F13))))) | L13: =IF('CST-Calculation'!L13=0,"",'CST-Calculation'!L13) | M13: =IF(K13="","",IF(L13="TEC Rejected","",IF(L13="","",ROUND(1.3224*Form!$D$10*L13,2)))) | N13: =IF(K13="","",IF(L13="TEC Rejected","",IF(L13="","",ROUND(K13*M13,2)))) | O13: =IF(P13="","",IF('CST-Calculation'!$F13="Indg","",IF('CST-Calculation'!$F13="TEC Del","",IF('CST-Calculation'!O13>0,'CST-Calculation'!O13,IF('CST-Calculation'!$F13=0,"",'CST-Calculation'!$F13))))) -> 17 | P13: =IF('CST-Calculation'!P13=0,"",'CST-Calculation'!P13) -> 6.6 | Q13: =IF(O13="","",IF(P13="TEC Rejected","",IF(P13="","",ROUND(1.3224*Form!$D$10*P13,2)))) -> 722.49 | R13: =IF(O13="","",IF(P13="TEC Rejected","",IF(P13="","",ROUND(O13*Q13,2)))) -> 12282.33 | S13: =IF(T13="","",IF('CST-Calculation'!$F13="Indg","",IF('CST-Calculation'!$F13="TEC Del","",IF('CST-Calculation'!S13>0,'CST-Calculation'!S13,IF('CST-Calculation'!$F13=0,"",'CST-Calculation'!$F13))))) | T13: =IF('CST-Calculation'!T13=0,"",'CST-Calculation'!T13) | U13: =IF(S13="","",IF(T13="TEC Rejected","",IF(T13="","",ROUND(1.3224*Form!$D$10*T13,2)))) | V13: =IF(S13="","",IF(T13="TEC Rejected","",IF(T13="","",ROUND(S13*U13,2)))) | W13: =IF(X13="","",IF('CST-Calculation'!$F13="Indg","",IF('CST-Calculation'!$F13="TEC Del","",IF('CST-Calculation'!W13>0,'CST-Calculation'!W13,IF('CST-Calculation'!$F13=0,"",'CST-Calculation'!$F13))))) | X13: =IF('CST-Calculation'!X13=0,"",'CST-Calculation'!X13) | Y13: =IF(W13="","",IF(X13="TEC Rejected","",IF(X13="","",ROUND(1.3224*Form!$D$10*X13,2)))) | Z13: =IF(W13="","",IF(X13="TEC Rejected","",IF(X13="","",ROUND(W13*Y13,2)))) | AA13: =IF(AB13="","",IF('CST-Calculation'!$F13="Indg","",IF('CST-Calculation'!$F13="TEC Del","",IF('CST-Calculation'!AA13>0,'CST-Calculation'!AA13,IF('CST-Calculation'!$F13=0,"",'CST-Calculation'!$F13))))) -> 17 | AB13: =IF('CST-Calculation'!AB13=0,"",'CST-Calculation'!AB13) -> 465 | AC13: =IF(AA13="","",IF(AB13="TEC Rejected","",IF(AB13="","",ROUND(1.18*AB13,2)))) -> 548.7 | AD13: =IF(AA13="","",IF(AB13="TEC Rejected","",IF(AB13="","",ROUND(AA13*AC13,2)))) -> 9327.9 | AE13: =IF(AF13="","",IF('CST-Calculation'!$F13="Indg","",IF('CST-Calculation'!$F13="TEC Del","",IF('CST-Calculation'!AE13>0,'CST-Calculation'!AE13,IF('CST-Calculation'!$F13=0,"",'CST-Calculation'!$F13))))) | AF13: =IF('CST-Calculation'!AF13=0,"",'CST-Calculation'!AF13) | AG13: =IF(AE13="","",IF(AF13="TEC Rejected","",IF(AF13="","",ROUND(1.3224*Form!$D$10*AF13,2)))) | AH13: =IF(AE13="","",IF(AF13="TEC Rejected","",IF(AF13="","",ROUND(AE13*AG13,2)))) | AI13: =IF(AJ13="","",IF('CST-Calculation'!$F13="Indg","",IF('CST-Calculation'!$F13="TEC Del","",IF('CST-Calculation'!AI13>0,'CST-Calculation'!AI13,IF('CST-Calculation'!$F13=0,"",'CST-Calculation'!$F13))))) | AJ13: =IF('CST-Calculation'!AJ13=0,"",'CST-Calculation'!AJ13) | AK13: =IF(AI13="","",IF(AJ13="TEC Rejected","",IF(AJ13="","",ROUND(1.18*AJ13,2)))) | AL13: =IF(AI13="","",IF(AJ13="TEC Rejected","",IF(AJ13="","",ROUND(AI13*AK13,2)))) | AM13: =IF(AN13="","",IF('CST-Calculation'!$F13="Indg","",IF('CST-Calculation'!$F13="TEC Del","",IF('CST-Calculation'!AM13>0,'CST-Calculation'!AM13,IF('CST-Calculation'!$F13=0,"",'CST-Calculation'!$F13))))) | AN13: =IF('CST-Calculation'!AN13=0,"",'CST-Calculation'!AN13) | AO13: =IF(AM13="","",IF(AN13="TEC Rejected","",IF(AN13="","",ROUND(1.3224*Form!$D$10*AN13,2)))) | AP13: =IF(AM13="","",IF(AN13="TEC Rejected","",IF(AN13="","",ROUND(AM13*AO13,2)))) | AQ13: =IF(AR13="","",IF('CST-Calculation'!$F13="Indg","",IF('CST-Calculation'!$F13="TEC Del","",IF('CST-Calculation'!AQ13>0,'CST-Calculation'!AQ13,IF('CST-Calculation'!$F13=0,"",'CST-Calculation'!$F13))))) | AR13: =IF('CST-Calculation'!AR13=0,"",'CST-Calculation'!AR13) | AS13: =IF(AQ13="","",IF(AR13="TEC Rejected","",IF(AR13="","",ROUND(1.3224*Form!$D$10*AR13,2)))) | AT13: =IF(AQ13="","",IF(AR13="TEC Rejected","",IF(AR13="","",ROUND(AQ13*AS13,2)))) | AU13: =IF(AV13="","",IF('CST-Calculation'!$F13="Indg","",IF('CST-Calculation'!$F13="TEC Del","",IF('CST-Calculation'!AU13>0,'CST-Calculation'!AU13,IF('CST-Calculation'!$F13=0,"",'CST-Calculation'!$F13))))) | AV13: =IF('CST-Calculation'!AV13=0,"",'CST-Calculation'!AV13) | AW13: =IF(AU13="","",IF(AV13="TEC Rejected","",IF(AV13="","",ROUND(1.3224*Form!$D$10*AV13,2)))) | AX13: =IF(AU13="","",IF(AV13="TEC Rejected","",IF(AV13="","",ROUND(AU13*AW13,2)))) | AY13: =IF(F13="Indg","INDG",IF(F13="TEC Del","DELETED",IF(F13=0,"DELETED",IF(BD13=0,"NO OFFER",IF(BD13=I13,$H$3,IF(BD13=M13,$L$3,IF(BD13=Q13,$P$3,IF(BD13=U13,$T$3,IF(BD13=Y13,$X$3,IF(BD13=AC13,$AB$3,IF(BD13=AG13,$AF$3,IF(BD13=AK13,$AJ$3,IF(BD13=AO13,$AN$3,IF(BD13=AS13,$AR$3,IF(BD13=AW13,$AV$3))))))))))))))) -> ADRYS | AZ13: =IF(F13=0,"DELETED",IF(COUNT(H13,L13,P13,T13,X13,AB13,AF13,AJ13,AN13,AR13,AV13)=0,"NO OFFER",IF(COUNT(H13,L13,P13,T13,X13,AB13,AF13,AJ13,AN13,AR13,AV13)=1,"SINGLE","MULTIPLE"))) -> MULTIPLE | BA13: =IF(AND(IF(G13="",TRUE,G13<=ROUNDUP(1.2*F13,0)),IF(K13="",TRUE,K13<=ROUNDUP(1.2*F13,0)),IF(O13="",TRUE,O13<=ROUNDUP(1.2*F13,0)),IF(S13="",TRUE,S13<=ROUNDUP(1.2*F13,0)),IF(W13="",TRUE,W13<=ROUNDUP(1.2*F13,0)),IF(AA13="",TRUE,AA13<=ROUNDUP(1.2*F13,0)),IF(AE13="",TRUE,AE13<=ROUNDUP(1.2*F13,0)),IF(AI13="",TRUE,AI13<=ROUNDUP(1.2*F13,0)),IF(AM13="",TRUE,AM13<=ROUNDUP(1.2*F13,0)),IF(AQ13="",TRUE,AQ13<=ROUNDUP(1.2*F13,0)),IF(AU13="",TRUE,AU13<=ROUNDUP(1.2*F13,0))),"<= 20%","> 20%") -> <= 20% | BB13: =IF(AY13="EST",ROUND(BD13/1.18,2),IF(AY13="ADRYS",ROUND(BD13/1.18,2),ROUND(BD13/(1.3224*Form!$D$10),2))) -> 465 | BC13: =IF(OR(AY13="EST",AY13="ADRYS"),ROUND(BE13/1.18,2),ROUND(BE13/(1.3224*Form!$D$10),2)) -> 7905 | BD13: =IF(F13="Indg",0,IF(F13="TEC Del",0,IF(AND(IF(G13="",TRUE,G13<=ROUNDUP(1.2*F13,0)),IF(K13="",TRUE,K13<=ROUNDUP(1.2*F13,0)),IF(O13="",TRUE,O13<=ROUNDUP(1.2*F13,0)),IF(S13="",TRUE,S13<=ROUNDUP(1.2*F13,0)),IF(W13="",TRUE,W13<=ROUNDUP(1.2*F13,0)),IF(AA13="",TRUE,AA13<=ROUNDUP(1.2*F13,0)),IF(AE13="",TRUE,AE13<=ROUNDUP(1.2*F13,0)),IF(AI13="",TRUE,AI13<=ROUNDUP(1.2*F13,0)),IF(AM13="",TRUE,AM13<=ROUNDUP(1.2*F13,0)),IF(AQ13="",TRUE,AQ13<=ROUNDUP(1.2*F13,0)),IF(AU13="",TRUE,AU13<=ROUNDUP(1.2*F13,0))),IF(F13=0,0,(IF(SUM(I13,M13,Q13,U13,Y13,AC13,AG13,AK13,AO13,AS13,AW13)=0,0,SMALL((I13,M13,Q13,U13,Y13,AC13,AG13,AK13,AO13,AS13,AW13),COUNTIF((I13:AW13),0)+1)))),IF(BE13=J13,I13,IF(BE13=N13,M13,IF(BE13=R13,Q13,IF(BE13=V13,U13,IF(BE13=Z13,Y13,IF(BE13=AD13,AC13,IF(BE13=AH13,AG13,IF(BE13=AL13,AK13,IF(BE13=AP13,AO13,IF(BE13=AT13,AS13,IF(BE13=AX13,AW13)))))))))))))) -> 548.7 | BE13: =IF(F13="Indg",0,IF(F13="TEC Del",0,IF(AND(IF(G13="",TRUE,G13<=ROUNDUP(1.2*F13,0)),IF(K13="",TRUE,K13<=ROUNDUP(1.2*F13,0)),IF(O13="",TRUE,O13<=ROUNDUP(1.2*F13,0)),IF(S13="",TRUE,S13<=ROUNDUP(1.2*F13,0)),IF(W13="",TRUE,W13<=ROUNDUP(1.2*F13,0)),IF(AA13="",TRUE,AA13<=ROUNDUP(1.2*F13,0)),IF(AE13="",TRUE,AE13<=ROUNDUP(1.2*F13,0)),IF(AI13="",TRUE,AI13<=ROUNDUP(1.2*F13,0)),IF(AM13="",TRUE,AM13<=ROUNDUP(1.2*F13,0)),IF(AQ13="",TRUE,AQ13<=ROUNDUP(1.2*F13,0)),IF(AU13="",TRUE,AU13<=ROUNDUP(1.2*F13,0))),ROUND(BD13*IF(BD13=I13,G13,IF(BD13=M13,K13,IF(BD13=Q13,O13,IF(BD13=U13,S13,IF(BD13=Y13,W13,IF(BD13=AC13,AA13,IF(BD13=AG13,AE13,IF(BD13=AK13,AI13,IF(BD13=AO13,AM13,IF(BD13=AS13,AQ13,IF(BD13=AW13,AU13))))))))))),2),(IF(SUM(J13,N13,R13,V13,Z13,AD13,AH13,AL13,AP13,AT13,AX13)=0,0,SMALL((J13,N13,R13,V13,Z13,AD13,AH13,AL13,AP13,AT13,AX13),COUNTIF((J13:AX13),0)+1)))))) -> 9327.9 | BF13: =IF('Annexure-I'!L10="",'Annexure-I'!F10,'Annexure-I'!L10) -> 6 | BG13: =IF('Annexure-I'!M10="",'Annexure-I'!G10,'Annexure-I'!M10) -> CONTRACT-A9 | BH13: =IF('Annexure-I'!N10="",'Annexure-I'!H10,'Annexure-I'!N10) -> 43298 | BI13: =IF('Annexure-I'!P10="",'Annexure-I'!J10,'Annexure-I'!P10) -> 8.09 | BJ13: =IF('Annexure-I'!Q10="",'Annexure-I'!K10,'Annexure-I'!Q10) -> 885.59832 | BK13: ='Annexure-I'!F10 -> 6 | BL13: ='Annexure-I'!G10 -> CONTRACT-A9 | BM13: =IF('Annexure-I'!H10=0,"",'Annexure-I'!H10) -> 43298 | BN13: ='Annexure-I'!J10 -> 8.09 | BO13: ='Annexure-I'!K10 -> 885.59832 | BP13: =IF(OR(AY13="EST",AY13="ADRYS"),ROUND((BC13*1.18)/(1.3224*Form!$D$10),2),BC13) -> 85.21 | BQ13: =ROUND(BS13/(1.3224*Form!$D$10),2) -> 137.53 | BR13: =IF(AY13="DELETED",0,BE13) -> 9327.9 | BS13: =IF(BR13=0,0,ROUND(IF($BQ$1="LPP",ROUND(BJ13*F13,2),ROUND(BO13*F13,2)),2)) -> 15055.17 | BT13: =IF(SUM(BR13:BS13)=0,0,(BR13-BS13)/BS13) -> -0.38041882 | BV13: =IF(F13="Indg",0,IF(F13="TEC Del",0,IF(CA13="Deleted",0,ROUND(F13*BU13,2)))) -> 0 | BW13: =IF(OR(AY13="EST",AY13="ADRYS"),ROUND(1.18*BU13,2),ROUND(BU13*1.3224*Form!$D$10,2)) -> 0 | BX13: =IF(F13="Indg",0,IF(F13="TEC Del",0,IF(CA13="Deleted",0,ROUND(BW13*F13,2)))) -> 0 | BY13: =IF((BX13)=0,0,(BX13-BS13)/BS13) -> 0 | BZ13: =IF(CA13="Deleted",0,ROUND(BO13*F13,2)) -> 15055.17
A14: =SUBTOTAL(2,$B$5:B14) -> 10 | B14: 10 | C14: X10 | D14: IC (Integrated Circuit ) | E14: 30 | F14: ='Annexure-I'!E11 -> 30 | G14: =IF('CST-Calculation'!G14=0,"",'CST-Calculation'!G14) | H14: =IF('CST-Calculation'!H14=0,"",'CST-Calculation'!H14) | I14: =IF(G14="","",IF(H14="TEC Rejected","",IF(H14="","",ROUND(1.3224*Form!$D$10*H14,2)))) | J14: =IF(G14="","",IF(H14="TEC Rejected","",IF(H14="","",ROUND(G14*I14,2)))) | K14: =IF(L14="","",IF('CST-Calculation'!$F14="Indg","",IF('CST-Calculation'!$F14="TEC Del","",IF('CST-Calculation'!K14>0,'CST-Calculation'!K14,IF('CST-Calculation'!$F14=0,"",'CST-Calculation'!$F14))))) | L14: =IF('CST-Calculation'!L14=0,"",'CST-Calculation'!L14) | M14: =IF(K14="","",IF(L14="TEC Rejected","",IF(L14="","",ROUND(1.3224*Form!$D$10*L14,2)))) | N14: =IF(K14="","",IF(L14="TEC Rejected","",IF(L14="","",ROUND(K14*M14,2)))) | O14: =IF(P14="","",IF('CST-Calculation'!$F14="Indg","",IF('CST-Calculation'!$F14="TEC Del","",IF('CST-Calculation'!O14>0,'CST-Calculation'!O14,IF('CST-Calculation'!$F14=0,"",'CST-Calculation'!$F14))))) -> 30 | P14: =IF('CST-Calculation'!P14=0,"",'CST-Calculation'!P14) -> 7.5 | Q14: =IF(O14="","",IF(P14="TEC Rejected","",IF(P14="","",ROUND(1.3224*Form!$D$10*P14,2)))) -> 821.01 | R14: =IF(O14="","",IF(P14="TEC Rejected","",IF(P14="","",ROUND(O14*Q14,2)))) -> 24630.3 | S14: =IF(T14="","",IF('CST-Calculation'!$F14="Indg","",IF('CST-Calculation'!$F14="TEC Del","",IF('CST-Calculation'!S14>0,'CST-Calculation'!S14,IF('CST-Calculation'!$F14=0,"",'CST-Calculation'!$F14))))) -> 30 | T14: =IF('CST-Calculation'!T14=0,"",'CST-Calculation'!T14) -> 36 | U14: =IF(S14="","",IF(T14="TEC Rejected","",IF(T14="","",ROUND(1.3224*Form!$D$10*T14,2)))) -> 3940.86 | V14: =IF(S14="","",IF(T14="TEC Rejected","",IF(T14="","",ROUND(S14*U14,2)))) -> 118225.8 | W14: =IF(X14="","",IF('CST-Calculation'!$F14="Indg","",IF('CST-Calculation'!$F14="TEC Del","",IF('CST-Calculation'!W14>0,'CST-Calculation'!W14,IF('CST-Calculation'!$F14=0,"",'CST-Calculation'!$F14))))) | X14: =IF('CST-Calculation'!X14=0,"",'CST-Calculation'!X14) | Y14: =IF(W14="","",IF(X14="TEC Rejected","",IF(X14="","",ROUND(1.3224*Form!$D$10*X14,2)))) | Z14: =IF(W14="","",IF(X14="TEC Rejected","",IF(X14="","",ROUND(W14*Y14,2)))) | AA14: =IF(AB14="","",IF('CST-Calculation'!$F14="Indg","",IF('CST-Calculation'!$F14="TEC Del","",IF('CST-Calculation'!AA14>0,'CST-Calculation'!AA14,IF('CST-Calculation'!$F14=0,"",'CST-Calculation'!$F14))))) -> 30 | AB14: =IF('CST-Calculation'!AB14=0,"",'CST-Calculation'!AB14) -> 1065 | AC14: =IF(AA14="","",IF(AB14="TEC Rejected","",IF(AB14="","",ROUND(1.18*AB14,2)))) -> 1256.7 | AD14: =IF(AA14="","",IF(AB14="TEC Rejected","",IF(AB14="","",ROUND(AA14*AC14,2)))) -> 37701 | AE14: =IF(AF14="","",IF('CST-Calculation'!$F14="Indg","",IF('CST-Calculation'!$F14="TEC Del","",IF('CST-Calculation'!AE14>0,'CST-Calculation'!AE14,IF('CST-Calculation'!$F14=0,"",'CST-Calculation'!$F14))))) | AF14: =IF('CST-Calculation'!AF14=0,"",'CST-Calculation'!AF14) | AG14: =IF(AE14="","",IF(AF14="TEC Rejected","",IF(AF14="","",ROUND(1.3224*Form!$D$10*AF14,2)))) | AH14: =IF(AE14="","",IF(AF14="TEC Rejected","",IF(AF14="","",ROUND(AE14*AG14,2)))) | AI14: =IF(AJ14="","",IF('CST-Calculation'!$F14="Indg","",IF('CST-Calculation'!$F14="TEC Del","",IF('CST-Calculation'!AI14>0,'CST-Calculation'!AI14,IF('CST-Calculation'!$F14=0,"",'CST-Calculation'!$F14))))) | AJ14: =IF('CST-Calculation'!AJ14=0,"",'CST-Calculation'!AJ14) | AK14: =IF(AI14="","",IF(AJ14="TEC Rejected","",IF(AJ14="","",ROUND(1.18*AJ14,2)))) | AL14: =IF(AI14="","",IF(AJ14="TEC Rejected","",IF(AJ14="","",ROUND(AI14*AK14,2)))) | AM14: =IF(AN14="","",IF('CST-Calculation'!$F14="Indg","",IF('CST-Calculation'!$F14="TEC Del","",IF('CST-Calculation'!AM14>0,'CST-Calculation'!AM14,IF('CST-Calculation'!$F14=0,"",'CST-Calculation'!$F14))))) | AN14: =IF('CST-Calculation'!AN14=0,"",'CST-Calculation'!AN14) | AO14: =IF(AM14="","",IF(AN14="TEC Rejected","",IF(AN14="","",ROUND(1.3224*Form!$D$10*AN14,2)))) | AP14: =IF(AM14="","",IF(AN14="TEC Rejected","",IF(AN14="","",ROUND(AM14*AO14,2)))) | AQ14: =IF(AR14="","",IF('CST-Calculation'!$F14="Indg","",IF('CST-Calculation'!$F14="TEC Del","",IF('CST-Calculation'!AQ14>0,'CST-Calculation'!AQ14,IF('CST-Calculation'!$F14=0,"",'CST-Calculation'!$F14))))) | AR14: =IF('CST-Calculation'!AR14=0,"",'CST-Calculation'!AR14) | AS14: =IF(AQ14="","",IF(AR14="TEC Rejected","",IF(AR14="","",ROUND(1.3224*Form!$D$10*AR14,2)))) | AT14: =IF(AQ14="","",IF(AR14="TEC Rejected","",IF(AR14="","",ROUND(AQ14*AS14,2)))) | AU14: =IF(AV14="","",IF('CST-Calculation'!$F14="Indg","",IF('CST-Calculation'!$F14="TEC Del","",IF('CST-Calculation'!AU14>0,'CST-Calculation'!AU14,IF('CST-Calculation'!$F14=0,"",'CST-Calculation'!$F14))))) | AV14: =IF('CST-Calculation'!AV14=0,"",'CST-Calculation'!AV14) | AW14: =IF(AU14="","",IF(AV14="TEC Rejected","",IF(AV14="","",ROUND(1.3224*Form!$D$10*AV14,2)))) | AX14: =IF(AU14="","",IF(AV14="TEC Rejected","",IF(AV14="","",ROUND(AU14*AW14,2)))) | AY14: =IF(F14="Indg","INDG",IF(F14="TEC Del","DELETED",IF(F14=0,"DELETED",IF(BD14=0,"NO OFFER",IF(BD14=I14,$H$3,IF(BD14=M14,$L$3,IF(BD14=Q14,$P$3,IF(BD14=U14,$T$3,IF(BD14=Y14,$X$3,IF(BD14=AC14,$AB$3,IF(BD14=AG14,$AF$3,IF(BD14=AK14,$AJ$3,IF(BD14=AO14,$AN$3,IF(BD14=AS14,$AR$3,IF(BD14=AW14,$AV$3))))))))))))))) -> GIS | AZ14: =IF(F14=0,"DELETED",IF(COUNT(H14,L14,P14,T14,X14,AB14,AF14,AJ14,AN14,AR14,AV14)=0,"NO OFFER",IF(COUNT(H14,L14,P14,T14,X14,AB14,AF14,AJ14,AN14,AR14,AV14)=1,"SINGLE","MULTIPLE"))) -> MULTIPLE | BA14: =IF(AND(IF(G14="",TRUE,G14<=ROUNDUP(1.2*F14,0)),IF(K14="",TRUE,K14<=ROUNDUP(1.2*F14,0)),IF(O14="",TRUE,O14<=ROUNDUP(1.2*F14,0)),IF(S14="",TRUE,S14<=ROUNDUP(1.2*F14,0)),IF(W14="",TRUE,W14<=ROUNDUP(1.2*F14,0)),IF(AA14="",TRUE,AA14<=ROUNDUP(1.2*F14,0)),IF(AE14="",TRUE,AE14<=ROUNDUP(1.2*F14,0)),IF(AI14="",TRUE,AI14<=ROUNDUP(1.2*F14,0)),IF(AM14="",TRUE,AM14<=ROUNDUP(1.2*F14,0)),IF(AQ14="",TRUE,AQ14<=ROUNDUP(1.2*F14,0)),IF(AU14="",TRUE,AU14<=ROUNDUP(1.2*F14,0))),"<= 20%","> 20%") -> <= 20% | BB14: =IF(AY14="EST",ROUND(BD14/1.18,2),IF(AY14="ADRYS",ROUND(BD14/1.18,2),ROUND(BD14/(1.3224*Form!$D$10),2))) -> 7.5 | BC14: =IF(OR(AY14="EST",AY14="ADRYS"),ROUND(BE14/1.18,2),ROUND(BE14/(1.3224*Form!$D$10),2)) -> 225 | BD14: =IF(F14="Indg",0,IF(F14="TEC Del",0,IF(AND(IF(G14="",TRUE,G14<=ROUNDUP(1.2*F14,0)),IF(K14="",TRUE,K14<=ROUNDUP(1.2*F14,0)),IF(O14="",TRUE,O14<=ROUNDUP(1.2*F14,0)),IF(S14="",TRUE,S14<=ROUNDUP(1.2*F14,0)),IF(W14="",TRUE,W14<=ROUNDUP(1.2*F14,0)),IF(AA14="",TRUE,AA14<=ROUNDUP(1.2*F14,0)),IF(AE14="",TRUE,AE14<=ROUNDUP(1.2*F14,0)),IF(AI14="",TRUE,AI14<=ROUNDUP(1.2*F14,0)),IF(AM14="",TRUE,AM14<=ROUNDUP(1.2*F14,0)),IF(AQ14="",TRUE,AQ14<=ROUNDUP(1.2*F14,0)),IF(AU14="",TRUE,AU14<=ROUNDUP(1.2*F14,0))),IF(F14=0,0,(IF(SUM(I14,M14,Q14,U14,Y14,AC14,AG14,AK14,AO14,AS14,AW14)=0,0,SMALL((I14,M14,Q14,U14,Y14,AC14,AG14,AK14,AO14,AS14,AW14),COUNTIF((I14:AW14),0)+1)))),IF(BE14=J14,I14,IF(BE14=N14,M14,IF(BE14=R14,Q14,IF(BE14=V14,U14,IF(BE14=Z14,Y14,IF(BE14=AD14,AC14,IF(BE14=AH14,AG14,IF(BE14=AL14,AK14,IF(BE14=AP14,AO14,IF(BE14=AT14,AS14,IF(BE14=AX14,AW14)))))))))))))) -> 821.01 | BE14: =IF(F14="Indg",0,IF(F14="TEC Del",0,IF(AND(IF(G14="",TRUE,G14<=ROUNDUP(1.2*F14,0)),IF(K14="",TRUE,K14<=ROUNDUP(1.2*F14,0)),IF(O14="",TRUE,O14<=ROUNDUP(1.2*F14,0)),IF(S14="",TRUE,S14<=ROUNDUP(1.2*F14,0)),IF(W14="",TRUE,W14<=ROUNDUP(1.2*F14,0)),IF(AA14="",TRUE,AA14<=ROUNDUP(1.2*F14,0)),IF(AE14="",TRUE,AE14<=ROUNDUP(1.2*F14,0)),IF(AI14="",TRUE,AI14<=ROUNDUP(1.2*F14,0)),IF(AM14="",TRUE,AM14<=ROUNDUP(1.2*F14,0)),IF(AQ14="",TRUE,AQ14<=ROUNDUP(1.2*F14,0)),IF(AU14="",TRUE,AU14<=ROUNDUP(1.2*F14,0))),ROUND(BD14*IF(BD14=I14,G14,IF(BD14=M14,K14,IF(BD14=Q14,O14,IF(BD14=U14,S14,IF(BD14=Y14,W14,IF(BD14=AC14,AA14,IF(BD14=AG14,AE14,IF(BD14=AK14,AI14,IF(BD14=AO14,AM14,IF(BD14=AS14,AQ14,IF(BD14=AW14,AU14))))))))))),2),(IF(SUM(J14,N14,R14,V14,Z14,AD14,AH14,AL14,AP14,AT14,AX14)=0,0,SMALL((J14,N14,R14,V14,Z14,AD14,AH14,AL14,AP14,AT14,AX14),COUNTIF((J14:AX14),0)+1)))))) -> 24630.3 | BF14: =IF('Annexure-I'!L11="",'Annexure-I'!F11,'Annexure-I'!L11) -> 18.81 | BG14: =IF('Annexure-I'!M11="",'Annexure-I'!G11,'Annexure-I'!M11) -> CONTRACT-A10 | BH14: =IF('Annexure-I'!N11="",'Annexure-I'!H11,'Annexure-I'!N11) -> 41891 | BI14: =IF('Annexure-I'!P11="",'Annexure-I'!J11,'Annexure-I'!P11) -> 30.96 | BJ14: =IF('Annexure-I'!Q11="",'Annexure-I'!K11,'Annexure-I'!Q11) -> 3389.1377 | BK14: ='Annexure-I'!F11 -> 18.81 | BL14: ='Annexure-I'!G11 -> CONTRACT-A10 | BM14: =IF('Annexure-I'!H11=0,"",'Annexure-I'!H11) -> 41891 | BN14: ='Annexure-I'!J11 -> 30.96 | BO14: ='Annexure-I'!K11 -> 3389.1377 | BP14: =IF(OR(AY14="EST",AY14="ADRYS"),ROUND((BC14*1.18)/(1.3224*Form!$D$10),2),BC14) -> 225 | BQ14: =ROUND(BS14/(1.3224*Form!$D$10),2) -> 928.8 | BR14: =IF(AY14="DELETED",0,BE14) -> 24630.3 | BS14: =IF(BR14=0,0,ROUND(IF($BQ$1="LPP",ROUND(BJ14*F14,2),ROUND(BO14*F14,2)),2)) -> 101674.13 | BT14: =IF(SUM(BR14:BS14)=0,0,(BR14-BS14)/BS14) -> -0.75775254 | BV14: =IF(F14="Indg",0,IF(F14="TEC Del",0,IF(CA14="Deleted",0,ROUND(F14*BU14,2)))) -> 0 | BW14: =IF(OR(AY14="EST",AY14="ADRYS"),ROUND(1.18*BU14,2),ROUND(BU14*1.3224*Form!$D$10,2)) -> 0 | BX14: =IF(F14="Indg",0,IF(F14="TEC Del",0,IF(CA14="Deleted",0,ROUND(BW14*F14,2)))) -> 0 | BY14: =IF((BX14)=0,0,(BX14-BS14)/BS14) -> 0 | BZ14: =IF(CA14="Deleted",0,ROUND(BO14*F14,2)) -> 101674.13
